Workbook

Sheet README
A1: README
A2: Índice | B2: Información general
A3: Cartera | B3: En esta hoja encuentra Cartera bruta y vencida, leasing y NPL. El NPL Se construye tomando la metodología de construcción de los indicadores gerenciales de la superfinanciera. La cartera vencida contempla el capital en mora mayor a 1 mes en las carteras de consumo y comercial. En la cartera de vivienda, se toma el capital en mora mayor a 4 meses (Fuente: metodología IG y catalogo unico de cuentas SFC.) Para carteras, la fuente son indicadores gerenciales y se toma el total de establecimientos de crèdito sin IOE's (que corresponde a la columna D en el IG). La cartera de vivienda incluye credito y leasing habitacional (puede corroborarse en la fila 69 del IG, en donde se observa el nombre, y es el mismo dato que traemos desde la fila D522 para este archivo). La cartera de consumo incluye credito y leasing de consumo (puede corroborarse en la fila 67 del IG, en donde se observa el nombre, y es el mismo dato que traemos desde la fila D505 para este archivo). La cartera comercial incluye credito y leasing (puede corroborarse en la fila 66 del IG, en donde se observa el nombre, y es el mismo dato que traemos desde la fila D596 para este archivo). Para QRES: se toma la cartera de consumo, comercial y vivienda con titularizaciones. La cartera total que se trabaja y envìa a España corresponde a la suma de estas tres carteras. NO se incluye microcredito en la suma de la total. El archivo cuenta tambièn con los datos de leasing habitacional de bancos y el leasing de compañìas de financiamiento. Estos se obtienen de Datos abiertos. Disclaimer: Es posible que en algún archivo previo de datos de cartera, cómo históricos de algún envío por QRES o a financiera u otro repositorio, se encuentren diferencias en las cifras respecto a las que figuran en este archivo. Esto se explica porque esas cifras provenían de un archivo anterior a este (llamado depositos y cartera), en el que se encontraron errores que fueron corregidos, y cuya corrección llevó a la construcción de este archivo, que es el repositorio oficial. Las diferencias en vivienda se explican por unos cálculos relacionados con leasing y algunas formulas malas que se encontraron en el archivo anterior. Las diferencias en consumo que se pueden encontrar, se deben a que la formula estaba mal hecha y no se traía la cartera de EC sin IOE's sino del total del sector privado (se estaba trayendo la columna E cuando se debía traer la D).
A4: Depósitos | B4: En esta hoja encuentra los depósitos vista, plazo y total, junto con la relación crédito a depósitos. Los depósitos se obtienen de los indicadores gerenciales de la SFC. Los recursos plazo contienen unicamente certificados de depósito a término. Los recursos vista contienen unicamente depositos en cuenta corriente y depositos de ahorro
A5: Titularizaciones | B5: En esta hoja encuentra las titularizaciones por saldo, por tipo y el indicador de calidad. *Indicador de calidad tradicional: Cartera Vencida / Cartera Bruta. La cartera vencida de vivienda en el plazo de 1 a 4 meses sólo incluye las cuotas vencidas. El capital no incluido en la cuotas de 1 a 4 meses se considera vigente.
A6: Profundización financiera | B6: En esta hoja encuentra la relación cartera a PIB. La cartera total en este cálculo incluye microcrédito. PIB tomado de escenariobase; hoja sup, fila 3

Sheet Cartera
D1: Miles de millones de pesos | V1: Variación anual (Porcentaje) | AN1: Variación real (Porcentaje) | BF1: Porcentaje | BN1: Porcentaje | CB1: Porcentaje
B2: Inflación | D2: Cartera comercial y leasing comercial | F2: Cartera consumo y leasing de consumo | H2: Cartera hipotecaria y operaciones de leasing habitacional | J2: Cartera microcrédito y leasing de microcredito | L2: Cartera hipotecaria con titularizaciones | N2: Cartera Total | P2: Cartera total con titularizaciones | R2: Cartera total con titularizaciones sin microcredito | T2: Leasing habitacional de bancos (AI) | U2: Leasing de compañías de financiamiento comercial (FR) | V2: Cartera comercial | X2: Cartera consumo | Z2: Cartera hipotecario | AB2: Cartera microcrédito | AD2: Cartera hipotecaria con titularizaciones | AF2: cartera total | AH2: cartera total con titularizaciones | AJ2: Cartera total con titularizaciones sin microcredito | AL2: Leasing habitacional de bancos (AI) | AM2: Leasing de compañías de financiamiento comercial (FR) | AN2: Cartera comercial | AP2: Cartera consumo | AR2: Cartera hipotecario | AT2: Cartera microcrédito | AV2: Cartera hipotecaria con titularizaciones | AX2: cartera total | AZ2: cartera total con titularizaciones | BB2: cartera total con titularizaciones sin microcredito | BD2: Leasing habitacional de bancos (AI) | BE2: Leasing de compañías de financiamiento comercial (FR) | BF2: Non Performing Loans - NPL | BN2: Participación sobre el total Cartera comercial | BP2: Participación sobre el total Cartera consumo | BR2: Participación sobre el total Cartera hipotecario | BT2: Participación sobre el total Cartera microcrédito | BV2: Participación sobre el total Cartera hipotecaria con titularizaciones | BX2: Participación sobre el total cartera total | BZ2: Participación sobre el total cartera total con titularizaciones | CB2: Contribucion al cambio Cartera comercial | CD2: Contribucion al cambio Cartera consumo | CF2: Contribucion al cambio Cartera hipotecario | CH2: Contribucion al cambio Cartera microcrédito | CJ2: Contribucion al cambio Cartera hipotecaria con titularizaciones | CL2: Contribucion al cambio cartera total | CN2: Contribucion al cambio cartera total con titularizaciones
A3: Fecha | B3: Inflación | C3: IPC | D3: Bruta | E3: Vencida | F3: Bruta | G3: Vencida | H3: Bruta | I3: Vencida | J3: Bruta | K3: Vencida | L3: Bruta | M3: Vencida | N3: Bruta | O3: Vencida | P3: Bruta | Q3: Vencida | R3: Bruta | S3: Vencida | T3: Bruta | U3: Bruta | V3: Bruta | W3: Vencida | X3: Bruta | Y3: Vencida | Z3: Bruta | AA3: Vencida | AB3: Bruta | AC3: Vencida | AD3: Bruta | AE3: Vencida | AF3: Bruta | AG3: Vencida | AH3: Bruta | AI3: Vencida | AJ3: Bruta | AK3: Vencida | AL3: Bruta | AM3: Bruta | AN3: Bruta | AO3: Vencida | AP3: Bruta | AQ3: Vencida | AR3: Bruta | AS3: Vencida | AT3: Bruta | AU3: Vencida | AV3: Bruta | AW3: Vencida | AX3: Bruta | AY3: Vencida | AZ3: Bruta | BA3: Vencida | BB3: Bruta | BC3: Vencida | BD3: Bruta | BE3: Bruta | BF3: Comercial | BG3: Consumo | BH3: Hipotecario | BI3: Microcredito | BJ3: Hipotecario con titularizaciones | BK3: Total | BL3: Total con titularizaciones | BM3: Total con titularizaciones sin microcredito | BN3: Bruta | BO3: Vencida | BP3: Bruta | BQ3: Vencida | BR3: Bruta | BS3: Vencida | BT3: Bruta | BU3: Vencida | BV3: Bruta | BW3: Vencida | BX3: Bruta | BY3: Vencida | BZ3: Bruta | CA3: Vencida | CB3: Bruta | CC3: Vencida | CD3: Bruta | CE3: Vencida | CF3: Bruta | CG3: Vencida | CH3: Bruta | CI3: Vencida | CJ3: Bruta | CK3: Vencida | CL3: Bruta | CM3: Vencida | CN3: Bruta | CO3: Vencida
A4: 34669 | B4: =+'[1]Senda Inflación Total'!F488 -> 22.59 | C4: =+'[1]Senda Inflación Total'!D488 -> 18.25 | D4: 11084.163 | E4: 411.16814 | F4: 5413.4141 | G4: 538.74159 | H4: 5157.5407 | I4: 177.5518 | L4: =+H4 -> 5157.5407 | M4: =+I4 -> 177.5518 | N4: =+D4+F4+H4+J4 -> 21655.117 | O4: =+E4+G4+I4+K4 -> 1127.4615 | P4: =+L4+J4+F4+D4 -> 21655.117 | Q4: =+M4+K4+G4+E4 -> 1127.4615 | R4: =+D4+F4+L4 -> 21655.117 | S4: =+E4+G4+M4 -> 1127.4615 | BF4: =+(E4/D4)*100 -> 3.7095101 | BG4: =+(G4/F4)*100 -> 9.9519744 | BH4: =+(I4/H4)*100 -> 3.4425671 | BJ4: =+(M4/L4)*100 -> 3.4425671 | BK4: =+(O4/N4)*100 -> 5.2064438 | BL4: =+(Q4/P4)*100 -> 5.2064438 | BM4: =+(S4/R4)*100 -> 5.2064438 | BN4: =+(D4/$N4)*100 -> 51.184958 | BO4: =+(E4/$O4)*100 -> 36.468485 | BP4: =+(F4/$N4)*100 -> 24.998313 | BQ4: =+(G4/$O4)*100 -> 47.78359 | BR4: =+(H4/$N4)*100 -> 23.816729 | BS4: =+(I4/$O4)*100 -> 15.747925 | BT4: =+(J4/$N4)*100 -> 0 | BU4: =+(K4/$O4)*100 -> 0 | BV4: ND | BW4: ND | BX4: =+(N4/$N4)*100 -> 100 | BY4: =+(O4/$O4)*100 -> 100 | BZ4: ND | CA4: ND
A5: 34700 | B5: =+'[1]Senda Inflación Total'!F489 -> 21.04 | C5: =+'[1]Senda Inflación Total'!D489 -> 18.59 | D5: 11234.422 | E5: 477.61451 | F5: 5645.6336 | G5: 625.27143 | H5: 5363.6298 | I5: 178.73763 | L5: =+H5 -> 5363.6298 | M5: =+I5 -> 178.73763 | N5: =+D5+F5+H5+J5 -> 22243.685 | O5: =+E5+G5+I5+K5 -> 1281.6236 | P5: =+L5+J5+F5+D5 -> 22243.685 | Q5: =+M5+K5+G5+E5 -> 1281.6236 | R5: =+D5+F5+L5 -> 22243.685 | S5: =+E5+G5+M5 -> 1281.6236 | BF5: =+(E5/D5)*100 -> 4.2513493 | BG5: =+(G5/F5)*100 -> 11.07531 | BH5: =+(I5/H5)*100 -> 3.3324006 | BJ5: =+(M5/L5)*100 -> 3.3324006 | BK5: =+(O5/N5)*100 -> 5.7617412 | BL5: =+(Q5/P5)*100 -> 5.7617412 | BM5: =+(S5/R5)*100 -> 5.7617412 | BN5: =+(D5/$N5)*100 -> 50.506118 | BO5: =+(E5/$O5)*100 -> 37.266364 | BP5: =+(F5/$N5)*100 -> 25.380838 | BQ5: =+(G5/$O5)*100 -> 48.787448 | BR5: =+(H5/$N5)*100 -> 24.113045 | BS5: =+(I5/$O5)*100 -> 13.946188 | BT5: =+(J5/$N5)*100 -> 0 | BU5: =+(K5/$O5)*100 -> 0 | BV5: ND | BW5: ND | BX5: =+(N5/$N5)*100 -> 100 | BY5: =+(O5/$O5)*100 -> 100 | BZ5: ND | CA5: ND
A6: 34731 | B6: =+'[1]Senda Inflación Total'!F490 -> 20.86 | C6: =+'[1]Senda Inflación Total'!D490 -> 19.24 | D6: 11507.894 | E6: 511.89638 | F6: 5714.4183 | G6: 664.79526 | H6: 5523.703 | I6: 188.2036 | L6: =+H6 -> 5523.703 | M6: =+I6 -> 188.2036 | N6: =+D6+F6+H6+J6 -> 22746.015 | O6: =+E6+G6+I6+K6 -> 1364.8952 | P6: =+L6+J6+F6+D6 -> 22746.015 | Q6: =+M6+K6+G6+E6 -> 1364.8952 | R6: =+D6+F6+L6 -> 22746.015 | S6: =+E6+G6+M6 -> 1364.8952 | BF6: =+(E6/D6)*100 -> 4.4482194 | BG6: =+(G6/F6)*100 -> 11.633647 | BH6: =+(I6/H6)*100 -> 3.4071998 | BJ6: =+(M6/L6)*100 -> 3.4071998 | BK6: =+(O6/N6)*100 -> 6.0005905 | BL6: =+(Q6/P6)*100 -> 6.0005905 | BM6: =+(S6/R6)*100 -> 6.0005905 | BN6: =+(D6/$N6)*100 -> 50.593011 | BO6: =+(E6/$O6)*100 -> 37.504445 | BP6: =+(F6/$N6)*100 -> 25.122722 | BQ6: =+(G6/$O6)*100 -> 48.706688 | BR6: =+(H6/$N6)*100 -> 24.284267 | BS6: =+(I6/$O6)*100 -> 13.788868 | BT6: =+(J6/$N6)*100 -> 0 | BU6: =+(K6/$O6)*100 -> 0 | BV6: ND | BW6: ND | BX6: =+(N6/$N6)*100 -> 100 | BY6: =+(O6/$O6)*100 -> 100 | BZ6: ND | CA6: ND
A7: 34759 | B7: =+'[1]Senda Inflación Total'!F491 -> 21.33 | C7: =+'[1]Senda Inflación Total'!D491 -> 19.75 | D7: 12066.986 | E7: 509.42083 | F7: 5828.1441 | G7: 634.7998 | H7: 5725.0241 | I7: 194.02646 | L7: =+H7 -> 5725.0241 | M7: =+I7 -> 194.02646 | N7: =+D7+F7+H7+J7 -> 23620.154 | O7: =+E7+G7+I7+K7 -> 1338.2471 | P7: =+L7+J7+F7+D7 -> 23620.154 | Q7: =+M7+K7+G7+E7 -> 1338.2471 | R7: =+D7+F7+L7 -> 23620.154 | S7: =+E7+G7+M7 -> 1338.2471 | BF7: =+(E7/D7)*100 -> 4.2216078 | BG7: =+(G7/F7)*100 -> 10.891972 | BH7: =+(I7/H7)*100 -> 3.3890942 | BJ7: =+(M7/L7)*100 -> 3.3890942 | BK7: =+(O7/N7)*100 -> 5.6657 | BL7: =+(Q7/P7)*100 -> 5.6657 | BM7: =+(S7/R7)*100 -> 5.6657 | BN7: =+(D7/$N7)*100 -> 51.087669 | BO7: =+(E7/$O7)*100 -> 38.066276 | BP7: =+(F7/$N7)*100 -> 24.674454 | BQ7: =+(G7/$O7)*100 -> 47.435171 | BR7: =+(H7/$N7)*100 -> 24.237877 | BS7: =+(I7/$O7)*100 -> 14.498553 | BT7: =+(J7/$N7)*100 -> 0 | BU7: =+(K7/$O7)*100 -> 0 | BV7: ND | BW7: ND | BX7: =+(N7/$N7)*100 -> 100 | BY7: =+(O7/$O7)*100 -> 100 | BZ7: ND | CA7: ND
A8: 34790 | B8: =+'[1]Senda Inflación Total'!F492 -> 21.17 | C8: =+'[1]Senda Inflación Total'!D492 -> 20.19 | D8: 12371.751 | E8: 531.89046 | F8: 5970.7464 | G8: 704.00344 | H8: 5877.3538 | I8: 205.80512 | L8: =+H8 -> 5877.3538 | M8: =+I8 -> 205.80512 | N8: =+D8+F8+H8+J8 -> 24219.851 | O8: =+E8+G8+I8+K8 -> 1441.699 | P8: =+L8+J8+F8+D8 -> 24219.851 | Q8: =+M8+K8+G8+E8 -> 1441.699 | R8: =+D8+F8+L8 -> 24219.851 | S8: =+E8+G8+M8 -> 1441.699 | BF8: =+(E8/D8)*100 -> 4.2992336 | BG8: =+(G8/F8)*100 -> 11.790878 | BH8: =+(I8/H8)*100 -> 3.5016629 | BJ8: =+(M8/L8)*100 -> 3.5016629 | BK8: =+(O8/N8)*100 -> 5.9525512 | BL8: =+(Q8/P8)*100 -> 5.9525512 | BM8: =+(S8/R8)*100 -> 5.9525512 | BN8: =+(D8/$N8)*100 -> 51.081036 | BO8: =+(E8/$O8)*100 -> 36.893308 | BP8: =+(F8/$N8)*100 -> 24.652284 | BQ8: =+(G8/$O8)*100 -> 48.831513 | BR8: =+(H8/$N8)*100 -> 24.26668 | BS8: =+(I8/$O8)*100 -> 14.275179 | BT8: =+(J8/$N8)*100 -> 0 | BU8: =+(K8/$O8)*100 -> 0 | BV8: ND | BW8: ND | BX8: =+(N8/$N8)*100 -> 100 | BY8: =+(O8/$O8)*100 -> 100 | BZ8: ND | CA8: ND
A9: 34820 | B9: =+'[1]Senda Inflación Total'!F493 -> 21.3 | C9: =+'[1]Senda Inflación Total'!D493 -> 20.52 | D9: 12803.208 | E9: 533.74045 | F9: 6077.1305 | G9: 722.78708 | H9: 6057.1458 | I9: 199.86292 | L9: =+H9 -> 6057.1458 | M9: =+I9 -> 199.86292 | N9: =+D9+F9+H9+J9 -> 24937.485 | O9: =+E9+G9+I9+K9 -> 1456.3905 | P9: =+L9+J9+F9+D9 -> 24937.485 | Q9: =+M9+K9+G9+E9 -> 1456.3905 | R9: =+D9+F9+L9 -> 24937.485 | S9: =+E9+G9+M9 -> 1456.3905 | BF9: =+(E9/D9)*100 -> 4.1688023 | BG9: =+(G9/F9)*100 -> 11.893559 | BH9: =+(I9/H9)*100 -> 3.2996221 | BJ9: =+(M9/L9)*100 -> 3.2996221 | BK9: =+(O9/N9)*100 -> 5.8401658 | BL9: =+(Q9/P9)*100 -> 5.8401658 | BM9: =+(S9/R9)*100 -> 5.8401658 | BN9: =+(D9/$N9)*100 -> 51.341218 | BO9: =+(E9/$O9)*100 -> 36.64817 | BP9: =+(F9/$N9)*100 -> 24.369461 | BQ9: =+(G9/$O9)*100 -> 49.628661 | BR9: =+(H9/$N9)*100 -> 24.289321 | BS9: =+(I9/$O9)*100 -> 13.723169 | BT9: =+(J9/$N9)*100 -> 0 | BU9: =+(K9/$O9)*100 -> 0 | BV9: ND | BW9: ND | BX9: =+(N9/$N9)*100 -> 100 | BY9: =+(O9/$O9)*100 -> 100 | BZ9: ND | CA9: ND
A10: 34851 | B10: =+'[1]Senda Inflación Total'!F494 -> 21.66 | C10: =+'[1]Senda Inflación Total'!D494 -> 20.77 | D10: 13231.281 | E10: 529.12972 | F10: 6141.0301 | G10: 699.14152 | H10: 6230.9789 | I10: 217.34537 | L10: =+H10 -> 6230.9789 | M10: =+I10 -> 217.34537 | N10: =+D10+F10+H10+J10 -> 25603.29 | O10: =+E10+G10+I10+K10 -> 1445.6166 | P10: =+L10+J10+F10+D10 -> 25603.29 | Q10: =+M10+K10+G10+E10 -> 1445.6166 | R10: =+D10+F10+L10 -> 25603.29 | S10: =+E10+G10+M10 -> 1445.6166 | BF10: =+(E10/D10)*100 -> 3.9990817 | BG10: =+(G10/F10)*100 -> 11.38476 | BH10: =+(I10/H10)*100 -> 3.4881416 | BI10: =+(K10/J10)*100 -> #DIV/0! | BJ10: =+(M10/L10)*100 -> 3.4881416 | BK10: =+(O10/N10)*100 -> 5.6462144 | BL10: =+(Q10/P10)*100 -> 5.6462144 | BM10: =+(S10/R10)*100 -> 5.6462144 | BN10: =+(D10/$N10)*100 -> 51.678049 | BO10: =+(E10/$O10)*100 -> 36.602355 | BP10: =+(F10/$N10)*100 -> 23.985317 | BQ10: =+(G10/$O10)*100 -> 48.362859 | BR10: =+(H10/$N10)*100 -> 24.336634 | BS10: =+(I10/$O10)*100 -> 15.034786 | BT10: =+(J10/$N10)*100 -> 0 | BU10: =+(K10/$O10)*100 -> 0 | BV10: ND | BW10: ND | BX10: =+(N10/$N10)*100 -> 100 | BY10: =+(O10/$O10)*100 -> 100 | BZ10: ND | CA10: ND
A11: 34881 | B11: =+'[1]Senda Inflación Total'!F495 -> 21.5 | C11: =+'[1]Senda Inflación Total'!D495 -> 20.93 | D11: 13740.455 | E11: 641.29952 | F11: 6227.5415 | G11: 780.72466 | H11: 6271.7224 | I11: 212.57915 | L11: =+H11 -> 6271.7224 | M11: =+I11 -> 212.57915 | N11: =+D11+F11+H11+J11 -> 26239.719 | O11: =+E11+G11+I11+K11 -> 1634.6033 | P11: =+L11+J11+F11+D11 -> 26239.719 | Q11: =+M11+K11+G11+E11 -> 1634.6033 | R11: =+D11+F11+L11 -> 26239.719 | S11: =+E11+G11+M11 -> 1634.6033 | BF11: =+(E11/D11)*100 -> 4.6672365 | BG11: =+(G11/F11)*100 -> 12.536643 | BH11: =+(I11/H11)*100 -> 3.3894859 | BI11: =+(K11/J11)*100 -> #DIV/0! | BJ11: =+(M11/L11)*100 -> 3.3894859 | BK11: =+(O11/N11)*100 -> 6.2295002 | BL11: =+(Q11/P11)*100 -> 6.2295002 | BM11: =+(S11/R11)*100 -> 6.2295002 | BN11: =+(D11/$N11)*100 -> 52.365099 | BO11: =+(E11/$O11)*100 -> 39.232731 | BP11: =+(F11/$N11)*100 -> 23.733263 | BQ11: =+(G11/$O11)*100 -> 47.762331 | BR11: =+(H11/$N11)*100 -> 23.901638 | BS11: =+(I11/$O11)*100 -> 13.004938 | BT11: =+(J11/$N11)*100 -> 0 | BU11: =+(K11/$O11)*100 -> 0 | BV11: ND | BW11: ND | BX11: =+(N11/$N11)*100 -> 100 | BY11: =+(O11/$O11)*100 -> 100 | BZ11: ND | CA11: ND
A12: 34912 | B12: =+'[1]Senda Inflación Total'!F496 -> 21.09 | C12: =+'[1]Senda Inflación Total'!D496 -> 21.07 | D12: 14246.975 | E12: 662.50681 | F12: 6325.7462 | G12: 785.93739 | H12: 6496.9663 | I12: 224.67818 | L12: =+H12 -> 6496.9663 | M12: =+I12 -> 224.67818 | N12: =+D12+F12+H12+J12 -> 27069.687 | O12: =+E12+G12+I12+K12 -> 1673.1224 | P12: =+L12+J12+F12+D12 -> 27069.687 | Q12: =+M12+K12+G12+E12 -> 1673.1224 | R12: =+D12+F12+L12 -> 27069.687 | S12: =+E12+G12+M12 -> 1673.1224 | BF12: =+(E12/D12)*100 -> 4.6501578 | BG12: =+(G12/F12)*100 -> 12.424422 | BH12: =+(I12/H12)*100 -> 3.4582014 | BI12: =+(K12/J12)*100 -> #DIV/0! | BJ12: =+(M12/L12)*100 -> 3.4582014 | BK12: =+(O12/N12)*100 -> 6.1807969 | BL12: =+(Q12/P12)*100 -> 6.1807969 | BM12: =+(S12/R12)*100 -> 6.1807969 | BN12: =+(D12/$N12)*100 -> 52.630733 | BO12: =+(E12/$O12)*100 -> 39.597032 | BP12: =+(F12/$N12)*100 -> 23.368376 | BQ12: =+(G12/$O12)*100 -> 46.974292 | BR12: =+(H12/$N12)*100 -> 24.000892 | BS12: =+(I12/$O12)*100 -> 13.428676 | BT12: =+(J12/$N12)*100 -> 0 | BU12: =+(K12/$O12)*100 -> 0 | BV12: ND | BW12: ND | BX12: =+(N12/$N12)*100 -> 100 | BY12: =+(O12/$O12)*100 -> 100 | BZ12: ND | CA12: ND
A13: 34943 | B13: =+'[1]Senda Inflación Total'!F497 -> 20.79 | C13: =+'[1]Senda Inflación Total'!D497 -> 21.24 | D13: 14763.526 | E13: 649.97139 | F13: 6472.4305 | G13: 779.23711 | H13: 6687.4221 | I13: 227.71376 | L13: =+H13 -> 6687.4221 | M13: =+I13 -> 227.71376 | N13: =+D13+F13+H13+J13 -> 27923.379 | O13: =+E13+G13+I13+K13 -> 1656.9223 | P13: =+L13+J13+F13+D13 -> 27923.379 | Q13: =+M13+K13+G13+E13 -> 1656.9223 | R13: =+D13+F13+L13 -> 27923.379 | S13: =+E13+G13+M13 -> 1656.9223 | BF13: =+(E13/D13)*100 -> 4.4025483 | BG13: =+(G13/F13)*100 -> 12.039328 | BH13: =+(I13/H13)*100 -> 3.4051052 | BI13: =+(K13/J13)*100 -> #DIV/0! | BJ13: =+(M13/L13)*100 -> 3.4051052 | BK13: =+(O13/N13)*100 -> 5.9338172 | BL13: =+(Q13/P13)*100 -> 5.9338172 | BM13: =+(S13/R13)*100 -> 5.9338172 | BN13: =+(D13/$N13)*100 -> 52.871561 | BO13: =+(E13/$O13)*100 -> 39.227633 | BP13: =+(F13/$N13)*100 -> 23.179252 | BQ13: =+(G13/$O13)*100 -> 47.02919 | BR13: =+(H13/$N13)*100 -> 23.949186 | BS13: =+(I13/$O13)*100 -> 13.743177 | BT13: =+(J13/$N13)*100 -> 0 | BU13: =+(K13/$O13)*100 -> 0 | BV13: ND | BW13: ND | BX13: =+(N13/$N13)*100 -> 100 | BY13: =+(O13/$O13)*100 -> 100 | BZ13: ND | CA13: ND
A14: 34973 | B14: =+'[1]Senda Inflación Total'!F498 -> 20.52 | C14: =+'[1]Senda Inflación Total'!D498 -> 21.43 | D14: 15161.709 | E14: 703.51071 | F14: 6591.4236 | G14: 797.70905 | H14: 6895.5346 | I14: 236.63223 | L14: =+H14 -> 6895.5346 | M14: =+I14 -> 236.63223 | N14: =+D14+F14+H14+J14 -> 28648.667 | O14: =+E14+G14+I14+K14 -> 1737.852 | P14: =+L14+J14+F14+D14 -> 28648.667 | Q14: =+M14+K14+G14+E14 -> 1737.852 | R14: =+D14+F14+L14 -> 28648.667 | S14: =+E14+G14+M14 -> 1737.852 | BF14: =+(E14/D14)*100 -> 4.6400489 | BG14: =+(G14/F14)*100 -> 12.102227 | BH14: =+(I14/H14)*100 -> 3.4316735 | BI14: =+(K14/J14)*100 -> #DIV/0! | BJ14: =+(M14/L14)*100 -> 3.4316735 | BK14: =+(O14/N14)*100 -> 6.0660832 | BL14: =+(Q14/P14)*100 -> 6.0660832 | BM14: =+(S14/R14)*100 -> 6.0660832 | BN14: =+(D14/$N14)*100 -> 52.922912 | BO14: =+(E14/$O14)*100 -> 40.481624 | BP14: =+(F14/$N14)*100 -> 23.007785 | BQ14: =+(G14/$O14)*100 -> 45.902013 | BR14: =+(H14/$N14)*100 -> 24.069303 | BS14: =+(I14/$O14)*100 -> 13.616363 | BT14: =+(J14/$N14)*100 -> 0 | BU14: =+(K14/$O14)*100 -> 0 | BV14: ND | BW14: ND | BX14: =+(N14/$N14)*100 -> 100 | BY14: =+(O14/$O14)*100 -> 100 | BZ14: ND | CA14: ND
A15: 35004 | B15: =+'[1]Senda Inflación Total'!F499 -> 20.13 | C15: =+'[1]Senda Inflación Total'!D499 -> 21.6 | D15: 15643.495 | E15: 725.00084 | F15: 6690.6695 | G15: 828.64086 | H15: 7049.7487 | I15: 250.81978 | L15: =+H15 -> 7049.7487 | M15: =+I15 -> 250.81978 | N15: =+D15+F15+H15+J15 -> 29383.913 | O15: =+E15+G15+I15+K15 -> 1804.4615 | P15: =+L15+J15+F15+D15 -> 29383.913 | Q15: =+M15+K15+G15+E15 -> 1804.4615 | R15: =+D15+F15+L15 -> 29383.913 | S15: =+E15+G15+M15 -> 1804.4615 | BF15: =+(E15/D15)*100 -> 4.6345197 | BG15: =+(G15/F15)*100 -> 12.385022 | BH15: =+(I15/H15)*100 -> 3.5578542 | BI15: =+(K15/J15)*100 -> #DIV/0! | BJ15: =+(M15/L15)*100 -> 3.5578542 | BK15: =+(O15/N15)*100 -> 6.1409843 | BL15: =+(Q15/P15)*100 -> 6.1409843 | BM15: =+(S15/R15)*100 -> 6.1409843 | BN15: =+(D15/$N15)*100 -> 53.238297 | BO15: =+(E15/$O15)*100 -> 40.178239 | BP15: =+(F15/$N15)*100 -> 22.769838 | BQ15: =+(G15/$O15)*100 -> 45.921782 | BR15: =+(H15/$N15)*100 -> 23.991865 | BS15: =+(I15/$O15)*100 -> 13.89998 | BT15: =+(J15/$N15)*100 -> 0 | BU15: =+(K15/$O15)*100 -> 0 | BV15: ND | BW15: ND | BX15: =+(N15/$N15)*100 -> 100 | BY15: =+(O15/$O15)*100 -> 100 | BZ15: ND | CA15: ND
A16: 35034 | B16: =+'[1]Senda Inflación Total'!F500 -> 19.46 | C16: =+'[1]Senda Inflación Total'!D500 -> 21.8 | D16: 16081.66 | E16: 656.73166 | F16: 6735.1318 | G16: 821.23487 | H16: 7265.1811 | I16: 251.12442 | L16: =+H16 -> 7265.1811 | M16: =+I16 -> 251.12442 | N16: =+D16+F16+H16+J16 -> 30081.972 | O16: =+E16+G16+I16+K16 -> 1729.0909 | P16: =+L16+J16+F16+D16 -> 30081.972 | Q16: =+M16+K16+G16+E16 -> 1729.0909 | R16: =+D16+F16+L16 -> 30081.972 | S16: =+E16+G16+M16 -> 1729.0909 | V16: =+D16/D4*100-100 -> 45.086823 | W16: =+E16/E4*100-100 -> 59.723382 | X16: =+F16/F4*100-100 -> 24.415603 | Y16: =+G16/G4*100-100 -> 52.435766 | Z16: =+H16/H4*100-100 -> 40.865221 | AA16: =+I16/I4*100-100 -> 41.437271 | AD16: =+L16/L4*100-100 -> 40.865221 | AE16: =+M16/M4*100-100 -> 41.437271 | AF16: =+N16/N4*100-100 -> 38.913919 | AG16: =+O16/O4*100-100 -> 53.361414 | AH16: =+P16/P4*100-100 -> 38.913919 | AI16: =+Q16/Q4*100-100 -> 53.361414 | AJ16: =+R16/R4*100-100 -> 38.913919 | AK16: =+S16/S4*100-100 -> 53.361414 | AN16: =+(1+V16/100)/(1+$B16/100)*100-100 -> 21.452221 | AO16: =+(1+W16/100)/(1+$B16/100)*100-100 -> 33.704489 | AP16: =+(1+X16/100)/(1+$B16/100)*100-100 -> 4.1483366 | AQ16: =+(1+Y16/100)/(1+$B16/100)*100-100 -> 27.604023 | AR16: =+(1+Z16/100)/(1+$B16/100)*100-100 -> 17.918317 | AS16: =+(1+AA16/100)/(1+$B16/100)*100-100 -> 18.39718 | AT16: =+(1+AB16/100)/(1+$B16/100)*100-100 -> -16.289972 | AU16: =+(1+AC16/100)/(1+$B16/100)*100-100 -> -16.289972 | ... BC16: =+(1+AK16/100)/(1+$B16/100)*100-100 -> 28.378884 | BF16: =+(E16/D16)*100 -> 4.0837307 | BG16: =+(G16/F16)*100 -> 12.193301 | BH16: =+(I16/H16)*100 -> 3.4565473 | BI16: =+(K16/J16)*100 -> #DIV/0! | BJ16: =+(M16/L16)*100 -> 3.4565473 | BK16: =+(O16/N16)*100 -> 5.7479308 | BL16: =+(Q16/P16)*100 -> 5.7479308 | BM16: =+(S16/R16)*100 -> 5.7479308 | BN16: =+(D16/$N16)*100 -> 53.459458 | BO16: =+(E16/$O16)*100 -> 37.981325 | BP16: =+(F16/$N16)*100 -> 22.389263 | BQ16: =+(G16/$O16)*100 -> 47.495181 | BR16: =+(H16/$N16)*100 -> 24.151279 | BS16: =+(I16/$O16)*100 -> 14.523494 | BT16: =+(J16/$N16)*100 -> 0 | BU16: =+(K16/$O16)*100 -> 0 | BV16: ND | BW16: ND | BX16: =+(N16/$N16)*100 -> 100 | BY16: =+(O16/$O16)*100 -> 100 | BZ16: ND | CA16: ND
A17: 35065 | B17: =+'[1]Senda Inflación Total'!F501 -> 20.24 | C17: =+'[1]Senda Inflación Total'!D501 -> 22.35 | D17: 16370.864 | E17: 759.31188 | F17: 6892.3545 | G17: 883.74904 | H17: 7469.316 | I17: 276.49345 | L17: =+H17 -> 7469.316 | M17: =+I17 -> 276.49345 | N17: =+D17+F17+H17+J17 -> 30732.535 | O17: =+E17+G17+I17+K17 -> 1919.5544 | P17: =+L17+J17+F17+D17 -> 30732.535 | Q17: =+M17+K17+G17+E17 -> 1919.5544 | R17: =+D17+F17+L17 -> 30732.535 | S17: =+E17+G17+M17 -> 1919.5544 | V17: =+D17/D5*100-100 -> 45.720575 | W17: =+E17/E5*100-100 -> 58.98007 | X17: =+F17/F5*100-100 -> 22.082923 | Y17: =+G17/G5*100-100 -> 41.338465 | Z17: =+H17/H5*100-100 -> 39.258606 | AA17: =+I17/I5*100-100 -> 54.692355 | AD17: =+L17/L5*100-100 -> 39.258606 | AE17: =+M17/M5*100-100 -> 54.692355 | AF17: =+N17/N5*100-100 -> 38.162964 | AG17: =+O17/O5*100-100 -> 49.775208 | AH17: =+P17/P5*100-100 -> 38.162964 | AI17: =+Q17/Q5*100-100 -> 49.775208 | AJ17: =+R17/R5*100-100 -> 38.162964 | AK17: =+S17/S5*100-100 -> 49.775208 | AN17: =+(1+V17/100)/(1+$B17/100)*100-100 -> 21.19143 | AO17: =+(1+W17/100)/(1+$B17/100)*100-100 -> 32.218953 | AP17: =+(1+X17/100)/(1+$B17/100)*100-100 -> 1.5327041 | AQ17: =+(1+Y17/100)/(1+$B17/100)*100-100 -> 17.54696 | AR17: =+(1+Z17/100)/(1+$B17/100)*100-100 -> 15.817204 | AS17: =+(1+AA17/100)/(1+$B17/100)*100-100 -> 28.65299 | AT17: =+(1+AB17/100)/(1+$B17/100)*100-100 -> -16.833001 | AU17: =+(1+AC17/100)/(1+$B17/100)*100-100 -> -16.833001 | ... BC17: =+(1+AK17/100)/(1+$B17/100)*100-100 -> 24.563546 | BF17: =+(E17/D17)*100 -> 4.6381906 | BG17: =+(G17/F17)*100 -> 12.822165 | BH17: =+(I17/H17)*100 -> 3.7017238 | BI17: =+(K17/J17)*100 -> #DIV/0! | BJ17: =+(M17/L17)*100 -> 3.7017238 | BK17: =+(O17/N17)*100 -> 6.2460008 | BL17: =+(Q17/P17)*100 -> 6.2460008 | BM17: =+(S17/R17)*100 -> 6.2460008 | BN17: =+(D17/$N17)*100 -> 53.268838 | BO17: =+(E17/$O17)*100 -> 39.556675 | BP17: =+(F17/$N17)*100 -> 22.426899 | BQ17: =+(G17/$O17)*100 -> 46.039282 | BR17: =+(H17/$N17)*100 -> 24.304263 | BS17: =+(I17/$O17)*100 -> 14.404044 | BT17: =+(J17/$N17)*100 -> 0 | BU17: =+(K17/$O17)*100 -> 0 | BV17: ND | BW17: ND | BX17: =+(N17/$N17)*100 -> 100 | BY17: =+(O17/$O17)*100 -> 100 | BZ17: ND | CA17: ND
A18: 35096 | B18: =+'[1]Senda Inflación Total'!F502 -> 20.81 | C18: =+'[1]Senda Inflación Total'!D502 -> 23.25 | D18: 16628.831 | E18: 806.2291 | F18: 6983.8367 | G18: 929.75646 | H18: 7650.069 | I18: 282.94512 | L18: =+H18 -> 7650.069 | M18: =+I18 -> 282.94512 | N18: =+D18+F18+H18+J18 -> 31262.737 | O18: =+E18+G18+I18+K18 -> 2018.9307 | P18: =+L18+J18+F18+D18 -> 31262.737 | Q18: =+M18+K18+G18+E18 -> 2018.9307 | R18: =+D18+F18+L18 -> 31262.737 | S18: =+E18+G18+M18 -> 2018.9307 | V18: =+D18/D6*100-100 -> 44.499343 | W18: =+E18/E6*100-100 -> 57.498496 | X18: =+F18/F6*100-100 -> 22.214308 | Y18: =+G18/G6*100-100 -> 39.85606 | Z18: =+H18/H6*100-100 -> 38.495299 | AA18: =+I18/I6*100-100 -> 50.339908 | AD18: =+L18/L6*100-100 -> 38.495299 | AE18: =+M18/M6*100-100 -> 50.339908 | AF18: =+N18/N6*100-100 -> 37.442697 | AG18: =+O18/O6*100-100 -> 47.918362 | AH18: =+P18/P6*100-100 -> 37.442697 | AI18: =+Q18/Q6*100-100 -> 47.918362 | AJ18: =+R18/R6*100-100 -> 37.442697 | AK18: =+S18/S6*100-100 -> 47.918362 | AN18: =+(1+V18/100)/(1+$B18/100)*100-100 -> 19.60876 | AO18: =+(1+W18/100)/(1+$B18/100)*100-100 -> 30.368758 | AP18: =+(1+X18/100)/(1+$B18/100)*100-100 -> 1.1624105 | AQ18: =+(1+Y18/100)/(1+$B18/100)*100-100 -> 15.765301 | AR18: =+(1+Z18/100)/(1+$B18/100)*100-100 -> 14.638936 | AS18: =+(1+AA18/100)/(1+$B18/100)*100-100 -> 24.443265 | AT18: =+(1+AB18/100)/(1+$B18/100)*100-100 -> -17.225395 | AU18: =+(1+AC18/100)/(1+$B18/100)*100-100 -> -17.225395 | ... BC18: =+(1+AK18/100)/(1+$B18/100)*100-100 -> 22.438839 | BF18: =+(E18/D18)*100 -> 4.848381 | BG18: =+(G18/F18)*100 -> 13.312975 | BH18: =+(I18/H18)*100 -> 3.6985957 | BI18: =+(K18/J18)*100 -> #DIV/0! | BJ18: =+(M18/L18)*100 -> 3.6985957 | BK18: =+(O18/N18)*100 -> 6.457946 | BL18: =+(Q18/P18)*100 -> 6.457946 | BM18: =+(S18/R18)*100 -> 6.457946 | BN18: =+(D18/$N18)*100 -> 53.190581 | BO18: =+(E18/$O18)*100 -> 39.933471 | BP18: =+(F18/$N18)*100 -> 22.339172 | BQ18: =+(G18/$O18)*100 -> 46.051926 | BR18: =+(H18/$N18)*100 -> 24.470247 | BS18: =+(I18/$O18)*100 -> 14.014603 | BT18: =+(J18/$N18)*100 -> 0 | BU18: =+(K18/$O18)*100 -> 0 | BV18: ND | BW18: ND | BX18: =+(N18/$N18)*100 -> 100 | BY18: =+(O18/$O18)*100 -> 100 | BZ18: ND | CA18: ND
A19: 35125 | B19: =+'[1]Senda Inflación Total'!F503 -> 20.2 | C19: =+'[1]Senda Inflación Total'!D503 -> 23.74 | D19: 17066.408 | E19: 809.17202 | F19: 7068.8792 | G19: 946.91955 | H19: 7854.8238 | I19: 292.03142 | L19: =+H19 -> 7854.8238 | M19: =+I19 -> 292.03142 | N19: =+D19+F19+H19+J19 -> 31990.111 | O19: =+E19+G19+I19+K19 -> 2048.123 | P19: =+L19+J19+F19+D19 -> 31990.111 | Q19: =+M19+K19+G19+E19 -> 2048.123 | R19: =+D19+F19+L19 -> 31990.111 | S19: =+E19+G19+M19 -> 2048.123 | V19: =+D19/D7*100-100 -> 41.430573 | W19: =+E19/E7*100-100 -> 58.841565 | X19: =+F19/F7*100-100 -> 21.288681 | Y19: =+G19/G7*100-100 -> 49.168218 | Z19: =+H19/H7*100-100 -> 37.201585 | AA19: =+I19/I7*100-100 -> 50.511131 | AD19: =+L19/L7*100-100 -> 37.201585 | AE19: =+M19/M7*100-100 -> 50.511131 | AF19: =+N19/N7*100-100 -> 35.435654 | AG19: =+O19/O7*100-100 -> 53.045204 | AH19: =+P19/P7*100-100 -> 35.435654 | AI19: =+Q19/Q7*100-100 -> 53.045204 | AJ19: =+R19/R7*100-100 -> 35.435654 | AK19: =+S19/S7*100-100 -> 53.045204 | AN19: =+(1+V19/100)/(1+$B19/100)*100-100 -> 17.662706 | AO19: =+(1+W19/100)/(1+$B19/100)*100-100 -> 32.147725 | AP19: =+(1+X19/100)/(1+$B19/100)*100-100 -> 0.90572457 | AQ19: =+(1+Y19/100)/(1+$B19/100)*100-100 -> 24.100015 | AR19: =+(1+Z19/100)/(1+$B19/100)*100-100 -> 14.144414 | AS19: =+(1+AA19/100)/(1+$B19/100)*100-100 -> 25.217247 | AT19: =+(1+AB19/100)/(1+$B19/100)*100-100 -> -16.805324 | AU19: =+(1+AC19/100)/(1+$B19/100)*100-100 -> -16.805324 | ... BC19: =+(1+AK19/100)/(1+$B19/100)*100-100 -> 27.325461 | BF19: =+(E19/D19)*100 -> 4.7413142 | BG19: =+(G19/F19)*100 -> 13.395611 | BH19: =+(I19/H19)*100 -> 3.7178609 | BI19: =+(K19/J19)*100 -> #DIV/0! | BJ19: =+(M19/L19)*100 -> 3.7178609 | BK19: =+(O19/N19)*100 -> 6.4023629 | BL19: =+(Q19/P19)*100 -> 6.4023629 | BM19: =+(S19/R19)*100 -> 6.4023629 | BN19: =+(D19/$N19)*100 -> 53.349011 | BO19: =+(E19/$O19)*100 -> 39.50798 | BP19: =+(F19/$N19)*100 -> 22.097076 | BQ19: =+(G19/$O19)*100 -> 46.23353 | BR19: =+(H19/$N19)*100 -> 24.553912 | BS19: =+(I19/$O19)*100 -> 14.25849 | BT19: =+(J19/$N19)*100 -> 0 | BU19: =+(K19/$O19)*100 -> 0 | BV19: ND | BW19: ND | BX19: =+(N19/$N19)*100 -> 100 | BY19: =+(O19/$O19)*100 -> 100 | BZ19: ND | CA19: ND
A20: 35156 | B20: =+'[1]Senda Inflación Total'!F504 -> 19.9 | C20: =+'[1]Senda Inflación Total'!D504 -> 24.21 | D20: 17302 | E20: 895.77896 | F20: 7166.5109 | G20: 994.33781 | H20: 8027.5465 | I20: 307.19289 | L20: =+H20 -> 8027.5465 | M20: =+I20 -> 307.19289 | N20: =+D20+F20+H20+J20 -> 32496.057 | O20: =+E20+G20+I20+K20 -> 2197.3097 | P20: =+L20+J20+F20+D20 -> 32496.057 | Q20: =+M20+K20+G20+E20 -> 2197.3097 | R20: =+D20+F20+L20 -> 32496.057 | S20: =+E20+G20+M20 -> 2197.3097 | V20: =+D20/D8*100-100 -> 39.850863 | W20: =+E20/E8*100-100 -> 68.414181 | X20: =+F20/F8*100-100 -> 20.027054 | Y20: =+G20/G8*100-100 -> 41.240476 | Z20: =+H20/H8*100-100 -> 36.584368 | AA20: =+I20/I8*100-100 -> 49.263969 | AD20: =+L20/L8*100-100 -> 36.584368 | AE20: =+M20/M8*100-100 -> 49.263969 | AF20: =+N20/N8*100-100 -> 34.171171 | AG20: =+O20/O8*100-100 -> 52.411123 | AH20: =+P20/P8*100-100 -> 34.171171 | AI20: =+Q20/Q8*100-100 -> 52.411123 | AJ20: =+R20/R8*100-100 -> 34.171171 | AK20: =+S20/S8*100-100 -> 52.411123 | AN20: =+(1+V20/100)/(1+$B20/100)*100-100 -> 16.639585 | AO20: =+(1+W20/100)/(1+$B20/100)*100-100 -> 40.462202 | AP20: =+(1+X20/100)/(1+$B20/100)*100-100 -> 0.10596622 | AQ20: =+(1+Y20/100)/(1+$B20/100)*100-100 -> 17.798562 | AR20: =+(1+Z20/100)/(1+$B20/100)*100-100 -> 13.915236 | AS20: =+(1+AA20/100)/(1+$B20/100)*100-100 -> 24.490383 | AT20: =+(1+AB20/100)/(1+$B20/100)*100-100 -> -16.597164 | AU20: =+(1+AC20/100)/(1+$B20/100)*100-100 -> -16.597164 | ... BC20: =+(1+AK20/100)/(1+$B20/100)*100-100 -> 27.115198 | BF20: =+(E20/D20)*100 -> 5.1773145 | BG20: =+(G20/F20)*100 -> 13.874783 | BH20: =+(I20/H20)*100 -> 3.8267345 | BI20: =+(K20/J20)*100 -> #DIV/0! | BJ20: =+(M20/L20)*100 -> 3.8267345 | BK20: =+(O20/N20)*100 -> 6.7617731 | BL20: =+(Q20/P20)*100 -> 6.7617731 | BM20: =+(S20/R20)*100 -> 6.7617731 | BN20: =+(D20/$N20)*100 -> 53.243382 | BO20: =+(E20/$O20)*100 -> 40.767079 | BP20: =+(F20/$N20)*100 -> 22.053478 | BQ20: =+(G20/$O20)*100 -> 45.252512 | BR20: =+(H20/$N20)*100 -> 24.70314 | BS20: =+(I20/$O20)*100 -> 13.98041 | BT20: =+(J20/$N20)*100 -> 0 | BU20: =+(K20/$O20)*100 -> 0 | BV20: ND | BW20: ND | BX20: =+(N20/$N20)*100 -> 100 | BY20: =+(O20/$O20)*100 -> 100 | BZ20: ND | CA20: ND
A21: 35186 | B21: =+'[1]Senda Inflación Total'!F505 -> 19.78 | C21: =+'[1]Senda Inflación Total'!D505 -> 24.58 | D21: 17694.366 | E21: 924.85888 | F21: 7198.3922 | G21: 983.24602 | H21: 8290.727 | I21: 322.63806 | L21: =+H21 -> 8290.727 | M21: =+I21 -> 322.63806 | N21: =+D21+F21+H21+J21 -> 33183.485 | O21: =+E21+G21+I21+K21 -> 2230.743 | P21: =+L21+J21+F21+D21 -> 33183.485 | Q21: =+M21+K21+G21+E21 -> 2230.743 | R21: =+D21+F21+L21 -> 33183.485 | S21: =+E21+G21+M21 -> 2230.743 | V21: =+D21/D9*100-100 -> 38.202591 | W21: =+E21/E9*100-100 -> 73.278769 | X21: =+F21/F9*100-100 -> 18.450512 | Y21: =+G21/G9*100-100 -> 36.035362 | Z21: =+H21/H9*100-100 -> 36.875143 | AA21: =+I21/I9*100-100 -> 61.429674 | AD21: =+L21/L9*100-100 -> 36.875143 | AE21: =+M21/M9*100-100 -> 61.429674 | AF21: =+N21/N9*100-100 -> 33.066688 | AG21: =+O21/O9*100-100 -> 53.169293 | AH21: =+P21/P9*100-100 -> 33.066688 | AI21: =+Q21/Q9*100-100 -> 53.169293 | AJ21: =+R21/R9*100-100 -> 33.066688 | AK21: =+S21/S9*100-100 -> 53.169293 | AN21: =+(1+V21/100)/(1+$B21/100)*100-100 -> 15.380357 | AO21: =+(1+W21/100)/(1+$B21/100)*100-100 -> 44.664192 | AP21: =+(1+X21/100)/(1+$B21/100)*100-100 -> -1.1099419 | AQ21: =+(1+Y21/100)/(1+$B21/100)*100-100 -> 13.571015 | AR21: =+(1+Z21/100)/(1+$B21/100)*100-100 -> 14.272118 | AS21: =+(1+AA21/100)/(1+$B21/100)*100-100 -> 34.77181 | AT21: =+(1+AB21/100)/(1+$B21/100)*100-100 -> -16.513608 | AU21: =+(1+AC21/100)/(1+$B21/100)*100-100 -> -16.513608 | ... BC21: =+(1+AK21/100)/(1+$B21/100)*100-100 -> 27.875516 | BF21: =+(E21/D21)*100 -> 5.2268552 | BG21: =+(G21/F21)*100 -> 13.659245 | BH21: =+(I21/H21)*100 -> 3.8915533 | BI21: =+(K21/J21)*100 -> #DIV/0! | BJ21: =+(M21/L21)*100 -> 3.8915533 | BK21: =+(O21/N21)*100 -> 6.7224493 | BL21: =+(Q21/P21)*100 -> 6.7224493 | BM21: =+(S21/R21)*100 -> 6.7224493 | BN21: =+(D21/$N21)*100 -> 53.322808 | BO21: =+(E21/$O21)*100 -> 41.459679 | BP21: =+(F21/$N21)*100 -> 21.692695 | BQ21: =+(G21/$O21)*100 -> 44.077065 | BR21: =+(H21/$N21)*100 -> 24.984497 | BS21: =+(I21/$O21)*100 -> 14.463256 | BT21: =+(J21/$N21)*100 -> 0 | BU21: =+(K21/$O21)*100 -> 0 | BV21: ND | BW21: ND | BX21: =+(N21/$N21)*100 -> 100 | BY21: =+(O21/$O21)*100 -> 100 | BZ21: ND | CA21: ND
A22: 35217 | B22: =+'[1]Senda Inflación Total'!F506 -> 19.7 | C22: =+'[1]Senda Inflación Total'!D506 -> 24.87 | D22: 17981.851 | E22: 903.9397 | F22: 7227.9786 | G22: 988.03819 | H22: 8528.1092 | I22: 336.47764 | L22: =+H22 -> 8528.1092 | M22: =+I22 -> 336.47764 | N22: =+D22+F22+H22+J22 -> 33737.939 | O22: =+E22+G22+I22+K22 -> 2228.4555 | P22: =+L22+J22+F22+D22 -> 33737.939 | Q22: =+M22+K22+G22+E22 -> 2228.4555 | R22: =+D22+F22+L22 -> 33737.939 | S22: =+E22+G22+M22 -> 2228.4555 | V22: =+D22/D10*100-100 -> 35.904089 | W22: =+E22/E10*100-100 -> 70.835178 | X22: =+F22/F10*100-100 -> 17.699774 | Y22: =+G22/G10*100-100 -> 41.32163 | Z22: =+H22/H10*100-100 -> 36.866281 | AA22: =+I22/I10*100-100 -> 54.812426 | AD22: =+L22/L10*100-100 -> 36.866281 | AE22: =+M22/M10*100-100 -> 54.812426 | AF22: =+N22/N10*100-100 -> 31.771892 | AG22: =+O22/O10*100-100 -> 54.152596 | AH22: =+P22/P10*100-100 -> 31.771892 | AI22: =+Q22/Q10*100-100 -> 54.152596 | AJ22: =+R22/R10*100-100 -> 31.771892 | AK22: =+S22/S10*100-100 -> 54.152596 | AN22: =+(1+V22/100)/(1+$B22/100)*100-100 -> 13.537251 | AO22: =+(1+W22/100)/(1+$B22/100)*100-100 -> 42.719447 | AP22: =+(1+X22/100)/(1+$B22/100)*100-100 -> -1.6710325 | AQ22: =+(1+Y22/100)/(1+$B22/100)*100-100 -> 18.063183 | AR22: =+(1+Z22/100)/(1+$B22/100)*100-100 -> 14.341087 | AS22: =+(1+AA22/100)/(1+$B22/100)*100-100 -> 29.333689 | AT22: =+(1+AB22/100)/(1+$B22/100)*100-100 -> -16.457811 | AU22: =+(1+AC22/100)/(1+$B22/100)*100-100 -> -16.457811 | ... BC22: =+(1+AK22/100)/(1+$B22/100)*100-100 -> 28.782453 | BF22: =+(E22/D22)*100 -> 5.0269557 | BG22: =+(G22/F22)*100 -> 13.669634 | BH22: =+(I22/H22)*100 -> 3.9455128 | BI22: =+(K22/J22)*100 -> #DIV/0! | BJ22: =+(M22/L22)*100 -> 3.9455128 | BK22: =+(O22/N22)*100 -> 6.6051916 | BL22: =+(Q22/P22)*100 -> 6.6051916 | BM22: =+(S22/R22)*100 -> 6.6051916 | BN22: =+(D22/$N22)*100 -> 53.298606 | BO22: =+(E22/$O22)*100 -> 40.563506 | BP22: =+(F22/$N22)*100 -> 21.423889 | BQ22: =+(G22/$O22)*100 -> 44.337353 | BR22: =+(H22/$N22)*100 -> 25.277505 | BS22: =+(I22/$O22)*100 -> 15.099141 | BT22: =+(J22/$N22)*100 -> 0 | BU22: =+(K22/$O22)*100 -> 0 | BV22: ND | BW22: ND | BX22: =+(N22/$N22)*100 -> 100 | BY22: =+(O22/$O22)*100 -> 100 | BZ22: ND | CA22: ND
A23: 35247 | B23: =+'[1]Senda Inflación Total'!F507 -> 20.57 | C23: =+'[1]Senda Inflación Total'!D507 -> 25.24 | D23: 18206.785 | E23: 1012.8559 | F23: 7345.5398 | G23: 1018.5946 | H23: 8788.178 | I23: 350.67155 | L23: =+H23 -> 8788.178 | M23: =+I23 -> 350.67155 | N23: =+D23+F23+H23+J23 -> 34340.502 | O23: =+E23+G23+I23+K23 -> 2382.1221 | P23: =+L23+J23+F23+D23 -> 34340.502 | Q23: =+M23+K23+G23+E23 -> 2382.1221 | R23: =+D23+F23+L23 -> 34340.502 | S23: =+E23+G23+M23 -> 2382.1221 | V23: =+D23/D11*100-100 -> 32.504965 | W23: =+E23/E11*100-100 -> 57.938046 | X23: =+F23/F11*100-100 -> 17.952481 | Y23: =+G23/G11*100-100 -> 30.46784 | Z23: =+H23/H11*100-100 -> 40.123834 | AA23: =+I23/I11*100-100 -> 64.960463 | AD23: =+L23/L11*100-100 -> 40.123834 | AE23: =+M23/M11*100-100 -> 64.960463 | AF23: =+N23/N11*100-100 -> 30.87222 | AG23: =+O23/O11*100-100 -> 45.730896 | AH23: =+P23/P11*100-100 -> 30.87222 | AI23: =+Q23/Q11*100-100 -> 45.730896 | AJ23: =+R23/R11*100-100 -> 30.87222 | AK23: =+S23/S11*100-100 -> 45.730896 | AN23: =+(1+V23/100)/(1+$B23/100)*100-100 -> 9.8987853 | AO23: =+(1+W23/100)/(1+$B23/100)*100-100 -> 30.992822 | AP23: =+(1+X23/100)/(1+$B23/100)*100-100 -> -2.1709536 | AQ23: =+(1+Y23/100)/(1+$B23/100)*100-100 -> 8.2092062 | AR23: =+(1+Z23/100)/(1+$B23/100)*100-100 -> 16.217827 | AS23: =+(1+AA23/100)/(1+$B23/100)*100-100 -> 36.817171 | AT23: =+(1+AB23/100)/(1+$B23/100)*100-100 -> -17.060629 | AU23: =+(1+AC23/100)/(1+$B23/100)*100-100 -> -17.060629 | ... BC23: =+(1+AK23/100)/(1+$B23/100)*100-100 -> 20.868289 | BF23: =+(E23/D23)*100 -> 5.5630686 | BG23: =+(G23/F23)*100 -> 13.866845 | BH23: =+(I23/H23)*100 -> 3.9902646 | BI23: =+(K23/J23)*100 -> #DIV/0! | BJ23: =+(M23/L23)*100 -> 3.9902646 | BK23: =+(O23/N23)*100 -> 6.9367712 | BL23: =+(Q23/P23)*100 -> 6.9367712 | BM23: =+(S23/R23)*100 -> 6.9367712 | BN23: =+(D23/$N23)*100 -> 53.018399 | BO23: =+(E23/$O23)*100 -> 42.519061 | BP23: =+(F23/$N23)*100 -> 21.39031 | BQ23: =+(G23/$O23)*100 -> 42.759966 | BR23: =+(H23/$N23)*100 -> 25.591291 | BS23: =+(I23/$O23)*100 -> 14.720973 | BT23: =+(J23/$N23)*100 -> 0 | BU23: =+(K23/$O23)*100 -> 0 | BV23: ND | BW23: ND | BX23: =+(N23/$N23)*100 -> 100 | BY23: =+(O23/$O23)*100 -> 100 | BZ23: ND | CA23: ND
A24: 35278 | B24: =+'[1]Senda Inflación Total'!F508 -> 21.13 | C24: =+'[1]Senda Inflación Total'!D508 -> 25.52 | D24: 18426.464 | E24: 1104.8916 | F24: 7418.3198 | G24: 1047.7519 | H24: 9041.3167 | I24: 364.25691 | L24: =+H24 -> 9041.3167 | M24: =+I24 -> 364.25691 | N24: =+D24+F24+H24+J24 -> 34886.1 | O24: =+E24+G24+I24+K24 -> 2516.9004 | P24: =+L24+J24+F24+D24 -> 34886.1 | Q24: =+M24+K24+G24+E24 -> 2516.9004 | R24: =+D24+F24+L24 -> 34886.1 | S24: =+E24+G24+M24 -> 2516.9004 | V24: =+D24/D12*100-100 -> 29.335976 | W24: =+E24/E12*100-100 -> 66.774375 | X24: =+F24/F12*100-100 -> 17.271854 | Y24: =+G24/G12*100-100 -> 33.312388 | Z24: =+H24/H12*100-100 -> 39.16213 | AA24: =+I24/I12*100-100 -> 62.123848 | AD24: =+L24/L12*100-100 -> 39.16213 | AE24: =+M24/M12*100-100 -> 62.123848 | AF24: =+N24/N12*100-100 -> 28.875151 | AG24: =+O24/O12*100-100 -> 50.431339 | AH24: =+P24/P12*100-100 -> 28.875151 | AI24: =+Q24/Q12*100-100 -> 50.431339 | AJ24: =+R24/R12*100-100 -> 28.875151 | AK24: =+S24/S12*100-100 -> 50.431339 | AN24: =+(1+V24/100)/(1+$B24/100)*100-100 -> 6.7745197 | AO24: =+(1+W24/100)/(1+$B24/100)*100-100 -> 37.682139 | AP24: =+(1+X24/100)/(1+$B24/100)*100-100 -> -3.1851283 | AQ24: =+(1+Y24/100)/(1+$B24/100)*100-100 -> 10.057284 | AR24: =+(1+Z24/100)/(1+$B24/100)*100-100 -> 14.886593 | AS24: =+(1+AA24/100)/(1+$B24/100)*100-100 -> 33.842853 | AT24: =+(1+AB24/100)/(1+$B24/100)*100-100 -> -17.444068 | AU24: =+(1+AC24/100)/(1+$B24/100)*100-100 -> -17.444068 | ... BC24: =+(1+AK24/100)/(1+$B24/100)*100-100 -> 24.189993 | BF24: =+(E24/D24)*100 -> 5.9962215 | BG24: =+(G24/F24)*100 -> 14.123844 | BH24: =+(I24/H24)*100 -> 4.0288038 | BI24: =+(K24/J24)*100 -> #DIV/0! | BJ24: =+(M24/L24)*100 -> 4.0288038 | BK24: =+(O24/N24)*100 -> 7.2146224 | BL24: =+(Q24/P24)*100 -> 7.2146224 | BM24: =+(S24/R24)*100 -> 7.2146224 | BN24: =+(D24/$N24)*100 -> 52.818927 | BO24: =+(E24/$O24)*100 -> 43.8989 | BP24: =+(F24/$N24)*100 -> 21.2644 | BQ24: =+(G24/$O24)*100 -> 41.62866 | BR24: =+(H24/$N24)*100 -> 25.916673 | BS24: =+(I24/$O24)*100 -> 14.47244 | BT24: =+(J24/$N24)*100 -> 0 | BU24: =+(K24/$O24)*100 -> 0 | BV24: ND | BW24: ND | BX24: =+(N24/$N24)*100 -> 100 | BY24: =+(O24/$O24)*100 -> 100 | BZ24: ND | CA24: ND
A25: 35309 | B25: =+'[1]Senda Inflación Total'!F509 -> 21.55 | C25: =+'[1]Senda Inflación Total'!D509 -> 25.82 | D25: 18703.253 | E25: 1088.7846 | F25: 7505.357 | G25: 1063.2052 | H25: 9286.2702 | I25: 389.61253 | L25: =+H25 -> 9286.2702 | M25: =+I25 -> 389.61253 | N25: =+D25+F25+H25+J25 -> 35494.881 | O25: =+E25+G25+I25+K25 -> 2541.6024 | P25: =+L25+J25+F25+D25 -> 35494.881 | Q25: =+M25+K25+G25+E25 -> 2541.6024 | R25: =+D25+F25+L25 -> 35494.881 | S25: =+E25+G25+M25 -> 2541.6024 | V25: =+D25/D13*100-100 -> 26.685541 | W25: =+E25/E13*100-100 -> 67.512702 | X25: =+F25/F13*100-100 -> 15.958866 | Y25: =+G25/G13*100-100 -> 36.441807 | Z25: =+H25/H13*100-100 -> 38.861733 | AA25: =+I25/I13*100-100 -> 71.097491 | AD25: =+L25/L13*100-100 -> 38.861733 | AE25: =+M25/M13*100-100 -> 71.097491 | AF25: =+N25/N13*100-100 -> 27.115277 | AG25: =+O25/O13*100-100 -> 53.392976 | AH25: =+P25/P13*100-100 -> 27.115277 | AI25: =+Q25/Q13*100-100 -> 53.392976 | AJ25: =+R25/R13*100-100 -> 27.115277 | AK25: =+S25/S13*100-100 -> 53.392976 | AN25: =+(1+V25/100)/(1+$B25/100)*100-100 -> 4.2250441 | AO25: =+(1+W25/100)/(1+$B25/100)*100-100 -> 37.813823 | AP25: =+(1+X25/100)/(1+$B25/100)*100-100 -> -4.5998635 | AQ25: =+(1+Y25/100)/(1+$B25/100)*100-100 -> 12.251589 | AR25: =+(1+Z25/100)/(1+$B25/100)*100-100 -> 14.242479 | AS25: =+(1+AA25/100)/(1+$B25/100)*100-100 -> 40.763053 | AT25: =+(1+AB25/100)/(1+$B25/100)*100-100 -> -17.729329 | AU25: =+(1+AC25/100)/(1+$B25/100)*100-100 -> -17.729329 | ... BC25: =+(1+AK25/100)/(1+$B25/100)*100-100 -> 26.19743 | BF25: =+(E25/D25)*100 -> 5.821365 | BG25: =+(G25/F25)*100 -> 14.165951 | BH25: =+(I25/H25)*100 -> 4.1955761 | BI25: =+(K25/J25)*100 -> #DIV/0! | BJ25: =+(M25/L25)*100 -> 4.1955761 | BK25: =+(O25/N25)*100 -> 7.1604759 | BL25: =+(Q25/P25)*100 -> 7.1604759 | BM25: =+(S25/R25)*100 -> 7.1604759 | BN25: =+(D25/$N25)*100 -> 52.69282 | BO25: =+(E25/$O25)*100 -> 42.838512 | BP25: =+(F25/$N25)*100 -> 21.1449 | BQ25: =+(G25/$O25)*100 -> 41.832082 | BR25: =+(H25/$N25)*100 -> 26.16228 | BS25: =+(I25/$O25)*100 -> 15.329405 | BT25: =+(J25/$N25)*100 -> 0 | BU25: =+(K25/$O25)*100 -> 0 | BV25: ND | BW25: ND | BX25: =+(N25/$N25)*100 -> 100 | BY25: =+(O25/$O25)*100 -> 100 | BZ25: ND | CA25: ND
A26: 35339 | B26: =+'[1]Senda Inflación Total'!F510 -> 21.87 | C26: =+'[1]Senda Inflación Total'!D510 -> 26.12 | D26: 18828.63 | E26: 1191.372 | F26: 7496.002 | G26: 1087.5661 | H26: 9476.0938 | I26: 410.04506 | L26: =+H26 -> 9476.0938 | M26: =+I26 -> 410.04506 | N26: =+D26+F26+H26+J26 -> 35800.726 | O26: =+E26+G26+I26+K26 -> 2688.9831 | P26: =+L26+J26+F26+D26 -> 35800.726 | Q26: =+M26+K26+G26+E26 -> 2688.9831 | R26: =+D26+F26+L26 -> 35800.726 | S26: =+E26+G26+M26 -> 2688.9831 | V26: =+D26/D14*100-100 -> 24.185409 | W26: =+E26/E14*100-100 -> 69.346671 | X26: =+F26/F14*100-100 -> 13.723566 | Y26: =+G26/G14*100-100 -> 36.336183 | Z26: =+H26/H14*100-100 -> 37.423627 | AA26: =+I26/I14*100-100 -> 73.28369 | AD26: =+L26/L14*100-100 -> 37.423627 | AE26: =+M26/M14*100-100 -> 73.28369 | AF26: =+N26/N14*100-100 -> 24.964718 | AG26: =+O26/O14*100-100 -> 54.730271 | AH26: =+P26/P14*100-100 -> 24.964718 | AI26: =+Q26/Q14*100-100 -> 54.730271 | AJ26: =+R26/R14*100-100 -> 24.964718 | AK26: =+S26/S14*100-100 -> 54.730271 | AN26: =+(1+V26/100)/(1+$B26/100)*100-100 -> 1.8999006 | AO26: =+(1+W26/100)/(1+$B26/100)*100-100 -> 38.956816 | AP26: =+(1+X26/100)/(1+$B26/100)*100-100 -> -6.6845276 | AQ26: =+(1+Y26/100)/(1+$B26/100)*100-100 -> 11.870176 | AR26: =+(1+Z26/100)/(1+$B26/100)*100-100 -> 12.762474 | AS26: =+(1+AA26/100)/(1+$B26/100)*100-100 -> 42.187323 | AT26: =+(1+AB26/100)/(1+$B26/100)*100-100 -> -17.945352 | AU26: =+(1+AC26/100)/(1+$B26/100)*100-100 -> -17.945352 | ... BC26: =+(1+AK26/100)/(1+$B26/100)*100-100 -> 26.96338 | BF26: =+(E26/D26)*100 -> 6.3274489 | BG26: =+(G26/F26)*100 -> 14.508615 | BH26: =+(I26/H26)*100 -> 4.3271528 | BI26: =+(K26/J26)*100 -> #DIV/0! | BJ26: =+(M26/L26)*100 -> 4.3271528 | BK26: =+(O26/N26)*100 -> 7.5109736 | BL26: =+(Q26/P26)*100 -> 7.5109736 | BM26: =+(S26/R26)*100 -> 7.5109736 | BN26: =+(D26/$N26)*100 -> 52.592873 | BO26: =+(E26/$O26)*100 -> 44.30567 | BP26: =+(F26/$N26)*100 -> 20.938128 | BQ26: =+(G26/$O26)*100 -> 40.445255 | BR26: =+(H26/$N26)*100 -> 26.468999 | BS26: =+(I26/$O26)*100 -> 15.249075 | BT26: =+(J26/$N26)*100 -> 0 | BU26: =+(K26/$O26)*100 -> 0 | BV26: ND | BW26: ND | BX26: =+(N26/$N26)*100 -> 100 | BY26: =+(O26/$O26)*100 -> 100 | BZ26: ND | CA26: ND
A27: 35370 | B27: =+'[1]Senda Inflación Total'!F511 -> 21.88 | C27: =+'[1]Senda Inflación Total'!D511 -> 26.33 | D27: 19485.43 | E27: 1253.6855 | F27: 7385.9305 | G27: 1100.2679 | H27: 9731.0553 | I27: 444.00469 | L27: =+H27 -> 9731.0553 | M27: =+I27 -> 444.00469 | N27: =+D27+F27+H27+J27 -> 36602.415 | O27: =+E27+G27+I27+K27 -> 2797.9581 | P27: =+L27+J27+F27+D27 -> 36602.415 | Q27: =+M27+K27+G27+E27 -> 2797.9582 | R27: =+D27+F27+L27 -> 36602.415 | S27: =+E27+G27+M27 -> 2797.9581 | V27: =+D27/D15*100-100 -> 24.559313 | W27: =+E27/E15*100-100 -> 72.92194 | X27: =+F27/F15*100-100 -> 10.391502 | Y27: =+G27/G15*100-100 -> 32.779832 | Z27: =+H27/H15*100-100 -> 38.034073 | AA27: =+I27/I15*100-100 -> 77.021402 | AD27: =+L27/L15*100-100 -> 38.034073 | AE27: =+M27/M15*100-100 -> 77.021402 | AF27: =+N27/N15*100-100 -> 24.566172 | AG27: =+O27/O15*100-100 -> 55.057793 | AH27: =+P27/P15*100-100 -> 24.566172 | AI27: =+Q27/Q15*100-100 -> 55.057793 | AJ27: =+R27/R15*100-100 -> 24.566172 | AK27: =+S27/S15*100-100 -> 55.057793 | AN27: =+(1+V27/100)/(1+$B27/100)*100-100 -> 2.1983206 | AO27: =+(1+W27/100)/(1+$B27/100)*100-100 -> 41.878848 | AP27: =+(1+X27/100)/(1+$B27/100)*100-100 -> -9.4260732 | AQ27: =+(1+Y27/100)/(1+$B27/100)*100-100 -> 8.9430848 | AR27: =+(1+Z27/100)/(1+$B27/100)*100-100 -> 13.25408 | AS27: =+(1+AA27/100)/(1+$B27/100)*100-100 -> 45.242371 | AT27: =+(1+AB27/100)/(1+$B27/100)*100-100 -> -17.952084 | AU27: =+(1+AC27/100)/(1+$B27/100)*100-100 -> -17.952084 | ... BC27: =+(1+AK27/100)/(1+$B27/100)*100-100 -> 27.221688 | BF27: =+(E27/D27)*100 -> 6.433964 | BG27: =+(G27/F27)*100 -> 14.896809 | BH27: =+(I27/H27)*100 -> 4.5627599 | BI27: =+(K27/J27)*100 -> #DIV/0! | BJ27: =+(M27/L27)*100 -> 4.5627599 | BK27: =+(O27/N27)*100 -> 7.6441899 | BL27: =+(Q27/P27)*100 -> 7.6441899 | BM27: =+(S27/R27)*100 -> 7.6441899 | BN27: =+(D27/$N27)*100 -> 53.235365 | BO27: =+(E27/$O27)*100 -> 44.807158 | BP27: =+(F27/$N27)*100 -> 20.178806 | BQ27: =+(G27/$O27)*100 -> 39.32396 | BR27: =+(H27/$N27)*100 -> 26.585828 | BS27: =+(I27/$O27)*100 -> 15.868882 | BT27: =+(J27/$N27)*100 -> 0 | BU27: =+(K27/$O27)*100 -> 0 | BV27: ND | BW27: ND | BX27: =+(N27/$N27)*100 -> 100 | BY27: =+(O27/$O27)*100 -> 100 | BZ27: ND | CA27: ND
A28: 35400 | B28: =+'[1]Senda Inflación Total'!F512 -> 21.63 | C28: =+'[1]Senda Inflación Total'!D512 -> 26.52 | D28: 20911.691 | E28: 1187.6357 | F28: ='[2]Dic-96'!$D$617/1000 -> 6781.9526 | G28: 879.57236 | H28: ='[2]Dic-96'!$D$630/1000 -> 9977.0954 | I28: ='[2]Dic-96'!$D$631/1000 -> 468.36723 | L28: =+H28 -> 9977.0954 | M28: =+I28 -> 468.36723 | N28: =+D28+F28+H28+J28 -> 37670.739 | O28: =+E28+G28+I28+K28 -> 2535.5753 | P28: =+L28+J28+F28+D28 -> 37670.739 | Q28: =+M28+K28+G28+E28 -> 2535.5753 | R28: =+D28+F28+L28 -> 37670.739 | S28: =+E28+G28+M28 -> 2535.5753 | V28: =+D28/D16*100-100 -> 30.034412 | W28: =+E28/E16*100-100 -> 80.840333 | X28: =+F28/F16*100-100 -> 0.69517273 | Y28: =+G28/G16*100-100 -> 7.1036304 | Z28: =+H28/H16*100-100 -> 37.327553 | AA28: =+I28/I16*100-100 -> 86.508039 | AD28: =+L28/L16*100-100 -> 37.327553 | AE28: =+M28/M16*100-100 -> 86.508039 | AF28: =+N28/N16*100-100 -> 25.22696 | AG28: =+O28/O16*100-100 -> 46.642102 | AH28: =+P28/P16*100-100 -> 25.22696 | AI28: =+Q28/Q16*100-100 -> 46.642102 | AJ28: =+R28/R16*100-100 -> 25.22696 | AK28: =+S28/S16*100-100 -> 46.642102 | AN28: =+(1+V28/100)/(1+$B28/100)*100-100 -> 6.9098183 | AO28: =+(1+W28/100)/(1+$B28/100)*100-100 -> 48.680698 | AP28: =+(1+X28/100)/(1+$B28/100)*100-100 -> -17.211894 | AQ28: =+(1+Y28/100)/(1+$B28/100)*100-100 -> -11.943081 | AR28: =+(1+Z28/100)/(1+$B28/100)*100-100 -> 12.905988 | AS28: =+(1+AA28/100)/(1+$B28/100)*100-100 -> 53.34049 | AT28: =+(1+AB28/100)/(1+$B28/100)*100-100 -> -17.783442 | AU28: =+(1+AC28/100)/(1+$B28/100)*100-100 -> -17.783442 | ... BC28: =+(1+AK28/100)/(1+$B28/100)*100-100 -> 20.564089 | BF28: =+(E28/D28)*100 -> 5.6792906 | BG28: =+(G28/F28)*100 -> 12.969309 | BH28: =+(I28/H28)*100 -> 4.6944247 | BI28: =+(K28/J28)*100 -> #DIV/0! | BJ28: =+(M28/L28)*100 -> 4.6944247 | BK28: =+(O28/N28)*100 -> 6.7308881 | BL28: =+(Q28/P28)*100 -> 6.7308881 | BM28: =+(S28/R28)*100 -> 6.7308881 | BN28: =+(D28/$N28)*100 -> 55.511762 | BO28: =+(E28/$O28)*100 -> 46.838905 | BP28: =+(F28/$N28)*100 -> 18.003237 | BQ28: =+(G28/$O28)*100 -> 34.689262 | BR28: =+(H28/$N28)*100 -> 26.485 | BS28: =+(I28/$O28)*100 -> 18.471833 | BT28: =+(J28/$N28)*100 -> 0 | BU28: =+(K28/$O28)*100 -> 0 | BV28: ND | BW28: ND | BX28: =+(N28/$N28)*100 -> 100 | BY28: =+(O28/$O28)*100 -> 100 | BZ28: ND | CA28: ND
A29: 35431 | B29: =+'[1]Senda Inflación Total'!F513 -> 20.62 | C29: =+'[1]Senda Inflación Total'!D513 -> 26.96 | D29: 21077.016 | E29: 1370.1327 | F29: 6988.0018 | G29: ='[2]Dic-96'!$E$618/1000 -> 879.57231 | H29: 10203.729 | I29: 507.85287 | L29: =+H29 -> 10203.729 | M29: =+I29 -> 507.85287 | N29: =+D29+F29+H29+J29 -> 38268.747 | O29: =+E29+G29+I29+K29 -> 2757.5579 | P29: =+L29+J29+F29+D29 -> 38268.747 | Q29: =+M29+K29+G29+E29 -> 2757.5579 | R29: =+D29+F29+L29 -> 38268.747 | S29: =+E29+G29+M29 -> 2757.5579 | V29: =+D29/D17*100-100 -> 28.74712 | W29: =+E29/E17*100-100 -> 80.444003 | X29: =+F29/F17*100-100 -> 1.3877294 | Y29: =+G29/G17*100-100 -> -0.47261494 | Z29: =+H29/H17*100-100 -> 36.608611 | AA29: =+I29/I17*100-100 -> 83.676275 | AD29: =+L29/L17*100-100 -> 36.608611 | AE29: =+M29/M17*100-100 -> 83.676275 | AF29: =+N29/N17*100-100 -> 24.521935 | AG29: =+O29/O17*100-100 -> 43.656151 | AH29: =+P29/P17*100-100 -> 24.521935 | AI29: =+Q29/Q17*100-100 -> 43.656151 | AJ29: =+R29/R17*100-100 -> 24.521935 | AK29: =+S29/S17*100-100 -> 43.656151 | AN29: =+(1+V29/100)/(1+$B29/100)*100-100 -> 6.7377882 | AO29: =+(1+W29/100)/(1+$B29/100)*100-100 -> 49.597084 | AP29: =+(1+X29/100)/(1+$B29/100)*100-100 -> -15.944512 | AQ29: =+(1+Y29/100)/(1+$B29/100)*100-100 -> -17.48683 | AR29: =+(1+Z29/100)/(1+$B29/100)*100-100 -> 13.255357 | AS29: =+(1+AA29/100)/(1+$B29/100)*100-100 -> 52.276799 | AT29: =+(1+AB29/100)/(1+$B29/100)*100-100 -> -17.095009 | AU29: =+(1+AC29/100)/(1+$B29/100)*100-100 -> -17.095009 | ... BC29: =+(1+AK29/100)/(1+$B29/100)*100-100 -> 19.098119 | BF29: =+(E29/D29)*100 -> 6.5006012 | BG29: =+(G29/F29)*100 -> 12.586893 | BH29: =+(I29/H29)*100 -> 4.9771302 | BI29: =+(K29/J29)*100 -> #DIV/0! | BJ29: =+(M29/L29)*100 -> 4.9771302 | BK29: =+(O29/N29)*100 -> 7.2057702 | BL29: =+(Q29/P29)*100 -> 7.2057702 | BM29: =+(S29/R29)*100 -> 7.2057702 | BN29: =+(D29/$N29)*100 -> 55.076316 | BO29: =+(E29/$O29)*100 -> 49.686454 | BP29: =+(F29/$N29)*100 -> 18.260336 | BQ29: =+(G29/$O29)*100 -> 31.896784 | BR29: =+(H29/$N29)*100 -> 26.663347 | BS29: =+(I29/$O29)*100 -> 18.416762 | BT29: =+(J29/$N29)*100 -> 0 | BU29: =+(K29/$O29)*100 -> 0 | BV29: ND | BW29: ND | BX29: =+(N29/$N29)*100 -> 100 | BY29: =+(O29/$O29)*100 -> 100 | BZ29: ND | CA29: ND
A30: 35462 | B30: =+'[1]Senda Inflación Total'!F514 -> 19.58 | C30: =+'[1]Senda Inflación Total'!D514 -> 27.8 | D30: 21385.497 | E30: 1380.4963 | F30: 7165.5649 | G30: 977.65909 | H30: 10418.016 | I30: 534.6808 | L30: =+H30 -> 10418.016 | M30: =+I30 -> 534.6808 | N30: =+D30+F30+H30+J30 -> 38969.078 | O30: =+E30+G30+I30+K30 -> 2892.8362 | P30: =+L30+J30+F30+D30 -> 38969.078 | Q30: =+M30+K30+G30+E30 -> 2892.8362 | R30: =+D30+F30+L30 -> 38969.078 | S30: =+E30+G30+M30 -> 2892.8362 | V30: =+D30/D18*100-100 -> 28.604932 | W30: =+E30/E18*100-100 -> 71.228785 | X30: =+F30/F18*100-100 -> 2.6021245 | Y30: =+G30/G18*100-100 -> 5.1521696 | Z30: =+H30/H18*100-100 -> 36.181982 | AA30: =+I30/I18*100-100 -> 88.96979 | AD30: =+L30/L18*100-100 -> 36.181982 | AE30: =+M30/M18*100-100 -> 88.96979 | AF30: =+N30/N18*100-100 -> 24.650243 | AG30: =+O30/O18*100-100 -> 43.285562 | AH30: =+P30/P18*100-100 -> 24.650243 | AI30: =+Q30/Q18*100-100 -> 43.285562 | AJ30: =+R30/R18*100-100 -> 24.650243 | AK30: =+S30/S18*100-100 -> 43.285562 | AN30: =+(1+V30/100)/(1+$B30/100)*100-100 -> 7.547192 | AO30: =+(1+W30/100)/(1+$B30/100)*100-100 -> 43.191825 | AP30: =+(1+X30/100)/(1+$B30/100)*100-100 -> -14.197922 | AQ30: =+(1+Y30/100)/(1+$B30/100)*100-100 -> -12.065421 | AR30: =+(1+Z30/100)/(1+$B30/100)*100-100 -> 13.883578 | AS30: =+(1+AA30/100)/(1+$B30/100)*100-100 -> 58.027923 | AT30: =+(1+AB30/100)/(1+$B30/100)*100-100 -> -16.373976 | AU30: =+(1+AC30/100)/(1+$B30/100)*100-100 -> -16.373976 | ... BC30: =+(1+AK30/100)/(1+$B30/100)*100-100 -> 19.824019 | BF30: =+(E30/D30)*100 -> 6.455292 | BG30: =+(G30/F30)*100 -> 13.643852 | BH30: =+(I30/H30)*100 -> 5.1322711 | BI30: =+(K30/J30)*100 -> #DIV/0! | BJ30: =+(M30/L30)*100 -> 5.1322711 | BK30: =+(O30/N30)*100 -> 7.4234145 | BL30: =+(Q30/P30)*100 -> 7.4234145 | BM30: =+(S30/R30)*100 -> 7.4234145 | BN30: =+(D30/$N30)*100 -> 54.87812 | BO30: =+(E30/$O30)*100 -> 47.721205 | BP30: =+(F30/$N30)*100 -> 18.387823 | BQ30: =+(G30/$O30)*100 -> 33.795868 | BR30: =+(H30/$N30)*100 -> 26.734057 | BS30: =+(I30/$O30)*100 -> 18.482927 | BT30: =+(J30/$N30)*100 -> 0 | BU30: =+(K30/$O30)*100 -> 0 | BV30: ND | BW30: ND | BX30: =+(N30/$N30)*100 -> 100 | BY30: =+(O30/$O30)*100 -> 100 | BZ30: ND | CA30: ND
A31: 35490 | B31: =+'[1]Senda Inflación Total'!F515 -> 18.93 | C31: =+'[1]Senda Inflación Total'!D515 -> 28.23 | D31: 21589.979 | E31: 1396.0562 | F31: 7285.6969 | G31: 1053.6412 | H31: 10652.597 | I31: 570.19793 | L31: =+H31 -> 10652.597 | M31: =+I31 -> 570.19793 | N31: =+D31+F31+H31+J31 -> 39528.273 | O31: =+E31+G31+I31+K31 -> 3019.8953 | P31: =+L31+J31+F31+D31 -> 39528.273 | Q31: =+M31+K31+G31+E31 -> 3019.8953 | R31: =+D31+F31+L31 -> 39528.273 | S31: =+E31+G31+M31 -> 3019.8953 | V31: =+D31/D19*100-100 -> 26.505703 | W31: =+E31/E19*100-100 -> 72.528978 | X31: =+F31/F19*100-100 -> 3.0672154 | Y31: =+G31/G19*100-100 -> 11.270403 | Z31: =+H31/H19*100-100 -> 35.61854 | AA31: =+I31/I19*100-100 -> 95.252254 | AD31: =+L31/L19*100-100 -> 35.61854 | AE31: =+M31/M19*100-100 -> 95.252254 | AF31: =+N31/N19*100-100 -> 23.56404 | AG31: =+O31/O19*100-100 -> 47.446973 | AH31: =+P31/P19*100-100 -> 23.56404 | AI31: =+Q31/Q19*100-100 -> 47.446973 | AJ31: =+R31/R19*100-100 -> 23.56404 | AK31: =+S31/S19*100-100 -> 47.446973 | AN31: =+(1+V31/100)/(1+$B31/100)*100-100 -> 6.3698839 | AO31: =+(1+W31/100)/(1+$B31/100)*100-100 -> 45.067669 | AP31: =+(1+X31/100)/(1+$B31/100)*100-100 -> -13.337917 | AQ31: =+(1+Y31/100)/(1+$B31/100)*100-100 -> -6.4404246 | AR31: =+(1+Z31/100)/(1+$B31/100)*100-100 -> 14.032237 | AS31: =+(1+AA31/100)/(1+$B31/100)*100-100 -> 64.174097 | AT31: =+(1+AB31/100)/(1+$B31/100)*100-100 -> -15.916926 | AU31: =+(1+AC31/100)/(1+$B31/100)*100-100 -> -15.916926 | ... BC31: =+(1+AK31/100)/(1+$B31/100)*100-100 -> 23.977947 | BF31: =+(E31/D31)*100 -> 6.4662231 | BG31: =+(G31/F31)*100 -> 14.461776 | BH31: =+(I31/H31)*100 -> 5.3526658 | BI31: =+(K31/J31)*100 -> #DIV/0! | BJ31: =+(M31/L31)*100 -> 5.3526658 | BK31: =+(O31/N31)*100 -> 7.6398362 | BL31: =+(Q31/P31)*100 -> 7.6398362 | BM31: =+(S31/R31)*100 -> 7.6398362 | BN31: =+(D31/$N31)*100 -> 54.61908 | BO31: =+(E31/$O31)*100 -> 46.228629 | BP31: =+(F31/$N31)*100 -> 18.431609 | BQ31: =+(G31/$O31)*100 -> 34.88999 | BR31: =+(H31/$N31)*100 -> 26.949311 | BS31: =+(I31/$O31)*100 -> 18.88138 | BT31: =+(J31/$N31)*100 -> 0 | BU31: =+(K31/$O31)*100 -> 0 | BV31: ND | BW31: ND | BX31: =+(N31/$N31)*100 -> 100 | BY31: =+(O31/$O31)*100 -> 100 | BZ31: ND | CA31: ND
A32: 35521 | B32: =+'[1]Senda Inflación Total'!F516 -> 18.52 | C32: =+'[1]Senda Inflación Total'!D516 -> 28.69 | D32: 21734.029 | E32: 1468.6465 | F32: 7264.2352 | G32: 958.53727 | H32: 10917.107 | I32: 588.46635 | L32: =+H32 -> 10917.107 | M32: =+I32 -> 588.46635 | N32: =+D32+F32+H32+J32 -> 39915.371 | O32: =+E32+G32+I32+K32 -> 3015.6501 | P32: =+L32+J32+F32+D32 -> 39915.371 | Q32: =+M32+K32+G32+E32 -> 3015.6501 | R32: =+D32+F32+L32 -> 39915.371 | S32: =+E32+G32+M32 -> 3015.6501 | V32: =+D32/D20*100-100 -> 25.615701 | W32: =+E32/E20*100-100 -> 63.951886 | X32: =+F32/F20*100-100 -> 1.3636244 | Y32: =+G32/G20*100-100 -> -3.6004404 | Z32: =+H32/H20*100-100 -> 35.995566 | AA32: =+I32/I20*100-100 -> 91.56249 | AD32: =+L32/L20*100-100 -> 35.995566 | AE32: =+M32/M20*100-100 -> 91.56249 | AF32: =+N32/N20*100-100 -> 22.831427 | AG32: =+O32/O20*100-100 -> 37.242837 | AH32: =+P32/P20*100-100 -> 22.831427 | AI32: =+Q32/Q20*100-100 -> 37.242837 | AJ32: =+R32/R20*100-100 -> 22.831427 | AK32: =+S32/S20*100-100 -> 37.242837 | AN32: =+(1+V32/100)/(1+$B32/100)*100-100 -> 5.9869227 | AO32: =+(1+W32/100)/(1+$B32/100)*100-100 -> 38.332675 | AP32: =+(1+X32/100)/(1+$B32/100)*100-100 -> -14.475511 | AQ32: =+(1+Y32/100)/(1+$B32/100)*100-100 -> -18.663888 | AR32: =+(1+Z32/100)/(1+$B32/100)*100-100 -> 14.744824 | AS32: =+(1+AA32/100)/(1+$B32/100)*100-100 -> 61.628831 | AT32: =+(1+AB32/100)/(1+$B32/100)*100-100 -> -15.626055 | AU32: =+(1+AC32/100)/(1+$B32/100)*100-100 -> -15.626055 | ... BC32: =+(1+AK32/100)/(1+$B32/100)*100-100 -> 15.797196 | BF32: =+(E32/D32)*100 -> 6.7573598 | BG32: =+(G32/F32)*100 -> 13.195295 | BH32: =+(I32/H32)*100 -> 5.3903139 | BI32: =+(K32/J32)*100 -> #DIV/0! | BJ32: =+(M32/L32)*100 -> 5.3903139 | BK32: =+(O32/N32)*100 -> 7.5551098 | BL32: =+(Q32/P32)*100 -> 7.5551098 | BM32: =+(S32/R32)*100 -> 7.5551098 | BN32: =+(D32/$N32)*100 -> 54.450273 | BO32: =+(E32/$O32)*100 -> 48.700825 | BP32: =+(F32/$N32)*100 -> 18.199092 | BQ32: =+(G32/$O32)*100 -> 31.785427 | BR32: =+(H32/$N32)*100 -> 27.350635 | BS32: =+(I32/$O32)*100 -> 19.513748 | BT32: =+(J32/$N32)*100 -> 0 | BU32: =+(K32/$O32)*100 -> 0 | BV32: ND | BW32: ND | BX32: =+(N32/$N32)*100 -> 100 | BY32: =+(O32/$O32)*100 -> 100 | BZ32: ND | CA32: ND
A33: 35551 | B33: =+'[1]Senda Inflación Total'!F517 -> 18.6 | C33: =+'[1]Senda Inflación Total'!D517 -> 29.16 | D33: 22207.357 | E33: 1473.2295 | F33: 7425.69 | G33: 959.12591 | H33: 11188.834 | I33: 639.09472 | L33: =+H33 -> 11188.834 | M33: =+I33 -> 639.09472 | N33: =+D33+F33+H33+J33 -> 40821.881 | O33: =+E33+G33+I33+K33 -> 3071.4501 | P33: =+L33+J33+F33+D33 -> 40821.881 | Q33: =+M33+K33+G33+E33 -> 3071.4501 | R33: =+D33+F33+L33 -> 40821.881 | S33: =+E33+G33+M33 -> 3071.4501 | V33: =+D33/D21*100-100 -> 25.505245 | W33: =+E33/E21*100-100 -> 59.292356 | X33: =+F33/F21*100-100 -> 3.1576187 | Y33: =+G33/G21*100-100 -> -2.4531104 | Z33: =+H33/H21*100-100 -> 34.956004 | AA33: =+I33/I21*100-100 -> 98.084107 | AD33: =+L33/L21*100-100 -> 34.956004 | AE33: =+M33/M21*100-100 -> 98.084107 | AF33: =+N33/N21*100-100 -> 23.018667 | AG33: =+O33/O21*100-100 -> 37.687317 | AH33: =+P33/P21*100-100 -> 23.018667 | AI33: =+Q33/Q21*100-100 -> 37.687317 | AJ33: =+R33/R21*100-100 -> 23.018667 | AK33: =+S33/S21*100-100 -> 37.687317 | AN33: =+(1+V33/100)/(1+$B33/100)*100-100 -> 5.8222978 | AO33: =+(1+W33/100)/(1+$B33/100)*100-100 -> 34.310587 | AP33: =+(1+X33/100)/(1+$B33/100)*100-100 -> -13.020558 | AQ33: =+(1+Y33/100)/(1+$B33/100)*100-100 -> -17.751358 | AR33: =+(1+Z33/100)/(1+$B33/100)*100-100 -> 13.790897 | AS33: =+(1+AA33/100)/(1+$B33/100)*100-100 -> 67.01864 | AT33: =+(1+AB33/100)/(1+$B33/100)*100-100 -> -15.682968 | AU33: =+(1+AC33/100)/(1+$B33/100)*100-100 -> -15.682968 | ... BC33: =+(1+AK33/100)/(1+$B33/100)*100-100 -> 16.093859 | BF33: =+(E33/D33)*100 -> 6.6339703 | BG33: =+(G33/F33)*100 -> 12.91632 | BH33: =+(I33/H33)*100 -> 5.7118975 | BI33: =+(K33/J33)*100 -> #DIV/0! | BJ33: =+(M33/L33)*100 -> 5.7118975 | BK33: =+(O33/N33)*100 -> 7.5240289 | BL33: =+(Q33/P33)*100 -> 7.5240289 | BM33: =+(S33/R33)*100 -> 7.5240289 | BN33: =+(D33/$N33)*100 -> 54.400622 | BO33: =+(E33/$O33)*100 -> 47.965275 | BP33: =+(F33/$N33)*100 -> 18.190465 | BQ33: =+(G33/$O33)*100 -> 31.227136 | BR33: =+(H33/$N33)*100 -> 27.408913 | BS33: =+(I33/$O33)*100 -> 20.807589 | BT33: =+(J33/$N33)*100 -> 0 | BU33: =+(K33/$O33)*100 -> 0 | BV33: ND | BW33: ND | BX33: =+(N33/$N33)*100 -> 100 | BY33: =+(O33/$O33)*100 -> 100 | BZ33: ND | CA33: ND
A34: 35582 | B34: =+'[1]Senda Inflación Total'!F518 -> 18.67 | C34: =+'[1]Senda Inflación Total'!D518 -> 29.51 | D34: 22852.38 | E34: 1415.9463 | F34: 7612.3735 | G34: 954.54847 | H34: 11438.714 | I34: 676.12544 | L34: =+H34 -> 11438.714 | M34: =+I34 -> 676.12544 | N34: =+D34+F34+H34+J34 -> 41903.467 | O34: =+E34+G34+I34+K34 -> 3046.6202 | P34: =+L34+J34+F34+D34 -> 41903.467 | Q34: =+M34+K34+G34+E34 -> 3046.6202 | R34: =+D34+F34+L34 -> 41903.467 | S34: =+E34+G34+M34 -> 3046.6202 | V34: =+D34/D22*100-100 -> 27.085802 | W34: =+E34/E22*100-100 -> 56.641678 | X34: =+F34/F22*100-100 -> 5.318153 | Y34: =+G34/G22*100-100 -> -3.3895168 | Z34: =+H34/H22*100-100 -> 34.129541 | AA34: =+I34/I22*100-100 -> 100.94216 | AD34: =+L34/L22*100-100 -> 34.129541 | AE34: =+M34/M22*100-100 -> 100.94216 | AF34: =+N34/N22*100-100 -> 24.202807 | AG34: =+O34/O22*100-100 -> 36.714428 | AH34: =+P34/P22*100-100 -> 24.202807 | AI34: =+Q34/Q22*100-100 -> 36.714428 | AJ34: =+R34/R22*100-100 -> 24.202807 | AK34: =+S34/S22*100-100 -> 36.714428 | AN34: =+(1+V34/100)/(1+$B34/100)*100-100 -> 7.0917688 | AO34: =+(1+W34/100)/(1+$B34/100)*100-100 -> 31.997706 | AP34: =+(1+X34/100)/(1+$B34/100)*100-100 -> -11.25124 | AQ34: =+(1+Y34/100)/(1+$B34/100)*100-100 -> -18.588958 | AR34: =+(1+Z34/100)/(1+$B34/100)*100-100 -> 13.027337 | AS34: =+(1+AA34/100)/(1+$B34/100)*100-100 -> 69.328525 | AT34: =+(1+AB34/100)/(1+$B34/100)*100-100 -> -15.732704 | AU34: =+(1+AC34/100)/(1+$B34/100)*100-100 -> -15.732704 | ... BC34: =+(1+AK34/100)/(1+$B34/100)*100-100 -> 15.205551 | BF34: =+(E34/D34)*100 -> 6.1960562 | BG34: =+(G34/F34)*100 -> 12.539433 | BH34: =+(I34/H34)*100 -> 5.910852 | BI34: =+(K34/J34)*100 -> #DIV/0! | BJ34: =+(M34/L34)*100 -> 5.910852 | BK34: =+(O34/N34)*100 -> 7.2705684 | BL34: =+(Q34/P34)*100 -> 7.2705684 | BM34: =+(S34/R34)*100 -> 7.2705684 | BN34: =+(D34/$N34)*100 -> 54.535773 | BO34: =+(E34/$O34)*100 -> 46.47597 | BP34: =+(F34/$N34)*100 -> 18.166453 | BQ34: =+(G34/$O34)*100 -> 31.33139 | BR34: =+(H34/$N34)*100 -> 27.297774 | BS34: =+(I34/$O34)*100 -> 22.192639 | BT34: =+(J34/$N34)*100 -> 0 | BU34: =+(K34/$O34)*100 -> 0 | BV34: ND | BW34: ND | BX34: =+(N34/$N34)*100 -> 100 | BY34: =+(O34/$O34)*100 -> 100 | BZ34: ND | CA34: ND
A35: 35612 | B35: =+'[1]Senda Inflación Total'!F519 -> 17.88 | C35: =+'[1]Senda Inflación Total'!D519 -> 29.76 | D35: 23205.824 | E35: 1502.1345 | F35: 7753.0286 | G35: 923.17376 | H35: 11731.616 | I35: 726.17555 | L35: =+H35 -> 11731.616 | M35: =+I35 -> 726.17555 | N35: =+D35+F35+H35+J35 -> 42690.468 | O35: =+E35+G35+I35+K35 -> 3151.4839 | P35: =+L35+J35+F35+D35 -> 42690.468 | Q35: =+M35+K35+G35+E35 -> 3151.4839 | R35: =+D35+F35+L35 -> 42690.468 | S35: =+E35+G35+M35 -> 3151.4839 | V35: =+D35/D23*100-100 -> 27.457011 | W35: =+E35/E23*100-100 -> 48.306833 | X35: =+F35/F23*100-100 -> 5.5474321 | Y35: =+G35/G23*100-100 -> -9.3678918 | Z35: =+H35/H23*100-100 -> 33.49315 | AA35: =+I35/I23*100-100 -> 107.0814 | AD35: =+L35/L23*100-100 -> 33.49315 | AE35: =+M35/M23*100-100 -> 107.0814 | AF35: =+N35/N23*100-100 -> 24.31521 | AG35: =+O35/O23*100-100 -> 32.297328 | AH35: =+P35/P23*100-100 -> 24.31521 | AI35: =+Q35/Q23*100-100 -> 32.297328 | AJ35: =+R35/R23*100-100 -> 24.31521 | AK35: =+S35/S23*100-100 -> 32.297328 | AN35: =+(1+V35/100)/(1+$B35/100)*100-100 -> 8.1243729 | AO35: =+(1+W35/100)/(1+$B35/100)*100-100 -> 25.811701 | AP35: =+(1+X35/100)/(1+$B35/100)*100-100 -> -10.461968 | AQ35: =+(1+Y35/100)/(1+$B35/100)*100-100 -> -23.11494 | AR35: =+(1+Z35/100)/(1+$B35/100)*100-100 -> 13.244952 | AS35: =+(1+AA35/100)/(1+$B35/100)*100-100 -> 75.671359 | AT35: =+(1+AB35/100)/(1+$B35/100)*100-100 -> -15.167967 | AU35: =+(1+AC35/100)/(1+$B35/100)*100-100 -> -15.167967 | ... BC35: =+(1+AK35/100)/(1+$B35/100)*100-100 -> 12.230512 | BF35: =+(E35/D35)*100 -> 6.4730931 | BG35: =+(G35/F35)*100 -> 11.907266 | BH35: =+(I35/H35)*100 -> 6.1899024 | BI35: =+(K35/J35)*100 -> #DIV/0! | BJ35: =+(M35/L35)*100 -> 6.1899024 | BK35: =+(O35/N35)*100 -> 7.3821723 | BL35: =+(Q35/P35)*100 -> 7.3821723 | BM35: =+(S35/R35)*100 -> 7.3821723 | BN35: =+(D35/$N35)*100 -> 54.358326 | BO35: =+(E35/$O35)*100 -> 47.664358 | BP35: =+(F35/$N35)*100 -> 18.16103 | BQ35: =+(G35/$O35)*100 -> 29.293304 | BR35: =+(H35/$N35)*100 -> 27.480644 | BS35: =+(I35/$O35)*100 -> 23.042338 | BT35: =+(J35/$N35)*100 -> 0 | BU35: =+(K35/$O35)*100 -> 0 | BV35: ND | BW35: ND | BX35: =+(N35/$N35)*100 -> 100 | BY35: =+(O35/$O35)*100 -> 100 | BZ35: ND | CA35: ND
A36: 35643 | B36: =+'[1]Senda Inflación Total'!F520 -> 17.93 | C36: =+'[1]Senda Inflación Total'!D520 -> 30.1 | D36: 23628.86 | E36: 1568.0921 | F36: 7956.2143 | G36: 974.91028 | H36: 11969.751 | I36: 744.07511 | L36: =+H36 -> 11969.751 | M36: =+I36 -> 744.07511 | N36: =+D36+F36+H36+J36 -> 43554.826 | O36: =+E36+G36+I36+K36 -> 3287.0775 | P36: =+L36+J36+F36+D36 -> 43554.826 | Q36: =+M36+K36+G36+E36 -> 3287.0775 | R36: =+D36+F36+L36 -> 43554.826 | S36: =+E36+G36+M36 -> 3287.0775 | V36: =+D36/D24*100-100 -> 28.233288 | W36: =+E36/E24*100-100 -> 41.922711 | X36: =+F36/F24*100-100 -> 7.2508939 | Y36: =+G36/G24*100-100 -> -6.9521821 | Z36: =+H36/H24*100-100 -> 32.389467 | AA36: =+I36/I24*100-100 -> 104.27206 | AD36: =+L36/L24*100-100 -> 32.389467 | AE36: =+M36/M24*100-100 -> 104.27206 | AF36: =+N36/N24*100-100 -> 24.848651 | AG36: =+O36/O24*100-100 -> 30.600221 | AH36: =+P36/P24*100-100 -> 24.848651 | AI36: =+Q36/Q24*100-100 -> 30.600221 | AJ36: =+R36/R24*100-100 -> 24.848651 | AK36: =+S36/S24*100-100 -> 30.600221 | AN36: =+(1+V36/100)/(1+$B36/100)*100-100 -> 8.7367828 | AO36: =+(1+W36/100)/(1+$B36/100)*100-100 -> 20.344875 | AP36: =+(1+X36/100)/(1+$B36/100)*100-100 -> -9.0554618 | AQ36: =+(1+Y36/100)/(1+$B36/100)*100-100 -> -21.099111 | AR36: =+(1+Z36/100)/(1+$B36/100)*100-100 -> 12.261059 | AS36: =+(1+AA36/100)/(1+$B36/100)*100-100 -> 73.214674 | AT36: =+(1+AB36/100)/(1+$B36/100)*100-100 -> -15.203935 | AU36: =+(1+AC36/100)/(1+$B36/100)*100-100 -> -15.203935 | ... BC36: =+(1+AK36/100)/(1+$B36/100)*100-100 -> 10.743849 | BF36: =+(E36/D36)*100 -> 6.6363425 | BG36: =+(G36/F36)*100 -> 12.253444 | BH36: =+(I36/H36)*100 -> 6.2162957 | BI36: =+(K36/J36)*100 -> #DIV/0! | BJ36: =+(M36/L36)*100 -> 6.2162957 | BK36: =+(O36/N36)*100 -> 7.5469881 | BL36: =+(Q36/P36)*100 -> 7.5469881 | BM36: =+(S36/R36)*100 -> 7.5469881 | BN36: =+(D36/$N36)*100 -> 54.250844 | BO36: =+(E36/$O36)*100 -> 47.70475 | BP36: =+(F36/$N36)*100 -> 18.267125 | BQ36: =+(G36/$O36)*100 -> 29.658877 | BR36: =+(H36/$N36)*100 -> 27.482032 | BS36: =+(I36/$O36)*100 -> 22.636373 | BT36: =+(J36/$N36)*100 -> 0 | BU36: =+(K36/$O36)*100 -> 0 | BV36: ND | BW36: ND | BX36: =+(N36/$N36)*100 -> 100 | BY36: =+(O36/$O36)*100 -> 100 | BZ36: ND | CA36: ND
A37: 35674 | B37: =+'[1]Senda Inflación Total'!F521 -> 18.01 | C37: =+'[1]Senda Inflación Total'!D521 -> 30.48 | D37: 24548.412 | E37: 1569.0705 | F37: 8156.3477 | G37: 959.545 | H37: 12254.176 | I37: 758.47443 | L37: =+H37 -> 12254.176 | M37: =+I37 -> 758.47443 | N37: =+D37+F37+H37+J37 -> 44958.936 | O37: =+E37+G37+I37+K37 -> 3287.09 | P37: =+L37+J37+F37+D37 -> 44958.936 | Q37: =+M37+K37+G37+E37 -> 3287.0899 | R37: =+D37+F37+L37 -> 44958.936 | S37: =+E37+G37+M37 -> 3287.09 | V37: =+D37/D25*100-100 -> 31.252095 | W37: =+E37/E25*100-100 -> 44.11211 | X37: =+F37/F25*100-100 -> 8.6736806 | Y37: =+G37/G25*100-100 -> -9.7497822 | Z37: =+H37/H25*100-100 -> 31.960146 | AA37: =+I37/I25*100-100 -> 94.674034 | AD37: =+L37/L25*100-100 -> 31.960146 | AE37: =+M37/M25*100-100 -> 94.674034 | AF37: =+N37/N25*100-100 -> 26.663155 | AG37: =+O37/O25*100-100 -> 29.331401 | AH37: =+P37/P25*100-100 -> 26.663155 | AI37: =+Q37/Q25*100-100 -> 29.331401 | AJ37: =+R37/R25*100-100 -> 26.663155 | AK37: =+S37/S25*100-100 -> 29.331401 | AN37: =+(1+V37/100)/(1+$B37/100)*100-100 -> 11.221164 | AO37: =+(1+W37/100)/(1+$B37/100)*100-100 -> 22.118558 | AP37: =+(1+X37/100)/(1+$B37/100)*100-100 -> -7.9114646 | AQ37: =+(1+Y37/100)/(1+$B37/100)*100-100 -> -23.523246 | AR37: =+(1+Z37/100)/(1+$B37/100)*100-100 -> 11.821156 | AS37: =+(1+AA37/100)/(1+$B37/100)*100-100 -> 64.964015 | AT37: =+(1+AB37/100)/(1+$B37/100)*100-100 -> -15.261419 | AU37: =+(1+AC37/100)/(1+$B37/100)*100-100 -> -15.261419 | ... BC37: =+(1+AK37/100)/(1+$B37/100)*100-100 -> 9.5935949 | BF37: =+(E37/D37)*100 -> 6.3917394 | BG37: =+(G37/F37)*100 -> 11.764395 | BH37: =+(I37/H37)*100 -> 6.1895181 | BI37: =+(K37/J37)*100 -> #DIV/0! | BJ37: =+(M37/L37)*100 -> 6.1895181 | BK37: =+(O37/N37)*100 -> 7.3113162 | BL37: =+(Q37/P37)*100 -> 7.3113162 | BM37: =+(S37/R37)*100 -> 7.3113162 | BN37: =+(D37/$N37)*100 -> 54.601853 | BO37: =+(E37/$O37)*100 -> 47.734335 | BP37: =+(F37/$N37)*100 -> 18.141772 | BQ37: =+(G37/$O37)*100 -> 29.191322 | BR37: =+(H37/$N37)*100 -> 27.256374 | BS37: =+(I37/$O37)*100 -> 23.074344 | BT37: =+(J37/$N37)*100 -> 0 | BU37: =+(K37/$O37)*100 -> 0 | BV37: ND | BW37: ND | BX37: =+(N37/$N37)*100 -> 100 | BY37: =+(O37/$O37)*100 -> 100 | BZ37: ND | CA37: ND
A38: 35704 | B38: =+'[1]Senda Inflación Total'!F522 -> 17.8 | C38: =+'[1]Senda Inflación Total'!D522 -> 30.77 | D38: 25270.293 | E38: 1562.3388 | F38: 8321.3743 | G38: 950.9166 | H38: 12540.92 | I38: 808.11736 | L38: =+H38 -> 12540.92 | M38: =+I38 -> 808.11736 | N38: =+D38+F38+H38+J38 -> 46132.588 | O38: =+E38+G38+I38+K38 -> 3321.3727 | P38: =+L38+J38+F38+D38 -> 46132.588 | Q38: =+M38+K38+G38+E38 -> 3321.3727 | R38: =+D38+F38+L38 -> 46132.588 | S38: =+E38+G38+M38 -> 3321.3727 | V38: =+D38/D26*100-100 -> 34.212065 | W38: =+E38/E26*100-100 -> 31.137781 | X38: =+F38/F26*100-100 -> 11.010833 | Y38: =+G38/G26*100-100 -> -12.564705 | Z38: =+H38/H26*100-100 -> 32.342716 | AA38: =+I38/I26*100-100 -> 97.080136 | AD38: =+L38/L26*100-100 -> 32.342716 | AE38: =+M38/M26*100-100 -> 97.080136 | AF38: =+N38/N26*100-100 -> 28.859363 | AG38: =+O38/O26*100-100 -> 23.517798 | AH38: =+P38/P26*100-100 -> 28.859363 | AI38: =+Q38/Q26*100-100 -> 23.517798 | AJ38: =+R38/R26*100-100 -> 28.859363 | AK38: =+S38/S26*100-100 -> 23.517798 | AN38: =+(1+V38/100)/(1+$B38/100)*100-100 -> 13.932143 | AO38: =+(1+W38/100)/(1+$B38/100)*100-100 -> 11.322394 | AP38: =+(1+X38/100)/(1+$B38/100)*100-100 -> -5.7632995 | AQ38: =+(1+Y38/100)/(1+$B38/100)*100-100 -> -25.77649 | AR38: =+(1+Z38/100)/(1+$B38/100)*100-100 -> 12.34526 | AS38: =+(1+AA38/100)/(1+$B38/100)*100-100 -> 67.300624 | AT38: =+(1+AB38/100)/(1+$B38/100)*100-100 -> -15.110357 | AU38: =+(1+AC38/100)/(1+$B38/100)*100-100 -> -15.110357 | ... BC38: =+(1+AK38/100)/(1+$B38/100)*100-100 -> 4.8538185 | BF38: =+(E38/D38)*100 -> 6.1825113 | BG38: =+(G38/F38)*100 -> 11.427398 | BH38: =+(I38/H38)*100 -> 6.4438444 | BI38: =+(K38/J38)*100 -> #DIV/0! | BJ38: =+(M38/L38)*100 -> 6.4438444 | BK38: =+(O38/N38)*100 -> 7.1996237 | BL38: =+(Q38/P38)*100 -> 7.1996237 | BM38: =+(S38/R38)*100 -> 7.1996237 | BN38: =+(D38/$N38)*100 -> 54.777533 | BO38: =+(E38/$O38)*100 -> 47.038947 | BP38: =+(F38/$N38)*100 -> 18.037953 | BQ38: =+(G38/$O38)*100 -> 28.630229 | BR38: =+(H38/$N38)*100 -> 27.184514 | BS38: =+(I38/$O38)*100 -> 24.330824 | BT38: =+(J38/$N38)*100 -> 0 | BU38: =+(K38/$O38)*100 -> 0 | BV38: ND | BW38: ND | BX38: =+(N38/$N38)*100 -> 100 | BY38: =+(O38/$O38)*100 -> 100 | BZ38: ND | CA38: ND
A39: 35735 | B39: =+'[1]Senda Inflación Total'!F523 -> 17.81 | C39: =+'[1]Senda Inflación Total'!D523 -> 31.02 | D39: 25916.285 | E39: 1613.2791 | F39: 8551.3068 | G39: 1020.0775 | H39: 12853.508 | I39: 831.37219 | L39: =+H39 -> 12853.508 | M39: =+I39 -> 831.37219 | N39: =+D39+F39+H39+J39 -> 47321.1 | O39: =+E39+G39+I39+K39 -> 3464.7288 | P39: =+L39+J39+F39+D39 -> 47321.1 | Q39: =+M39+K39+G39+E39 -> 3464.7288 | R39: =+D39+F39+L39 -> 47321.1 | S39: =+E39+G39+M39 -> 3464.7288 | V39: =+D39/D27*100-100 -> 33.003407 | W39: =+E39/E27*100-100 -> 28.682915 | X39: =+F39/F27*100-100 -> 15.778328 | Y39: =+G39/G27*100-100 -> -7.2882602 | Z39: =+H39/H27*100-100 -> 32.087505 | AA39: =+I39/I27*100-100 -> 87.244011 | AD39: =+L39/L27*100-100 -> 32.087505 | AE39: =+M39/M27*100-100 -> 87.244011 | AF39: =+N39/N27*100-100 -> 29.284092 | AG39: =+O39/O27*100-100 -> 23.830616 | AH39: =+P39/P27*100-100 -> 29.284092 | AI39: =+Q39/Q27*100-100 -> 23.830616 | AJ39: =+R39/R27*100-100 -> 29.284092 | AK39: =+S39/S27*100-100 -> 23.830616 | AN39: =+(1+V39/100)/(1+$B39/100)*100-100 -> 12.896534 | AO39: =+(1+W39/100)/(1+$B39/100)*100-100 -> 9.2291952 | AP39: =+(1+X39/100)/(1+$B39/100)*100-100 -> -1.7245329 | AQ39: =+(1+Y39/100)/(1+$B39/100)*100-100 -> -21.304015 | AR39: =+(1+Z39/100)/(1+$B39/100)*100-100 -> 12.119094 | AS39: =+(1+AA39/100)/(1+$B39/100)*100-100 -> 58.937281 | AT39: =+(1+AB39/100)/(1+$B39/100)*100-100 -> -15.117562 | AU39: =+(1+AC39/100)/(1+$B39/100)*100-100 -> -15.117562 | ... BC39: =+(1+AK39/100)/(1+$B39/100)*100-100 -> 5.1104456 | BF39: =+(E39/D39)*100 -> 6.2249626 | BG39: =+(G39/F39)*100 -> 11.928908 | BH39: =+(I39/H39)*100 -> 6.4680566 | BI39: =+(K39/J39)*100 -> #DIV/0! | BJ39: =+(M39/L39)*100 -> 6.4680566 | BK39: =+(O39/N39)*100 -> 7.3217419 | BL39: =+(Q39/P39)*100 -> 7.3217419 | BM39: =+(S39/R39)*100 -> 7.3217419 | BN39: =+(D39/$N39)*100 -> 54.76687 | BO39: =+(E39/$O39)*100 -> 46.562925 | BP39: =+(F39/$N39)*100 -> 18.070811 | BQ39: =+(G39/$O39)*100 -> 29.441772 | BR39: =+(H39/$N39)*100 -> 27.162319 | BS39: =+(I39/$O39)*100 -> 23.995303 | BT39: =+(J39/$N39)*100 -> 0 | BU39: =+(K39/$O39)*100 -> 0 | BV39: ND | BW39: ND | BX39: =+(N39/$N39)*100 -> 100 | BY39: =+(O39/$O39)*100 -> 100 | BZ39: ND | CA39: ND
A40: 35765 | B40: =+'[1]Senda Inflación Total'!F524 -> 17.68 | C40: =+'[1]Senda Inflación Total'!D524 -> 31.21 | D40: 26517.463 | E40: 1433.2468 | F40: 8649.025 | G40: 942.86737 | H40: 13219.207 | I40: 849.46852 | L40: =+H40 -> 13219.207 | M40: =+I40 -> 849.46852 | N40: =+D40+F40+H40+J40 -> 48385.696 | O40: =+E40+G40+I40+K40 -> 3225.5827 | P40: =+L40+J40+F40+D40 -> 48385.696 | Q40: =+M40+K40+G40+E40 -> 3225.5827 | R40: =+D40+F40+L40 -> 48385.696 | S40: =+E40+G40+M40 -> 3225.5827 | V40: =+D40/D28*100-100 -> 26.80688 | W40: =+E40/E28*100-100 -> 20.680677 | X40: =+F40/F28*100-100 -> 27.530012 | Y40: =+G40/G28*100-100 -> 7.1961118 | Z40: =+H40/H28*100-100 -> 32.49555 | AA40: =+I40/I28*100-100 -> 81.368052 | AD40: =+L40/L28*100-100 -> 32.49555 | AE40: =+M40/M28*100-100 -> 81.368052 | AF40: =+N40/N28*100-100 -> 28.443711 | AG40: =+O40/O28*100-100 -> 27.213051 | AH40: =+P40/P28*100-100 -> 28.443711 | AI40: =+Q40/Q28*100-100 -> 27.213051 | AJ40: =+R40/R28*100-100 -> 28.443711 | AK40: =+S40/S28*100-100 -> 27.213051 | AN40: =+(1+V40/100)/(1+$B40/100)*100-100 -> 7.7556764 | AO40: =+(1+W40/100)/(1+$B40/100)*100-100 -> 2.5498617 | AP40: =+(1+X40/100)/(1+$B40/100)*100-100 -> 8.3701669 | AQ40: =+(1+Y40/100)/(1+$B40/100)*100-100 -> -8.9088105 | AR40: =+(1+Z40/100)/(1+$B40/100)*100-100 -> 12.589692 | AS40: =+(1+AA40/100)/(1+$B40/100)*100-100 -> 54.11969 | AT40: =+(1+AB40/100)/(1+$B40/100)*100-100 -> -15.023793 | AU40: =+(1+AC40/100)/(1+$B40/100)*100-100 -> -15.023793 | ... BC40: =+(1+AK40/100)/(1+$B40/100)*100-100 -> 8.1008254 | BF40: =+(E40/D40)*100 -> 5.4049168 | BG40: =+(G40/F40)*100 -> 10.90143 | BH40: =+(I40/H40)*100 -> 6.426017 | BI40: =+(K40/J40)*100 -> #DIV/0! | BJ40: =+(M40/L40)*100 -> 6.426017 | BK40: =+(O40/N40)*100 -> 6.6663973 | BL40: =+(Q40/P40)*100 -> 6.6663973 | BM40: =+(S40/R40)*100 -> 6.6663973 | BN40: =+(D40/$N40)*100 -> 54.804344 | BO40: =+(E40/$O40)*100 -> 44.433734 | BP40: =+(F40/$N40)*100 -> 17.875169 | BQ40: =+(G40/$O40)*100 -> 29.230916 | BR40: =+(H40/$N40)*100 -> 27.320486 | BS40: =+(I40/$O40)*100 -> 26.335351 | BT40: =+(J40/$N40)*100 -> 0 | BU40: =+(K40/$O40)*100 -> 0 | BV40: ND | BW40: ND | BX40: =+(N40/$N40)*100 -> 100 | BY40: =+(O40/$O40)*100 -> 100 | BZ40: ND | CA40: ND
A41: 35796 | B41: =+'[1]Senda Inflación Total'!F525 -> 17.84 | C41: =+'[1]Senda Inflación Total'!D525 -> 31.77 | D41: 25467.349 | E41: 1515.5727 | F41: 8460.9481 | G41: 956.85044 | H41: 13486.579 | I41: 896.38633 | L41: =+H41 -> 13486.579 | M41: =+I41 -> 896.38633 | N41: =+D41+F41+H41+J41 -> 47414.876 | O41: =+E41+G41+I41+K41 -> 3368.8095 | P41: =+L41+J41+F41+D41 -> 47414.876 | Q41: =+M41+K41+G41+E41 -> 3368.8095 | R41: =+D41+F41+L41 -> 47414.876 | S41: =+E41+G41+M41 -> 3368.8095 | V41: =+D41/D29*100-100 -> 20.829955 | W41: =+E41/E29*100-100 -> 10.615028 | X41: =+F41/F29*100-100 -> 21.07822 | Y41: =+G41/G29*100-100 -> 8.7858757 | Z41: =+H41/H29*100-100 -> 32.173041 | AA41: =+I41/I29*100-100 -> 76.505122 | AD41: =+L41/L29*100-100 -> 32.173041 | AE41: =+M41/M29*100-100 -> 76.505122 | AF41: =+N41/N29*100-100 -> 23.899735 | AG41: =+O41/O29*100-100 -> 22.166409 | AH41: =+P41/P29*100-100 -> 23.899735 | AI41: =+Q41/Q29*100-100 -> 22.166409 | AJ41: =+R41/R29*100-100 -> 23.899735 | AK41: =+S41/S29*100-100 -> 22.166409 | AN41: =+(1+V41/100)/(1+$B41/100)*100-100 -> 2.5373006 | AO41: =+(1+W41/100)/(1+$B41/100)*100-100 -> -6.1311708 | AP41: =+(1+X41/100)/(1+$B41/100)*100-100 -> 2.7479799 | AQ41: =+(1+Y41/100)/(1+$B41/100)*100-100 -> -7.6834049 | AR41: =+(1+Z41/100)/(1+$B41/100)*100-100 -> 12.163137 | AS41: =+(1+AA41/100)/(1+$B41/100)*100-100 -> 49.783709 | AT41: =+(1+AB41/100)/(1+$B41/100)*100-100 -> -15.139172 | AU41: =+(1+AC41/100)/(1+$B41/100)*100-100 -> -15.139172 | ... BC41: =+(1+AK41/100)/(1+$B41/100)*100-100 -> 3.6714265 | BF41: =+(E41/D41)*100 -> 5.9510424 | BG41: =+(G41/F41)*100 -> 11.309021 | BH41: =+(I41/H41)*100 -> 6.6465065 | BI41: =+(K41/J41)*100 -> #DIV/0! | BJ41: =+(M41/L41)*100 -> 6.6465065 | BK41: =+(O41/N41)*100 -> 7.1049633 | BL41: =+(Q41/P41)*100 -> 7.1049633 | BM41: =+(S41/R41)*100 -> 7.1049633 | BN41: =+(D41/$N41)*100 -> 53.711728 | BO41: =+(E41/$O41)*100 -> 44.988377 | BP41: =+(F41/$N41)*100 -> 17.844501 | BQ41: =+(G41/$O41)*100 -> 28.403222 | BR41: =+(H41/$N41)*100 -> 28.443771 | BS41: =+(I41/$O41)*100 -> 26.608401 | BT41: =+(J41/$N41)*100 -> 0 | BU41: =+(K41/$O41)*100 -> 0 | BV41: ND | BW41: ND | BX41: =+(N41/$N41)*100 -> 100 | BY41: =+(O41/$O41)*100 -> 100 | BZ41: ND | CA41: ND
... A88: 37226 | B88: =+'[1]Senda Inflación Total'!F572 -> 7.65 | C88: =+'[1]Senda Inflación Total'!D572 -> 46.58 | D88: 27829.868 | E88: 1426.5809 | F88: 7458.2705 | G88: 553.43186 | H88: 12404.667 | I88: 2659.6294 | L88: =+H88 -> 12404.667 | M88: =+I88 -> 2659.6294 | N88: =+D88+F88+H88+J88 -> 47692.806 | O88: =+E88+G88+I88+K88 -> 4639.6422 | P88: =+L88+J88+F88+D88 -> 47692.806 | Q88: =+M88+K88+G88+E88 -> 4639.6422 | R88: =+D88+F88+L88 -> 47692.806 | S88: =+E88+G88+M88 -> 4639.6422 | V88: =+D88/D76*100-100 -> 0.35032685 | W88: =+E88/E76*100-100 -> -25.548444 | X88: =+F88/F76*100-100 -> 11.885605 | Y88: =+G88/G76*100-100 -> -26.943183 | Z88: =+H88/H76*100-100 -> -3.4896278 | AA88: =+I88/I76*100-100 -> 4.8382441 | AD88: =+L88/L76*100-100 -> -3.4896278 | AE88: =+M88/M76*100-100 -> 4.8382441 | AF88: =+N88/N76*100-100 -> 0.93312316 | AG88: =+O88/O76*100-100 -> -10.956672 | AH88: =+P88/P76*100-100 -> 0.93312316 | AI88: =+Q88/Q76*100-100 -> -10.956672 | AJ88: =+R88/R76*100-100 -> 0.93312316 | AK88: =+S88/S76*100-100 -> -10.956672 | AN88: =+(1+V88/100)/(1+$B88/100)*100-100 -> -6.7809319 | AO88: =+(1+W88/100)/(1+$B88/100)*100-100 -> -30.839242 | AP88: =+(1+X88/100)/(1+$B88/100)*100-100 -> 3.9346072 | AQ88: =+(1+Y88/100)/(1+$B88/100)*100-100 -> -32.134865 | AR88: =+(1+Z88/100)/(1+$B88/100)*100-100 -> -10.348005 | AS88: =+(1+AA88/100)/(1+$B88/100)*100-100 -> -2.6119424 | AT88: =+(1+AB88/100)/(1+$B88/100)*100-100 -> -7.1063632 | AU88: =+(1+AC88/100)/(1+$B88/100)*100-100 -> -7.1063632 | ... BC88: =+(1+AK88/100)/(1+$B88/100)*100-100 -> -17.284415 | BF88: =+(E88/D88)*100 -> 5.1260785 | BG88: =+(G88/F88)*100 -> 7.4203779 | BH88: =+(I88/H88)*100 -> 21.440554 | BI88: =+(K88/J88)*100 -> #DIV/0! | BJ88: =+(M88/L88)*100 -> 21.440554 | BK88: =+(O88/N88)*100 -> 9.7281803 | BL88: =+(Q88/P88)*100 -> 9.7281803 | BM88: =+(S88/R88)*100 -> 9.7281803 | BN88: =+(D88/$N88)*100 -> 58.35234 | BO88: =+(E88/$O88)*100 -> 30.747649 | BP88: =+(F88/$N88)*100 -> 15.638146 | BQ88: =+(G88/$O88)*100 -> 11.928331 | BR88: =+(H88/$N88)*100 -> 26.009514 | BS88: =+(I88/$O88)*100 -> 57.32402 | BT88: =+(J88/$N88)*100 -> 0 | BU88: =+(K88/$O88)*100 -> 0 | BV88: ND | BW88: ND | BX88: =+(N88/$N88)*100 -> 100 | BY88: =+(O88/$O88)*100 -> 100 | BZ88: ND | CA88: ND
A89: 37257 | B89: =+'[1]Senda Inflación Total'!F573 -> 7.37 | C89: =+'[1]Senda Inflación Total'!D573 -> 46.95 | D89: 27956.067 | E89: 1794.7543 | F89: 6706.3182 | G89: 526.44728 | H89: 12158.395 | I89: 2684.1704 | J89: 262.3412 | K89: 23.93683 | L89: =+H89 -> 12158.395 | M89: =+I89 -> 2684.1704 | N89: =+D89+F89+H89+J89 -> 47083.121 | O89: =+E89+G89+I89+K89 -> 5029.3088 | P89: =+L89+J89+F89+D89 -> 47083.121 | Q89: =+M89+K89+G89+E89 -> 5029.3088 | R89: =+D89+F89+L89 -> 46820.78 | S89: =+E89+G89+M89 -> 5005.372 | V89: =+D89/D77*100-100 -> 2.0085011 | W89: =+E89/E77*100-100 -> -12.992932 | X89: =+F89/F77*100-100 -> 0.53872437 | Y89: =+G89/G77*100-100 -> -28.831753 | Z89: =+H89/H77*100-100 -> -4.9227164 | AA89: =+I89/I77*100-100 -> 3.1337431 | AD89: =+L89/L77*100-100 -> -4.9227164 | AE89: =+M89/M77*100-100 -> 3.1337431 | AF89: =+N89/N77*100-100 -> 0.46775014 | AG89: =+O89/O77*100-100 -> -6.9525607 | AH89: =+P89/P77*100-100 -> 0.46775014 | AI89: =+Q89/Q77*100-100 -> -6.9525607 | AJ89: =+R89/R77*100-100 -> -0.092043462 | AK89: =+S89/S77*100-100 -> -7.3954169 | AN89: =+(1+V89/100)/(1+$B89/100)*100-100 -> -4.9934795 | AO89: =+(1+W89/100)/(1+$B89/100)*100-100 -> -18.965197 | AP89: =+(1+X89/100)/(1+$B89/100)*100-100 -> -6.362369 | AQ89: =+(1+Y89/100)/(1+$B89/100)*100-100 -> -33.716823 | AR89: =+(1+Z89/100)/(1+$B89/100)*100-100 -> -11.44893 | AS89: =+(1+AA89/100)/(1+$B89/100)*100-100 -> -3.9454753 | AT89: =+(1+AB89/100)/(1+$B89/100)*100-100 -> -6.8641147 | AU89: =+(1+AC89/100)/(1+$B89/100)*100-100 -> -6.8641147 | ... BC89: =+(1+AK89/100)/(1+$B89/100)*100-100 -> -13.751902 | BF89: =+(E89/D89)*100 -> 6.4199099 | BG89: =+(G89/F89)*100 -> 7.8500194 | BH89: =+(I89/H89)*100 -> 22.076684 | BI89: =+(K89/J89)*100 -> 9.1243122 | BJ89: =+(M89/L89)*100 -> 22.076684 | BK89: =+(O89/N89)*100 -> 10.681766 | BL89: =+(Q89/P89)*100 -> 10.681766 | BM89: =+(S89/R89)*100 -> 10.690492 | BN89: =+(D89/$N89)*100 -> 59.375985 | BO89: =+(E89/$O89)*100 -> 35.685904 | BP89: =+(F89/$N89)*100 -> 14.243572 | BQ89: =+(G89/$O89)*100 -> 10.467587 | BR89: =+(H89/$N89)*100 -> 25.823256 | BS89: =+(I89/$O89)*100 -> 53.370562 | BT89: =+(J89/$N89)*100 -> 0.55718736 | BU89: =+(K89/$O89)*100 -> 0.47594672 | BV89: ND | BW89: ND | BX89: =+(N89/$N89)*100 -> 100 | BY89: =+(O89/$O89)*100 -> 100 | BZ89: ND | CA89: ND
A90: 37288 | B90: =+'[1]Senda Inflación Total'!F574 -> 6.7 | C90: =+'[1]Senda Inflación Total'!D574 -> 47.54 | D90: 28175.611 | E90: 1767.0409 | F90: 6763.7859 | G90: 555.04664 | H90: 12102.274 | I90: 2684.9763 | J90: 263.05682 | K90: 24.56166 | L90: =+H90 -> 12102.274 | M90: =+I90 -> 2684.9763 | N90: =+D90+F90+H90+J90 -> 47304.728 | O90: =+E90+G90+I90+K90 -> 5031.6256 | P90: =+L90+J90+F90+D90 -> 47304.728 | Q90: =+M90+K90+G90+E90 -> 5031.6256 | R90: =+D90+F90+L90 -> 47041.671 | S90: =+E90+G90+M90 -> 5007.0639 | V90: =+D90/D78*100-100 -> 2.6244709 | W90: =+E90/E78*100-100 -> -10.748957 | X90: =+F90/F78*100-100 -> 0.50767134 | Y90: =+G90/G78*100-100 -> -27.039922 | Z90: =+H90/H78*100-100 -> -5.1262299 | AA90: =+I90/I78*100-100 -> 1.4716451 | AD90: =+L90/L78*100-100 -> -5.1262299 | AE90: =+M90/M78*100-100 -> 1.4716451 | AF90: =+N90/N78*100-100 -> 0.77514525 | AG90: =+O90/O78*100-100 -> -6.5907273 | AH90: =+P90/P78*100-100 -> 0.77514525 | AI90: =+Q90/Q78*100-100 -> -6.5907273 | AJ90: =+R90/R78*100-100 -> 0.21474484 | AK90: =+S90/S78*100-100 -> -7.0467006 | AN90: =+(1+V90/100)/(1+$B90/100)*100-100 -> -3.8196149 | AO90: =+(1+W90/100)/(1+$B90/100)*100-100 -> -16.353286 | AP90: =+(1+X90/100)/(1+$B90/100)*100-100 -> -5.8034945 | AQ90: =+(1+Y90/100)/(1+$B90/100)*100-100 -> -31.621295 | AR90: =+(1+Z90/100)/(1+$B90/100)*100-100 -> -11.083627 | AS90: =+(1+AA90/100)/(1+$B90/100)*100-100 -> -4.9000515 | AT90: =+(1+AB90/100)/(1+$B90/100)*100-100 -> -6.2792877 | AU90: =+(1+AC90/100)/(1+$B90/100)*100-100 -> -6.2792877 | ... BC90: =+(1+AK90/100)/(1+$B90/100)*100-100 -> -12.883506 | BF90: =+(E90/D90)*100 -> 6.2715265 | BG90: =+(G90/F90)*100 -> 8.2061533 | BH90: =+(I90/H90)*100 -> 22.185718 | BI90: =+(K90/J90)*100 -> 9.337017 | BJ90: =+(M90/L90)*100 -> 22.185718 | BK90: =+(O90/N90)*100 -> 10.636623 | BL90: =+(Q90/P90)*100 -> 10.636623 | BM90: =+(S90/R90)*100 -> 10.64389 | BN90: =+(D90/$N90)*100 -> 59.561935 | BO90: =+(E90/$O90)*100 -> 35.118689 | BP90: =+(F90/$N90)*100 -> 14.29833 | BQ90: =+(G90/$O90)*100 -> 11.031159 | BR90: =+(H90/$N90)*100 -> 25.583645 | BS90: =+(I90/$O90)*100 -> 53.362006 | BT90: =+(J90/$N90)*100 -> 0.55608991 | BU90: =+(K90/$O90)*100 -> 0.48814562 | BV90: ND | BW90: ND | BX90: =+(N90/$N90)*100 -> 100 | BY90: =+(O90/$O90)*100 -> 100 | BZ90: ND | CA90: ND
A91: 37316 | B91: =+'[1]Senda Inflación Total'!F575 -> 5.89 | C91: =+'[1]Senda Inflación Total'!D575 -> 47.87 | D91: 28247.755 | E91: 1682.9841 | F91: 6615.8595 | G91: 566.65524 | H91: 12105.587 | I91: 2725.5424 | J91: 293.2587 | K91: 26.83217 | L91: =+H91 -> 12105.587 | M91: =+I91 -> 2725.5424 | N91: =+D91+F91+H91+J91 -> 47262.46 | O91: =+E91+G91+I91+K91 -> 5002.0139 | P91: =+L91+J91+F91+D91 -> 47262.46 | Q91: =+M91+K91+G91+E91 -> 5002.0139 | R91: =+D91+F91+L91 -> 46969.201 | S91: =+E91+G91+M91 -> 4975.1817 | V91: =+D91/D79*100-100 -> 2.3339191 | W91: =+E91/E79*100-100 -> -12.786669 | X91: =+F91/F79*100-100 -> -1.2408078 | Y91: =+G91/G79*100-100 -> -23.133406 | Z91: =+H91/H79*100-100 -> -5.6121361 | AA91: =+I91/I79*100-100 -> 0.28538336 | AD91: =+L91/L79*100-100 -> -5.6121361 | AE91: =+M91/M79*100-100 -> 0.28538336 | AF91: =+N91/N79*100-100 -> 0.28561444 | AG91: =+O91/O79*100-100 -> -7.1071231 | AH91: =+P91/P79*100-100 -> 0.28561444 | AI91: =+Q91/Q79*100-100 -> -7.1071231 | AJ91: =+R91/R79*100-100 -> -0.33664748 | AK91: =+S91/S79*100-100 -> -7.6054259 | AN91: =+(1+V91/100)/(1+$B91/100)*100-100 -> -3.3582783 | AO91: =+(1+W91/100)/(1+$B91/100)*100-100 -> -17.637802 | AP91: =+(1+X91/100)/(1+$B91/100)*100-100 -> -6.7341655 | AQ91: =+(1+Y91/100)/(1+$B91/100)*100-100 -> -27.409015 | AR91: =+(1+Z91/100)/(1+$B91/100)*100-100 -> -10.862344 | AS91: =+(1+AA91/100)/(1+$B91/100)*100-100 -> -5.2928668 | AT91: =+(1+AB91/100)/(1+$B91/100)*100-100 -> -5.5623761 | AU91: =+(1+AC91/100)/(1+$B91/100)*100-100 -> -5.5623761 | ... BC91: =+(1+AK91/100)/(1+$B91/100)*100-100 -> -12.74476 | BF91: =+(E91/D91)*100 -> 5.9579392 | BG91: =+(G91/F91)*100 -> 8.5651039 | BH91: =+(I91/H91)*100 -> 22.514749 | BI91: =+(K91/J91)*100 -> 9.1496586 | BJ91: =+(M91/L91)*100 -> 22.514749 | BK91: =+(O91/N91)*100 -> 10.583482 | BL91: =+(Q91/P91)*100 -> 10.583482 | BM91: =+(S91/R91)*100 -> 10.592434 | BN91: =+(D91/$N91)*100 -> 59.767847 | BO91: =+(E91/$O91)*100 -> 33.646129 | BP91: =+(F91/$N91)*100 -> 13.998128 | BQ91: =+(G91/$O91)*100 -> 11.328542 | BR91: =+(H91/$N91)*100 -> 25.613535 | BS91: =+(I91/$O91)*100 -> 54.488902 | BT91: =+(J91/$N91)*100 -> 0.62048971 | BU91: =+(K91/$O91)*100 -> 0.53642734 | BV91: ND | BW91: ND | BX91: =+(N91/$N91)*100 -> 100 | BY91: =+(O91/$O91)*100 -> 100 | BZ91: ND | CA91: ND
A92: 37347 | B92: =+'[1]Senda Inflación Total'!F576 -> 5.65 | C92: =+'[1]Senda Inflación Total'!D576 -> 48.31 | D92: 28195.477 | E92: 1652.0657 | F92: 6723.9035 | G92: 523.26484 | H92: 12080.576 | I92: 2733.3187 | J92: 297.88358 | K92: 25.78445 | L92: =+H92+(Titularizaciones!C4/1000) -> 12080.576 | M92: =+I92+((Titularizaciones!C4/1000)*Titularizaciones!M4) -> 2733.3187 | N92: =+D92+F92+H92+J92 -> 47297.84 | O92: =+E92+G92+I92+K92 -> 4934.4337 | P92: =+L92+J92+F92+D92 -> 47297.84 | Q92: =+M92+K92+G92+E92 -> 4934.4337 | R92: =+D92+F92+L92 -> 46999.956 | S92: =+E92+G92+M92 -> 4908.6493 | V92: =+D92/D80*100-100 -> 2.9541354 | W92: =+E92/E80*100-100 -> -17.933857 | X92: =+F92/F80*100-100 -> -0.022602442 | Y92: =+G92/G80*100-100 -> -28.456431 | Z92: =+H92/H80*100-100 -> -5.2459593 | AA92: =+I92/I80*100-100 -> 6.3086024 | AD92: =+L92/L80*100-100 -> -5.2459593 | AE92: =+M92/M80*100-100 -> 6.3086024 | AF92: =+N92/N80*100-100 -> 0.93161696 | AG92: =+O92/O80*100-100 -> -7.1707257 | AH92: =+P92/P80*100-100 -> 0.93161696 | AI92: =+Q92/Q80*100-100 -> -7.1707257 | AJ92: =+R92/R80*100-100 -> 0.29594583 | AK92: =+S92/S80*100-100 -> -7.6557969 | AN92: =+(1+V92/100)/(1+$B92/100)*100-100 -> -2.5516939 | AO92: =+(1+W92/100)/(1+$B92/100)*100-100 -> -22.322628 | AP92: =+(1+X92/100)/(1+$B92/100)*100-100 -> -5.3692404 | AQ92: =+(1+Y92/100)/(1+$B92/100)*100-100 -> -32.282472 | AR92: =+(1+Z92/100)/(1+$B92/100)*100-100 -> -10.31326 | AS92: =+(1+AA92/100)/(1+$B92/100)*100-100 -> 0.62338133 | AT92: =+(1+AB92/100)/(1+$B92/100)*100-100 -> -5.3478467 | AU92: =+(1+AC92/100)/(1+$B92/100)*100-100 -> -5.3478467 | ... BC92: =+(1+AK92/100)/(1+$B92/100)*100-100 -> -12.594223 | BF92: =+(E92/D92)*100 -> 5.8593287 | BG92: =+(G92/F92)*100 -> 7.7821587 | BH92: =+(I92/H92)*100 -> 22.625733 | BI92: =+(K92/J92)*100 -> 8.6558816 | BJ92: =+(M92/L92)*100 -> 22.625733 | BK92: =+(O92/N92)*100 -> 10.432683 | BL92: =+(Q92/P92)*100 -> 10.432683 | BM92: =+(S92/R92)*100 -> 10.443944 | BN92: =+(D92/$N92)*100 -> 59.612611 | BO92: =+(E92/$O92)*100 -> 33.48035 | BP92: =+(F92/$N92)*100 -> 14.21609 | BQ92: =+(G92/$O92)*100 -> 10.604354 | BR92: =+(H92/$N92)*100 -> 25.541496 | BS92: =+(I92/$O92)*100 -> 55.392754 | BT92: =+(J92/$N92)*100 -> 0.62980378 | BU92: =+(K92/$O92)*100 -> 0.52254122 | BV92: ND | BW92: ND | BX92: =+(N92/$N92)*100 -> 100 | BY92: =+(O92/$O92)*100 -> 100 | BZ92: ND | CA92: ND
A93: 37377 | B93: =+'[1]Senda Inflación Total'!F577 -> 5.84 | C93: =+'[1]Senda Inflación Total'!D577 -> 48.6 | D93: 28097.78 | E93: 1587.7057 | F93: 6947.6959 | G93: 523.08729 | H93: 11781.556 | I93: 2783.2014 | J93: 301.83846 | K93: 25.40233 | L93: =+H93+(Titularizaciones!C5/1000) -> 12256.414 | M93: =+I93+((Titularizaciones!C5/1000)*Titularizaciones!M5) -> 2783.3491 | N93: =+D93+F93+H93+J93 -> 47128.87 | O93: =+E93+G93+I93+K93 -> 4919.3968 | P93: =+L93+J93+F93+D93 -> 47603.728 | Q93: =+M93+K93+G93+E93 -> 4919.5445 | R93: =+D93+F93+L93 -> 47301.89 | S93: =+E93+G93+M93 -> 4894.1421 | V93: =+D93/D81*100-100 -> 2.5032077 | W93: =+E93/E81*100-100 -> -19.795559 | X93: =+F93/F81*100-100 -> 1.5258173 | Y93: =+G93/G81*100-100 -> -24.344457 | Z93: =+H93/H81*100-100 -> -8.4569921 | AA93: =+I93/I81*100-100 -> 9.3207777 | AD93: =+L93/L81*100-100 -> -4.7673297 | AE93: =+M93/M81*100-100 -> 9.3265778 | AF93: =+N93/N81*100-100 -> 0.0085130654 | AG93: =+O93/O81*100-100 -> -5.7023784 | AH93: =+P93/P81*100-100 -> 1.0161731 | AI93: =+Q93/Q81*100-100 -> -5.6995478 | AJ93: =+R93/R81*100-100 -> 0.37566518 | AK93: =+S93/S81*100-100 -> -6.1864733 | AN93: =+(1+V93/100)/(1+$B93/100)*100-100 -> -3.152676 | AO93: =+(1+W93/100)/(1+$B93/100)*100-100 -> -24.22105 | AP93: =+(1+X93/100)/(1+$B93/100)*100-100 -> -4.0761363 | AQ93: =+(1+Y93/100)/(1+$B93/100)*100-100 -> -28.51895 | AR93: =+(1+Z93/100)/(1+$B93/100)*100-100 -> -13.508118 | AS93: =+(1+AA93/100)/(1+$B93/100)*100-100 -> 3.2887167 | AT93: =+(1+AB93/100)/(1+$B93/100)*100-100 -> -5.5177627 | AU93: =+(1+AC93/100)/(1+$B93/100)*100-100 -> -5.5177627 | ... BC93: =+(1+AK93/100)/(1+$B93/100)*100-100 -> -11.362881 | BF93: =+(E93/D93)*100 -> 5.6506448 | BG93: =+(G93/F93)*100 -> 7.5289318 | BH93: =+(I93/H93)*100 -> 23.623378 | BI93: =+(K93/J93)*100 -> 8.4158692 | BJ93: =+(M93/L93)*100 -> 22.709326 | BK93: =+(O93/N93)*100 -> 10.438181 | BL93: =+(Q93/P93)*100 -> 10.334368 | BM93: =+(S93/R93)*100 -> 10.34661 | BN93: =+(D93/$N93)*100 -> 59.61904 | BO93: =+(E93/$O93)*100 -> 32.274399 | BP93: =+(F93/$N93)*100 -> 14.741911 | BQ93: =+(G93/$O93)*100 -> 10.633159 | BR93: =+(H93/$N93)*100 -> 24.998596 | BS93: =+(I93/$O93)*100 -> 56.576071 | BT93: =+(J93/$N93)*100 -> 0.64045342 | BU93: =+(K93/$O93)*100 -> 0.51637083 | BV93: ND | BW93: ND | BX93: =+(N93/$N93)*100 -> 100 | BY93: =+(O93/$O93)*100 -> 100 | BZ93: ND | CA93: ND
A94: 37408 | B94: =+'[1]Senda Inflación Total'!F578 -> 6.25 | C94: =+'[1]Senda Inflación Total'!D578 -> 48.81 | D94: 28527.147 | E94: 1474.7966 | F94: 6969.9154 | G94: 496.45847 | H94: 11734.476 | I94: 2798.5548 | J94: 303.04262 | K94: 26.01543 | L94: =+H94+(Titularizaciones!C6/1000) -> 12205.072 | M94: =+I94+((Titularizaciones!C6/1000)*Titularizaciones!M6) -> 2798.8032 | N94: =+D94+F94+H94+J94 -> 47534.581 | O94: =+E94+G94+I94+K94 -> 4795.8252 | P94: =+L94+J94+F94+D94 -> 48005.178 | Q94: =+M94+K94+G94+E94 -> 4796.0736 | R94: =+D94+F94+L94 -> 47702.135 | S94: =+E94+G94+M94 -> 4770.0582 | V94: =+D94/D82*100-100 -> 2.5587956 | W94: =+E94/E82*100-100 -> -20.89565 | X94: =+F94/F82*100-100 -> 1.0353933 | Y94: =+G94/G82*100-100 -> -26.596892 | Z94: =+H94/H82*100-100 -> -8.8124731 | AA94: =+I94/I82*100-100 -> 9.1393248 | AD94: =+L94/L82*100-100 -> -5.1555099 | AE94: =+M94/M82*100-100 -> 9.1490118 | AF94: =+N94/N82*100-100 -> -0.10051066 | AG94: =+O94/O82*100-100 -> -6.0547966 | AH94: =+P94/P82*100-100 -> 0.88850332 | AI94: =+Q94/Q82*100-100 -> -6.0499308 | AJ94: =+R94/R82*100-100 -> 0.25162376 | AK94: =+S94/S82*100-100 -> -6.5595459 | AN94: =+(1+V94/100)/(1+$B94/100)*100-100 -> -3.4740747 | AO94: =+(1+W94/100)/(1+$B94/100)*100-100 -> -25.548847 | AP94: =+(1+X94/100)/(1+$B94/100)*100-100 -> -4.9078652 | AQ94: =+(1+Y94/100)/(1+$B94/100)*100-100 -> -30.914722 | AR94: =+(1+Z94/100)/(1+$B94/100)*100-100 -> -14.176445 | AS94: =+(1+AA94/100)/(1+$B94/100)*100-100 -> 2.7193645 | AT94: =+(1+AB94/100)/(1+$B94/100)*100-100 -> -5.8823529 | AU94: =+(1+AC94/100)/(1+$B94/100)*100-100 -> -5.8823529 | ... BC94: =+(1+AK94/100)/(1+$B94/100)*100-100 -> -12.056043 | BF94: =+(E94/D94)*100 -> 5.1698004 | BG94: =+(G94/F94)*100 -> 7.1228765 | BH94: =+(I94/H94)*100 -> 23.848998 | BI94: =+(K94/J94)*100 -> 8.584743 | BJ94: =+(M94/L94)*100 -> 22.931476 | BK94: =+(O94/N94)*100 -> 10.089129 | BL94: =+(Q94/P94)*100 -> 9.9907424 | BM94: =+(S94/R94)*100 -> 9.9996745 | BN94: =+(D94/$N94)*100 -> 60.013461 | BO94: =+(E94/$O94)*100 -> 30.751674 | BP94: =+(F94/$N94)*100 -> 14.662831 | BQ94: =+(G94/$O94)*100 -> 10.351888 | BR94: =+(H94/$N94)*100 -> 24.686187 | BS94: =+(I94/$O94)*100 -> 58.353978 | BT94: =+(J94/$N94)*100 -> 0.63752034 | BU94: =+(K94/$O94)*100 -> 0.54245992 | BV94: ND | BW94: ND | BX94: =+(N94/$N94)*100 -> 100 | BY94: =+(O94/$O94)*100 -> 100 | BZ94: ND | CA94: ND
A95: 37438 | B95: =+'[1]Senda Inflación Total'!F579 -> 6.16 | C95: =+'[1]Senda Inflación Total'!D579 -> 48.82 | D95: 29194.196 | E95: 1447.1209 | F95: 7172.7224 | G95: 474.45091 | H95: 11661.073 | I95: 2777.9922 | J95: 307.80662 | K95: 26.23435 | L95: =+H95+(Titularizaciones!C7/1000) -> 12124.608 | M95: =+I95+((Titularizaciones!C7/1000)*Titularizaciones!M7) -> 2778.5626 | N95: =+D95+F95+H95+J95 -> 48335.798 | O95: =+E95+G95+I95+K95 -> 4725.7984 | P95: =+L95+J95+F95+D95 -> 48799.333 | Q95: =+M95+K95+G95+E95 -> 4726.3688 | R95: =+D95+F95+L95 -> 48491.527 | S95: =+E95+G95+M95 -> 4700.1344 | V95: =+D95/D83*100-100 -> 5.4620974 | W95: =+E95/E83*100-100 -> -23.955753 | X95: =+F95/F83*100-100 -> 2.9924652 | Y95: =+G95/G83*100-100 -> -29.175708 | Z95: =+H95/H83*100-100 -> -9.0992777 | AA95: =+I95/I83*100-100 -> 7.9166471 | AD95: =+L95/L83*100-100 -> -5.485915 | AE95: =+M95/M83*100-100 -> 7.9388033 | AF95: =+N95/N83*100-100 -> 1.8134871 | AG95: =+O95/O83*100-100 -> -8.1852023 | AH95: =+P95/P83*100-100 -> 2.7898677 | AI95: =+Q95/Q83*100-100 -> -8.1741214 | AJ95: =+R95/R83*100-100 -> 2.1415105 | AK95: =+S95/S83*100-100 -> -8.6838134 | AN95: =+(1+V95/100)/(1+$B95/100)*100-100 -> -0.65740633 | AO95: =+(1+W95/100)/(1+$B95/100)*100-100 -> -28.368267 | AP95: =+(1+X95/100)/(1+$B95/100)*100-100 -> -2.9837367 | AQ95: =+(1+Y95/100)/(1+$B95/100)*100-100 -> -33.285332 | AR95: =+(1+Z95/100)/(1+$B95/100)*100-100 -> -14.373849 | AS95: =+(1+AA95/100)/(1+$B95/100)*100-100 -> 1.6547165 | AT95: =+(1+AB95/100)/(1+$B95/100)*100-100 -> -5.8025622 | AU95: =+(1+AC95/100)/(1+$B95/100)*100-100 -> -5.8025622 | ... BC95: =+(1+AK95/100)/(1+$B95/100)*100-100 -> -13.982492 | BF95: =+(E95/D95)*100 -> 4.9568789 | BG95: =+(G95/F95)*100 -> 6.6146559 | BH95: =+(I95/H95)*100 -> 23.822784 | BI95: =+(K95/J95)*100 -> 8.5229973 | BJ95: =+(M95/L95)*100 -> 22.916721 | BK95: =+(O95/N95)*100 -> 9.7770155 | BL95: =+(Q95/P95)*100 -> 9.6853143 | BM95: =+(S95/R95)*100 -> 9.6926923 | BN95: =+(D95/$N95)*100 -> 60.398705 | BO95: =+(E95/$O95)*100 -> 30.621723 | BP95: =+(F95/$N95)*100 -> 14.839359 | BQ95: =+(G95/$O95)*100 -> 10.039593 | BR95: =+(H95/$N95)*100 -> 24.125128 | BS95: =+(I95/$O95)*100 -> 58.783553 | BT95: =+(J95/$N95)*100 -> 0.63680881 | BU95: =+(K95/$O95)*100 -> 0.55513053 | BV95: ND | BW95: ND | BX95: =+(N95/$N95)*100 -> 100 | BY95: =+(O95/$O95)*100 -> 100 | BZ95: ND | CA95: ND
A96: 37469 | B96: =+'[1]Senda Inflación Total'!F580 -> 5.98 | C96: =+'[1]Senda Inflación Total'!D580 -> 48.87 | D96: 29304.103 | E96: 1416.129 | F96: 7297.333 | G96: 470.01942 | H96: 11577.498 | I96: 2751.3058 | J96: 319.02561 | K96: 25.76074 | L96: =+H96+(Titularizaciones!C8/1000) -> 12033.734 | M96: =+I96+((Titularizaciones!C8/1000)*Titularizaciones!M8) -> 2752.5725 | N96: =+D96+F96+H96+J96 -> 48497.96 | O96: =+E96+G96+I96+K96 -> 4663.215 | P96: =+L96+J96+F96+D96 -> 48954.196 | Q96: =+M96+K96+G96+E96 -> 4664.4817 | R96: =+D96+F96+L96 -> 48635.17 | S96: =+E96+G96+M96 -> 4638.721 | V96: =+D96/D84*100-100 -> 5.7328231 | W96: =+E96/E84*100-100 -> -24.259982 | X96: =+F96/F84*100-100 -> 3.3649434 | Y96: =+G96/G84*100-100 -> -27.453195 | Z96: =+H96/H84*100-100 -> -9.1540055 | AA96: =+I96/I84*100-100 -> 4.4281758 | AD96: =+L96/L84*100-100 -> -5.5740257 | AE96: =+M96/M84*100-100 -> 4.4762566 | AF96: =+N96/N84*100-100 -> 2.0599158 | AG96: =+O96/O84*100-100 -> -9.4916323 | AH96: =+P96/P84*100-100 -> 3.0200264 | AI96: =+Q96/Q84*100-100 -> -9.4670458 | AJ96: =+R96/R84*100-100 -> 2.3486636 | AK96: =+S96/S84*100-100 -> -9.9670361 | AN96: =+(1+V96/100)/(1+$B96/100)*100-100 -> -0.2332298 | AO96: =+(1+W96/100)/(1+$B96/100)*100-100 -> -28.533668 | AP96: =+(1+X96/100)/(1+$B96/100)*100-100 -> -2.4675001 | AQ96: =+(1+Y96/100)/(1+$B96/100)*100-100 -> -31.546702 | AR96: =+(1+Z96/100)/(1+$B96/100)*100-100 -> -14.280058 | AS96: =+(1+AA96/100)/(1+$B96/100)*100-100 -> -1.4642614 | AT96: =+(1+AB96/100)/(1+$B96/100)*100-100 -> -5.6425741 | AU96: =+(1+AC96/100)/(1+$B96/100)*100-100 -> -5.6425741 | ... BC96: =+(1+AK96/100)/(1+$B96/100)*100-100 -> -15.047213 | BF96: =+(E96/D96)*100 -> 4.8325282 | BG96: =+(G96/F96)*100 -> 6.4409754 | BH96: =+(I96/H96)*100 -> 23.764251 | BI96: =+(K96/J96)*100 -> 8.0748188 | BJ96: =+(M96/L96)*100 -> 22.873802 | BK96: =+(O96/N96)*100 -> 9.6152807 | BL96: =+(Q96/P96)*100 -> 9.5282573 | BM96: =+(S96/R96)*100 -> 9.5377912 | BN96: =+(D96/$N96)*100 -> 60.423373 | BO96: =+(E96/$O96)*100 -> 30.368084 | BP96: =+(F96/$N96)*100 -> 15.04668 | BQ96: =+(G96/$O96)*100 -> 10.0793 | BR96: =+(H96/$N96)*100 -> 23.872135 | BS96: =+(I96/$O96)*100 -> 59.000192 | BT96: =+(J96/$N96)*100 -> 0.65781244 | BU96: =+(K96/$O96)*100 -> 0.55242446 | BV96: ND | BW96: ND | BX96: =+(N96/$N96)*100 -> 100 | BY96: =+(O96/$O96)*100 -> 100 | BZ96: ND | CA96: ND
A97: 37500 | B97: =+'[1]Senda Inflación Total'!F581 -> 5.97 | C97: =+'[1]Senda Inflación Total'!D581 -> 49.04 | D97: 29949.262 | E97: 1359.3842 | F97: 7427.8242 | G97: 493.6691 | H97: 11501.742 | I97: 2754.9877 | J97: 328.50832 | K97: 26.59422 | L97: =+H97+(Titularizaciones!C9/1000) -> 11949.117 | M97: =+I97+((Titularizaciones!C9/1000)*Titularizaciones!M9) -> 2756.8897 | N97: =+D97+F97+H97+J97 -> 49207.336 | O97: =+E97+G97+I97+K97 -> 4634.6352 | P97: =+L97+J97+F97+D97 -> 49654.711 | Q97: =+M97+K97+G97+E97 -> 4636.5373 | R97: =+D97+F97+L97 -> 49326.203 | S97: =+E97+G97+M97 -> 4609.9431 | V97: =+D97/D85*100-100 -> 7.7849362 | W97: =+E97/E85*100-100 -> -21.622414 | X97: =+F97/F85*100-100 -> 3.7987568 | Y97: =+G97/G85*100-100 -> -24.298144 | Z97: =+H97/H85*100-100 -> -9.2316352 | AA97: =+I97/I85*100-100 -> 1.4566205 | AD97: =+L97/L85*100-100 -> -5.7010846 | AE97: =+M97/M85*100-100 -> 1.5266657 | AF97: =+N97/N85*100-100 -> 3.347128 | AG97: =+O97/O85*100-100 -> -9.1597332 | AH97: =+P97/P85*100-100 -> 4.2867217 | AI97: =+Q97/Q85*100-100 -> -9.1224527 | AJ97: =+R97/R85*100-100 -> 3.596776 | AK97: =+S97/S85*100-100 -> -9.6437076 | AN97: =+(1+V97/100)/(1+$B97/100)*100-100 -> 1.7126887 | AO97: =+(1+W97/100)/(1+$B97/100)*100-100 -> -26.037949 | AP97: =+(1+X97/100)/(1+$B97/100)*100-100 -> -2.0489226 | AQ97: =+(1+Y97/100)/(1+$B97/100)*100-100 -> -28.562937 | AR97: =+(1+Z97/100)/(1+$B97/100)*100-100 -> -14.345225 | AS97: =+(1+AA97/100)/(1+$B97/100)*100-100 -> -4.2591106 | AT97: =+(1+AB97/100)/(1+$B97/100)*100-100 -> -5.6336699 | AU97: =+(1+AC97/100)/(1+$B97/100)*100-100 -> -5.6336699 | ... BC97: =+(1+AK97/100)/(1+$B97/100)*100-100 -> -14.734083 | BF97: =+(E97/D97)*100 -> 4.5389573 | BG97: =+(G97/F97)*100 -> 6.6462141 | BH97: =+(I97/H97)*100 -> 23.952786 | BI97: =+(K97/J97)*100 -> 8.0954479 | BJ97: =+(M97/L97)*100 -> 23.071912 | BK97: =+(O97/N97)*100 -> 9.4185859 | BL97: =+(Q97/P97)*100 -> 9.3375576 | BM97: =+(S97/R97)*100 -> 9.34583 | BN97: =+(D97/$N97)*100 -> 60.863408 | BO97: =+(E97/$O97)*100 -> 29.330986 | BP97: =+(F97/$N97)*100 -> 15.094953 | BQ97: =+(G97/$O97)*100 -> 10.651736 | BR97: =+(H97/$N97)*100 -> 23.374039 | BS97: =+(I97/$O97)*100 -> 59.443463 | BT97: =+(J97/$N97)*100 -> 0.66760029 | BU97: =+(K97/$O97)*100 -> 0.57381474 | BV97: ND | BW97: ND | BX97: =+(N97/$N97)*100 -> 100 | BY97: =+(O97/$O97)*100 -> 100 | BZ97: ND | CA97: ND
A98: 37530 | B98: =+'[1]Senda Inflación Total'!F582 -> 6.37 | C98: =+'[1]Senda Inflación Total'!D582 -> 49.32 | D98: 30056.181 | E98: 1334.0336 | F98: 7581.2071 | G98: 492.64048 | H98: 11416.236 | I98: 2733.1099 | J98: 347.14333 | K98: 28.07238 | L98: =+H98+(Titularizaciones!C10/1000) -> 11856.026 | M98: =+I98+((Titularizaciones!C10/1000)*Titularizaciones!M10) -> 2735.4804 | N98: =+D98+F98+H98+J98 -> 49400.768 | O98: =+E98+G98+I98+K98 -> 4587.8564 | P98: =+L98+J98+F98+D98 -> 49840.558 | Q98: =+M98+K98+G98+E98 -> 4590.2268 | R98: =+D98+F98+L98 -> 49493.415 | S98: =+E98+G98+M98 -> 4562.1545 | V98: =+D98/D86*100-100 -> 7.9648594 | W98: =+E98/E86*100-100 -> -21.286161 | X98: =+F98/F86*100-100 -> 3.869793 | Y98: =+G98/G86*100-100 -> -26.089865 | Z98: =+H98/H86*100-100 -> -9.0545002 | AA98: =+I98/I86*100-100 -> 2.0856774 | AD98: =+L98/L86*100-100 -> -5.5509906 | AE98: =+M98/M86*100-100 -> 2.1742186 | AF98: =+N98/N86*100-100 -> 3.586294 | AG98: =+O98/O86*100-100 -> -8.9458048 | AH98: =+P98/P86*100-100 -> 4.5084696 | AI98: =+Q98/Q86*100-100 -> -8.8987583 | AJ98: =+R98/R86*100-100 -> 3.7805601 | AK98: =+S98/S86*100-100 -> -9.4559048 | AN98: =+(1+V98/100)/(1+$B98/100)*100-100 -> 1.4993508 | AO98: =+(1+W98/100)/(1+$B98/100)*100-100 -> -25.999964 | AP98: =+(1+X98/100)/(1+$B98/100)*100-100 -> -2.3504814 | AQ98: =+(1+Y98/100)/(1+$B98/100)*100-100 -> -30.515996 | AR98: =+(1+Z98/100)/(1+$B98/100)*100-100 -> -14.500799 | AS98: =+(1+AA98/100)/(1+$B98/100)*100-100 -> -4.0277546 | AT98: =+(1+AB98/100)/(1+$B98/100)*100-100 -> -5.9885306 | AU98: =+(1+AC98/100)/(1+$B98/100)*100-100 -> -5.9885306 | ... BC98: =+(1+AK98/100)/(1+$B98/100)*100-100 -> -14.878166 | BF98: =+(E98/D98)*100 -> 4.4384668 | BG98: =+(G98/F98)*100 -> 6.4981799 | BH98: =+(I98/H98)*100 -> 23.940551 | BI98: =+(K98/J98)*100 -> 8.0866828 | BJ98: =+(M98/L98)*100 -> 23.072489 | BK98: =+(O98/N98)*100 -> 9.2870142 | BL98: =+(Q98/P98)*100 -> 9.2098223 | BM98: =+(S98/R98)*100 -> 9.2177 | BN98: =+(D98/$N98)*100 -> 60.841526 | BO98: =+(E98/$O98)*100 -> 29.077493 | BP98: =+(F98/$N98)*100 -> 15.346334 | BQ98: =+(G98/$O98)*100 -> 10.737923 | BR98: =+(H98/$N98)*100 -> 23.109431 | BS98: =+(I98/$O98)*100 -> 59.572699 | BT98: =+(J98/$N98)*100 -> 0.70270836 | BU98: =+(K98/$O98)*100 -> 0.61188446 | BV98: ND | BW98: ND | BX98: =+(N98/$N98)*100 -> 100 | BY98: =+(O98/$O98)*100 -> 100 | BZ98: ND | CA98: ND
A99: 37561 | B99: =+'[1]Senda Inflación Total'!F583 -> 7.07 | C99: =+'[1]Senda Inflación Total'!D583 -> 49.7 | D99: 30688.431 | E99: 1340.9145 | F99: 7735.1655 | G99: 518.36837 | H99: 10809.749 | I99: 2733.8789 | J99: 354.47462 | K99: 28.84219 | L99: =+H99+(Titularizaciones!C11/1000) -> 11804.125 | M99: =+I99+((Titularizaciones!C11/1000)*Titularizaciones!M11) -> 2736.7522 | N99: =+D99+F99+H99+J99 -> 49587.819 | O99: =+E99+G99+I99+K99 -> 4622.004 | P99: =+L99+J99+F99+D99 -> 50582.196 | Q99: =+M99+K99+G99+E99 -> 4624.8772 | R99: =+D99+F99+L99 -> 50227.721 | S99: =+E99+G99+M99 -> 4596.0351 | V99: =+D99/D87*100-100 -> 9.6464232 | W99: =+E99/E87*100-100 -> -18.203073 | X99: =+F99/F87*100-100 -> 4.0589917 | Y99: =+G99/G87*100-100 -> -17.635331 | Z99: =+H99/H87*100-100 -> -13.485403 | AA99: =+I99/I87*100-100 -> 0.28470232 | AD99: =+L99/L87*100-100 -> -5.527024 | AE99: =+M99/M87*100-100 -> 0.39010019 | AF99: =+N99/N87*100-100 -> 3.48757 | AG99: =+O99/O87*100-100 -> -7.4636204 | AH99: =+P99/P87*100-100 -> 5.5627893 | AI99: =+Q99/Q87*100-100 -> -7.4060951 | AJ99: =+R99/R87*100-100 -> 4.8230166 | AK99: =+S99/S87*100-100 -> -7.9835399 | AN99: =+(1+V99/100)/(1+$B99/100)*100-100 -> 2.4062979 | AO99: =+(1+W99/100)/(1+$B99/100)*100-100 -> -23.604252 | AP99: =+(1+X99/100)/(1+$B99/100)*100-100 -> -2.8121867 | AQ99: =+(1+Y99/100)/(1+$B99/100)*100-100 -> -23.073999 | AR99: =+(1+Z99/100)/(1+$B99/100)*100-100 -> -19.198097 | AS99: =+(1+AA99/100)/(1+$B99/100)*100-100 -> -6.3372538 | AT99: =+(1+AB99/100)/(1+$B99/100)*100-100 -> -6.6031568 | AU99: =+(1+AC99/100)/(1+$B99/100)*100-100 -> -6.6031568 | ... BC99: =+(1+AK99/100)/(1+$B99/100)*100-100 -> -14.059531 | BF99: =+(E99/D99)*100 -> 4.3694464 | BG99: =+(G99/F99)*100 -> 6.7014515 | BH99: =+(I99/H99)*100 -> 25.290865 | BI99: =+(K99/J99)*100 -> 8.1366023 | BJ99: =+(M99/L99)*100 -> 23.18471 | BK99: =+(O99/N99)*100 -> 9.3208454 | BL99: =+(Q99/P99)*100 -> 9.1432908 | BM99: =+(S99/R99)*100 -> 9.1503953 | BN99: =+(D99/$N99)*100 -> 61.887034 | BO99: =+(E99/$O99)*100 -> 29.01154 | BP99: =+(F99/$N99)*100 -> 15.598923 | BQ99: =+(G99/$O99)*100 -> 11.21523 | BR99: =+(H99/$N99)*100 -> 21.799201 | BS99: =+(I99/$O99)*100 -> 59.149211 | BT99: =+(J99/$N99)*100 -> 0.71484212 | BU99: =+(K99/$O99)*100 -> 0.62401915 | BV99: ND | BW99: ND | BX99: =+(N99/$N99)*100 -> 100 | BY99: =+(O99/$O99)*100 -> 100 | BZ99: ND | CA99: ND
A100: 37591 | B100: =+'[1]Senda Inflación Total'!F584 -> 6.99 | C100: =+'[1]Senda Inflación Total'!D584 -> 49.83 | D100: 31072.241 | E100: 1211.1286 | F100: 7854.7573 | G100: 461.49055 | H100: 10914.861 | I100: 2688.0682 | J100: 389.71331 | K100: 25.56188 | L100: =+H100+(Titularizaciones!C12/1000) -> 11895.701 | M100: =+I100+((Titularizaciones!C12/1000)*Titularizaciones!M12) -> 2691.0682 | N100: =+D100+F100+H100+J100 -> 50231.573 | O100: =+E100+G100+I100+K100 -> 4386.2493 | P100: =+L100+J100+F100+D100 -> 51212.413 | Q100: =+M100+K100+G100+E100 -> 4389.2493 | R100: =+D100+F100+L100 -> 50822.7 | S100: =+E100+G100+M100 -> 4363.6874 | V100: =+D100/D88*100-100 -> 11.650695 | W100: =+E100/E88*100-100 -> -15.102702 | X100: =+F100/F88*100-100 -> 5.3160686 | Y100: =+G100/G88*100-100 -> -16.612941 | Z100: =+H100/H88*100-100 -> -12.010047 | AA100: =+I100/I88*100-100 -> 1.0692757 | AD100: =+L100/L88*100-100 -> -4.10302 | AE100: =+M100/M88*100-100 -> 1.1820739 | AF100: =+N100/N88*100-100 -> 5.3231651 | AG100: =+O100/O88*100-100 -> -5.4614755 | AH100: =+P100/P88*100-100 -> 7.3797443 | AI100: =+Q100/Q88*100-100 -> -5.396815 | AJ100: =+R100/R88*100-100 -> 6.5626121 | AK100: =+S100/S88*100-100 -> -5.9477601 | AN100: =+(1+V100/100)/(1+$B100/100)*100-100 -> 4.3561968 | AO100: =+(1+W100/100)/(1+$B100/100)*100-100 -> -20.649315 | AP100: =+(1+X100/100)/(1+$B100/100)*100-100 -> -1.5645681 | AQ100: =+(1+Y100/100)/(1+$B100/100)*100-100 -> -22.060885 | AR100: =+(1+Z100/100)/(1+$B100/100)*100-100 -> -17.758713 | AS100: =+(1+AA100/100)/(1+$B100/100)*100-100 -> -5.5339044 | AT100: =+(1+AB100/100)/(1+$B100/100)*100-100 -> -6.5333209 | AU100: =+(1+AC100/100)/(1+$B100/100)*100-100 -> -6.5333209 | ... BC100: =+(1+AK100/100)/(1+$B100/100)*100-100 -> -12.092495 | BF100: =+(E100/D100)*100 -> 3.8977833 | BG100: =+(G100/F100)*100 -> 5.8752999 | BH100: =+(I100/H100)*100 -> 24.627599 | BI100: =+(K100/J100)*100 -> 6.5591499 | BJ100: =+(M100/L100)*100 -> 22.62219 | BK100: =+(O100/N100)*100 -> 8.7320564 | BL100: =+(Q100/P100)*100 -> 8.5706746 | BM100: =+(S100/R100)*100 -> 8.5860991 | BN100: =+(D100/$N100)*100 -> 61.85799 | BO100: =+(E100/$O100)*100 -> 27.611943 | BP100: =+(F100/$N100)*100 -> 15.637092 | BQ100: =+(G100/$O100)*100 -> 10.521302 | BR100: =+(H100/$N100)*100 -> 21.729085 | BS100: =+(I100/$O100)*100 -> 61.283982 | BT100: =+(J100/$N100)*100 -> 0.77583338 | BU100: =+(K100/$O100)*100 -> 0.58277308 | BV100: ND | BW100: ND | BX100: =+(N100/$N100)*100 -> 100 | BY100: =+(O100/$O100)*100 -> 100 | BZ100: ND | CA100: ND
A101: 37622 | B101: =+'[1]Senda Inflación Total'!F585 -> 7.39 | C101: =+'[1]Senda Inflación Total'!D585 -> 50.42 | D101: ='[2]Ene-03'!$D$606/1000 -> 31095.59 | E101: ='[2]Ene-03'!$D$607/1000 -> 1199.6673 | F101: ='[2]Ene-03'!$D$617/1000 -> 8015.731 | G101: ='[2]Ene-03'!$D$618/1000 -> 488.4375 | H101: ='[2]Ene-03'!$D$630/1000 -> 10891.152 | I101: ='[2]Ene-03'!$D$631/1000 -> 2688.5341 | J101: ='[2]Ene-03'!$D$641/1000 -> 406.03595 | K101: ='[2]Ene-03'!$D$642/1000 -> 26.44333 | L101: =+H101+(Titularizaciones!C13/1000) -> 11857.933 | M101: =+I101+((Titularizaciones!C13/1000)*Titularizaciones!M13) -> 2692.589 | N101: =+D101+F101+H101+J101 -> 50408.509 | O101: =+E101+G101+I101+K101 -> 4403.0822 | P101: =+L101+J101+F101+D101 -> 51375.29 | Q101: =+M101+K101+G101+E101 -> 4407.1371 | R101: =+D101+F101+L101 -> 50969.254 | S101: =+E101+G101+M101 -> 4380.6937 | V101: =+D101/D89*100-100 -> 11.230203 | W101: =+E101/E89*100-100 -> -33.15702 | X101: =+F101/F89*100-100 -> 19.525062 | Y101: =+G101/G89*100-100 -> -7.2200544 | Z101: =+H101/H89*100-100 -> -10.422778 | AA101: =+I101/I89*100-100 -> 0.16257388 | AB101: =+J101/J89*100-100 -> 54.773993 | AC101: =+K101/K89*100-100 -> 10.471311 | ... AK101: =+S101/S89*100-100 -> -12.480156 | AN101: =+(1+V101/100)/(1+$B101/100)*100-100 -> 3.5759414 | AO101: =+(1+W101/100)/(1+$B101/100)*100-100 -> -37.756793 | AP101: =+(1+X101/100)/(1+$B101/100)*100-100 -> 11.299992 | AQ101: =+(1+Y101/100)/(1+$B101/100)*100-100 -> -13.604669 | AR101: =+(1+Z101/100)/(1+$B101/100)*100-100 -> -16.586999 | AS101: =+(1+AA101/100)/(1+$B101/100)*100-100 -> -6.7300737 | AT101: =+(1+AB101/100)/(1+$B101/100)*100-100 -> 44.123282 | AU101: =+(1+AC101/100)/(1+$B101/100)*100-100 -> 2.8692722 | ... BC101: =+(1+AK101/100)/(1+$B101/100)*100-100 -> -18.502799 | BF101: =+(E101/D101)*100 -> 3.8579981 | BG101: =+(G101/F101)*100 -> 6.0934867 | BH101: =+(I101/H101)*100 -> 24.685488 | BI101: =+(K101/J101)*100 -> 6.5125588 | BJ101: =+(M101/L101)*100 -> 22.707069 | BK101: =+(O101/N101)*100 -> 8.7347995 | BL101: =+(Q101/P101)*100 -> 8.5783206 | BM101: =+(S101/R101)*100 -> 8.5947771 | BN101: =+(D101/$N101)*100 -> 61.687184 | BO101: =+(E101/$O101)*100 -> 27.246079 | BP101: =+(F101/$N101)*100 -> 15.901543 | BQ101: =+(G101/$O101)*100 -> 11.093082 | BR101: =+(H101/$N101)*100 -> 21.605781 | BS101: =+(I101/$O101)*100 -> 61.060275 | BT101: =+(J101/$N101)*100 -> 0.80549089 | BU101: =+(K101/$O101)*100 -> 0.60056407 | BV101: ND | BW101: ND | BX101: =+(N101/$N101)*100 -> 100 | BY101: =+(O101/$O101)*100 -> 100 | BZ101: ND | CA101: ND
A102: 37653 | B102: =+'[1]Senda Inflación Total'!F586 -> 7.24 | C102: =+'[1]Senda Inflación Total'!D586 -> 50.98 | D102: ='[2]Feb-03'!$D$606/1000 -> 31415.979 | E102: ='[2]Feb-03'!$D$607/1000 -> 1242.9595 | F102: ='[2]Feb-03'!$D$617/1000 -> 8063.4274 | G102: ='[2]Feb-03'!$D$618/1000 -> 513.70503 | H102: ='[2]Feb-03'!$D$630/1000 -> 10849.661 | I102: ='[2]Feb-03'!$D$631/1000 -> 2646.5775 | J102: ='[2]Feb-03'!$D$641/1000 -> 416.32287 | K102: ='[2]Feb-03'!$D$642/1000 -> 27.37526 | L102: =+H102+(Titularizaciones!C14/1000) -> 11805.928 | M102: =+I102+((Titularizaciones!C14/1000)*Titularizaciones!M14) -> 2651.4807 | N102: =+D102+F102+H102+J102 -> 50745.39 | O102: =+E102+G102+I102+K102 -> 4430.6173 | P102: =+L102+J102+F102+D102 -> 51701.657 | Q102: =+M102+K102+G102+E102 -> 4435.5205 | R102: =+D102+F102+L102 -> 51285.334 | S102: =+E102+G102+M102 -> 4408.1452 | V102: =+D102/D90*100-100 -> 11.50061 | W102: =+E102/E90*100-100 -> -29.658703 | X102: =+F102/F90*100-100 -> 19.214704 | Y102: =+G102/G90*100-100 -> -7.4483128 | Z102: =+H102/H90*100-100 -> -10.350227 | AA102: =+I102/I90*100-100 -> -1.4301359 | AB102: =+J102/J90*100-100 -> 58.263477 | AC102: =+K102/K90*100-100 -> 11.455252 | ... AK102: =+S102/S90*100-100 -> -11.961475 | AN102: =+(1+V102/100)/(1+$B102/100)*100-100 -> 3.9729671 | AO102: =+(1+W102/100)/(1+$B102/100)*100-100 -> -34.407594 | AP102: =+(1+X102/100)/(1+$B102/100)*100-100 -> 11.166266 | AQ102: =+(1+Y102/100)/(1+$B102/100)*100-100 -> -13.696674 | AR102: =+(1+Z102/100)/(1+$B102/100)*100-100 -> -16.402674 | AS102: =+(1+AA102/100)/(1+$B102/100)*100-100 -> -8.0847966 | AT102: =+(1+AB102/100)/(1+$B102/100)*100-100 -> 47.578774 | AU102: =+(1+AC102/100)/(1+$B102/100)*100-100 -> 3.9306712 | ... BC102: =+(1+AK102/100)/(1+$B102/100)*100-100 -> -17.905142 | BF102: =+(E102/D102)*100 -> 3.9564564 | BG102: =+(G102/F102)*100 -> 6.3708025 | BH102: =+(I102/H102)*100 -> 24.393182 | BI102: =+(K102/J102)*100 -> 6.5754879 | BJ102: =+(M102/L102)*100 -> 22.458893 | BK102: =+(O102/N102)*100 -> 8.7310736 | BL102: =+(Q102/P102)*100 -> 8.5790684 | BM102: =+(S102/R102)*100 -> 8.595333 | BN102: =+(D102/$N102)*100 -> 61.90903 | BO102: =+(E102/$O102)*100 -> 28.053867 | BP102: =+(F102/$N102)*100 -> 15.88997 | BQ102: =+(G102/$O102)*100 -> 11.594435 | BR102: =+(H102/$N102)*100 -> 21.380584 | BS102: =+(I102/$O102)*100 -> 59.733832 | BT102: =+(J102/$N102)*100 -> 0.82041516 | BU102: =+(K102/$O102)*100 -> 0.61786559 | BV102: ND | BW102: ND | BX102: =+(N102/$N102)*100 -> 100 | BY102: =+(O102/$O102)*100 -> 100 | BZ102: ND | CA102: ND
A103: 37681 | B103: =+'[1]Senda Inflación Total'!F587 -> 7.6 | C103: =+'[1]Senda Inflación Total'!D587 -> 51.51 | D103: ='[2]Mar-03'!$D$606/1000 -> 31759.563 | E103: ='[2]Mar-03'!$D$607/1000 -> 1192.3183 | F103: ='[2]Mar-03'!$D$617/1000 -> 8097.8787 | G103: ='[2]Mar-03'!$D$618/1000 -> 531.15345 | H103: ='[2]Mar-03'!$D$630/1000 -> 10907.467 | I103: ='[2]Mar-03'!$D$631/1000 -> 2644.9386 | J103: ='[2]Mar-03'!$D$641/1000 -> 425.92578 | K103: ='[2]Mar-03'!$D$642/1000 -> 27.47067 | L103: =+H103+(Titularizaciones!C15/1000) -> 11857.044 | M103: =+I103+((Titularizaciones!C15/1000)*Titularizaciones!M15) -> 2650.845 | N103: =+D103+F103+H103+J103 -> 51190.835 | O103: =+E103+G103+I103+K103 -> 4395.881 | P103: =+L103+J103+F103+D103 -> 52140.411 | Q103: =+M103+K103+G103+E103 -> 4401.7874 | R103: =+D103+F103+L103 -> 51714.486 | S103: =+E103+G103+M103 -> 4374.3168 | V103: =+D103/D91*100-100 -> 12.432168 | W103: =+E103/E91*100-100 -> -29.15451 | X103: =+F103/F91*100-100 -> 22.401008 | Y103: =+G103/G91*100-100 -> -6.2651481 | Z103: =+H103/H91*100-100 -> -9.8972428 | AA103: =+I103/I91*100-100 -> -2.95735 | AB103: =+J103/J91*100-100 -> 45.238924 | AC103: =+K103/K91*100-100 -> 2.3796063 | ... AK103: =+S103/S91*100-100 -> -12.077246 | AN103: =+(1+V103/100)/(1+$B103/100)*100-100 -> 4.4908627 | AO103: =+(1+W103/100)/(1+$B103/100)*100-100 -> -34.158466 | AP103: =+(1+X103/100)/(1+$B103/100)*100-100 -> 13.755584 | AQ103: =+(1+Y103/100)/(1+$B103/100)*100-100 -> -12.885825 | AR103: =+(1+Z103/100)/(1+$B103/100)*100-100 -> -16.261378 | AS103: =+(1+AA103/100)/(1+$B103/100)*100-100 -> -9.8116636 | AT103: =+(1+AB103/100)/(1+$B103/100)*100-100 -> 34.980413 | AU103: =+(1+AC103/100)/(1+$B103/100)*100-100 -> -4.851667 | ... BC103: =+(1+AK103/100)/(1+$B103/100)*100-100 -> -18.287404 | BF103: =+(E103/D103)*100 -> 3.7542024 | BG103: =+(G103/F103)*100 -> 6.5591678 | BH103: =+(I103/H103)*100 -> 24.248879 | BI103: =+(K103/J103)*100 -> 6.4496378 | BJ103: =+(M103/L103)*100 -> 22.356711 | BK103: =+(O103/N103)*100 -> 8.5872422 | BL103: =+(Q103/P103)*100 -> 8.4421801 | BM103: =+(S103/R103)*100 -> 8.4585909 | BN103: =+(D103/$N103)*100 -> 62.041502 | BO103: =+(E103/$O103)*100 -> 27.123534 | BP103: =+(F103/$N103)*100 -> 15.819001 | BQ103: =+(G103/$O103)*100 -> 12.082981 | BR103: =+(H103/$N103)*100 -> 21.307461 | BS103: =+(I103/$O103)*100 -> 60.168567 | BT103: =+(J103/$N103)*100 -> 0.83203522 | BU103: =+(K103/$O103)*100 -> 0.62491842 | BV103: ND | BW103: ND | BX103: =+(N103/$N103)*100 -> 100 | BY103: =+(O103/$O103)*100 -> 100 | BZ103: ND | CA103: ND
A104: 37712 | B104: =+'[1]Senda Inflación Total'!F588 -> 7.85 | C104: =+'[1]Senda Inflación Total'!D588 -> 52.1 | D104: ='[2]Abr-03'!$D$606/1000 -> 32149.415 | E104: ='[2]Abr-03'!$D$607/1000 -> 1153.1318 | F104: ='[2]Abr-03'!$D$617/1000 -> 8270.0024 | G104: ='[2]Abr-03'!$D$618/1000 -> 525.08825 | H104: ='[2]Abr-03'!$D$630/1000 -> 10904.051 | I104: ='[2]Abr-03'!$D$631/1000 -> 2634.9751 | J104: ='[2]Abr-03'!$D$641/1000 -> 398.39196 | K104: ='[2]Abr-03'!$D$642/1000 -> 27.21231 | L104: =+H104+(Titularizaciones!C16/1000) -> 11846.796 | M104: =+I104+((Titularizaciones!C16/1000)*Titularizaciones!M16) -> 2641.7185 | N104: =+D104+F104+H104+J104 -> 51721.861 | O104: =+E104+G104+I104+K104 -> 4340.4075 | P104: =+L104+J104+F104+D104 -> 52664.606 | Q104: =+M104+K104+G104+E104 -> 4347.1509 | R104: =+D104+F104+L104 -> 52266.214 | S104: =+E104+G104+M104 -> 4319.9386 | V104: =+D104/D92*100-100 -> 14.023308 | W104: =+E104/E92*100-100 -> -30.200606 | X104: =+F104/F92*100-100 -> 22.994067 | Y104: =+G104/G92*100-100 -> 0.3484679 | Z104: =+H104/H92*100-100 -> -9.7389766 | AA104: =+I104/I92*100-100 -> -3.5979587 | AB104: =+J104/J92*100-100 -> 33.740826 | AC104: =+K104/K92*100-100 -> 5.5376787 | ... AK104: =+S104/S92*100-100 -> -11.993333 | AN104: =+(1+V104/100)/(1+$B104/100)*100-100 -> 5.7239755 | AO104: =+(1+W104/100)/(1+$B104/100)*100-100 -> -35.281044 | AP104: =+(1+X104/100)/(1+$B104/100)*100-100 -> 14.041787 | AQ104: =+(1+Y104/100)/(1+$B104/100)*100-100 -> -6.9555235 | AR104: =+(1+Z104/100)/(1+$B104/100)*100-100 -> -16.30874 | AS104: =+(1+AA104/100)/(1+$B104/100)*100-100 -> -10.614704 | AT104: =+(1+AB104/100)/(1+$B104/100)*100-100 -> 24.006329 | AU104: =+(1+AC104/100)/(1+$B104/100)*100-100 -> -2.144016 | ... BC104: =+(1+AK104/100)/(1+$B104/100)*100-100 -> -18.399011 | BF104: =+(E104/D104)*100 -> 3.5867894 | BG104: =+(G104/F104)*100 -> 6.3493119 | BH104: =+(I104/H104)*100 -> 24.165102 | BI104: =+(K104/J104)*100 -> 6.8305369 | BJ104: =+(M104/L104)*100 -> 22.299013 | BK104: =+(O104/N104)*100 -> 8.3918239 | BL104: =+(Q104/P104)*100 -> 8.2544071 | BM104: =+(S104/R104)*100 -> 8.2652603 | BN104: =+(D104/$N104)*100 -> 62.158273 | BO104: =+(E104/$O104)*100 -> 26.567364 | BP104: =+(F104/$N104)*100 -> 15.989375 | BQ104: =+(G104/$O104)*100 -> 12.097672 | BR104: =+(H104/$N104)*100 -> 21.082094 | BS104: =+(I104/$O104)*100 -> 60.708012 | BT104: =+(J104/$N104)*100 -> 0.77025836 | BU104: =+(K104/$O104)*100 -> 0.62695289 | BV104: ND | BW104: ND | BX104: =+(N104/$N104)*100 -> 100 | BY104: =+(O104/$O104)*100 -> 100 | BZ104: ND | CA104: ND
A105: 37742 | B105: =+'[1]Senda Inflación Total'!F589 -> 7.73 | C105: =+'[1]Senda Inflación Total'!D589 -> 52.36 | D105: ='[2]May-03'!$D$606/1000 -> 32386.058 | E105: ='[2]May-03'!$D$607/1000 -> 1187.8461 | F105: ='[2]May-03'!$D$617/1000 -> 8419.3461 | G105: ='[2]May-03'!$D$618/1000 -> 517.99841 | H105: ='[2]May-03'!$D$630/1000 -> 10893.25 | I105: ='[2]May-03'!$D$631/1000 -> 2621.1245 | J105: ='[2]May-03'!$D$641/1000 -> 413.76973 | K105: ='[2]May-03'!$D$642/1000 -> 26.62524 | L105: =+H105+(Titularizaciones!C17/1000) -> 11828.127 | M105: =+I105+((Titularizaciones!C17/1000)*Titularizaciones!M17) -> 2628.5822 | N105: =+D105+F105+H105+J105 -> 52112.424 | O105: =+E105+G105+I105+K105 -> 4353.5942 | P105: =+L105+J105+F105+D105 -> 53047.301 | Q105: =+M105+K105+G105+E105 -> 4361.0519 | R105: =+D105+F105+L105 -> 52633.531 | S105: =+E105+G105+M105 -> 4334.4267 | V105: =+D105/D93*100-100 -> 15.261981 | W105: =+E105/E93*100-100 -> -25.184744 | X105: =+F105/F93*100-100 -> 21.181845 | Y105: =+G105/G93*100-100 -> -0.97285484 | Z105: =+H105/H93*100-100 -> -7.5397996 | AA105: =+I105/I93*100-100 -> -5.8234003 | AB105: =+J105/J93*100-100 -> 37.08317 | AC105: =+K105/K93*100-100 -> 4.8141647 | ... AK105: =+S105/S93*100-100 -> -11.436436 | AN105: =+(1+V105/100)/(1+$B105/100)*100-100 -> 6.9915357 | AO105: =+(1+W105/100)/(1+$B105/100)*100-100 -> -30.552998 | AP105: =+(1+X105/100)/(1+$B105/100)*100-100 -> 12.486628 | AQ105: =+(1+Y105/100)/(1+$B105/100)*100-100 -> -8.0783949 | AR105: =+(1+Z105/100)/(1+$B105/100)*100-100 -> -14.174139 | AS105: =+(1+AA105/100)/(1+$B105/100)*100-100 -> -12.580897 | AT105: =+(1+AB105/100)/(1+$B105/100)*100-100 -> 27.246979 | AU105: =+(1+AC105/100)/(1+$B105/100)*100-100 -> -2.706614 | ... BC105: =+(1+AK105/100)/(1+$B105/100)*100-100 -> -17.791178 | BF105: =+(E105/D105)*100 -> 3.66777 | BG105: =+(G105/F105)*100 -> 6.1524779 | BH105: =+(I105/H105)*100 -> 24.061914 | BI105: =+(K105/J105)*100 -> 6.4347965 | BJ105: =+(M105/L105)*100 -> 22.223148 | BK105: =+(O105/N105)*100 -> 8.3542348 | BL105: =+(Q105/P105)*100 -> 8.2210628 | BM105: =+(S105/R105)*100 -> 8.2351053 | BN105: =+(D105/$N105)*100 -> 62.14652 | BO105: =+(E105/$O105)*100 -> 27.284263 | BP105: =+(F105/$N105)*100 -> 16.156121 | BQ105: =+(G105/$O105)*100 -> 11.898178 | BR105: =+(H105/$N105)*100 -> 20.903365 | BS105: =+(I105/$O105)*100 -> 60.205989 | BT105: =+(J105/$N105)*100 -> 0.79399441 | BU105: =+(K105/$O105)*100 -> 0.61156917 | BV105: ND | BW105: ND | BX105: =+(N105/$N105)*100 -> 100 | BY105: =+(O105/$O105)*100 -> 100 | BZ105: ND | CA105: ND
A106: 37773 | B106: =+'[1]Senda Inflación Total'!F590 -> 7.21 | C106: =+'[1]Senda Inflación Total'!D590 -> 52.33 | D106: ='[2]Jun-03'!$D$606/1000 -> 32168.067 | E106: ='[2]Jun-03'!$D$607/1000 -> 1078.5318 | F106: ='[2]Jun-03'!$D$617/1000 -> 8578.8609 | G106: ='[2]Jun-03'!$D$618/1000 -> 522.98704 | H106: ='[2]Jun-03'!$D$630/1000 -> 10380.294 | I106: ='[2]Jun-03'!$D$631/1000 -> 2550.9957 | J106: ='[2]Jun-03'!$D$641/1000 -> 429.06067 | K106: ='[2]Jun-03'!$D$642/1000 -> 27.66785 | L106: =+H106+(Titularizaciones!C18/1000) -> 11753.587 | M106: =+I106+((Titularizaciones!C18/1000)*Titularizaciones!M18) -> 2559.8434 | N106: =+D106+F106+H106+J106 -> 51556.283 | O106: =+E106+G106+I106+K106 -> 4180.1824 | P106: =+L106+J106+F106+D106 -> 52929.576 | Q106: =+M106+K106+G106+E106 -> 4189.0301 | R106: =+D106+F106+L106 -> 52500.515 | S106: =+E106+G106+M106 -> 4161.3622 | V106: =+D106/D94*100-100 -> 12.763 | W106: =+E106/E94*100-100 -> -26.869116 | X106: =+F106/F94*100-100 -> 23.084146 | Y106: =+G106/G94*100-100 -> 5.3435628 | Z106: =+H106/H94*100-100 -> -11.540195 | AA106: =+I106/I94*100-100 -> -8.8459612 | AB106: =+J106/J94*100-100 -> 41.584266 | AC106: =+K106/K94*100-100 -> 6.3516921 | ... AK106: =+S106/S94*100-100 -> -12.760766 | AN106: =+(1+V106/100)/(1+$B106/100)*100-100 -> 5.1795541 | AO106: =+(1+W106/100)/(1+$B106/100)*100-100 -> -31.787255 | AP106: =+(1+X106/100)/(1+$B106/100)*100-100 -> 14.806591 | AQ106: =+(1+Y106/100)/(1+$B106/100)*100-100 -> -1.7409171 | AR106: =+(1+Z106/100)/(1+$B106/100)*100-100 -> -17.489222 | AS106: =+(1+AA106/100)/(1+$B106/100)*100-100 -> -14.976179 | AT106: =+(1+AB106/100)/(1+$B106/100)*100-100 -> 32.062556 | AU106: =+(1+AC106/100)/(1+$B106/100)*100-100 -> -0.80058572 | ... BC106: =+(1+AK106/100)/(1+$B106/100)*100-100 -> -18.627709 | BF106: =+(E106/D106)*100 -> 3.3528025 | BG106: =+(G106/F106)*100 -> 6.0962294 | BH106: =+(I106/H106)*100 -> 24.57537 | BI106: =+(K106/J106)*100 -> 6.4484703 | BJ106: =+(M106/L106)*100 -> 21.779253 | BK106: =+(O106/N106)*100 -> 8.107998 | BL106: =+(Q106/P106)*100 -> 7.9143466 | BM106: =+(S106/R106)*100 -> 7.9263265 | BN106: =+(D106/$N106)*100 -> 62.394078 | BO106: =+(E106/$O106)*100 -> 25.80107 | BP106: =+(F106/$N106)*100 -> 16.639797 | BQ106: =+(G106/$O106)*100 -> 12.511106 | BR106: =+(H106/$N106)*100 -> 20.133907 | BS106: =+(I106/$O106)*100 -> 61.025943 | BT106: =+(J106/$N106)*100 -> 0.83221801 | BU106: =+(K106/$O106)*100 -> 0.66188141 | BV106: ND | BW106: ND | BX106: =+(N106/$N106)*100 -> 100 | BY106: =+(O106/$O106)*100 -> 100 | BZ106: ND | CA106: ND
A107: 37803 | B107: =+'[1]Senda Inflación Total'!F591 -> 7.04 | C107: =+'[1]Senda Inflación Total'!D591 -> 52.26 | D107: ='[2]Ago-03'!$D$606/1000 -> 32413.135 | E107: ='[2]Jul-03'!$D$607/1000 -> 1050.0101 | F107: ='[2]Jul-03'!$D$617/1000 -> 8726.6505 | G107: ='[2]Jul-03'!$D$618/1000 -> 486.17125 | H107: ='[2]Jul-03'!$D$630/1000 -> 10309.857 | I107: ='[2]Jul-03'!$D$631/1000 -> 2522.8777 | J107: ='[2]Jul-03'!$D$641/1000 -> 461.05199 | K107: ='[2]Jul-03'!$D$642/1000 -> 27.53214 | L107: =+H107+(Titularizaciones!C19/1000) -> 11660.414 | M107: =+I107+((Titularizaciones!C19/1000)*Titularizaciones!M19) -> 2532.1309 | N107: =+D107+F107+H107+J107 -> 51910.694 | O107: =+E107+G107+I107+K107 -> 4086.5913 | P107: =+L107+J107+F107+D107 -> 53261.251 | Q107: =+M107+K107+G107+E107 -> 4095.8444 | R107: =+D107+F107+L107 -> 52800.199 | S107: =+E107+G107+M107 -> 4068.3123 | V107: =+D107/D95*100-100 -> 11.025954 | W107: =+E107/E95*100-100 -> -27.441438 | X107: =+F107/F95*100-100 -> 21.664411 | Y107: =+G107/G95*100-100 -> 2.4702956 | Z107: =+H107/H95*100-100 -> -11.587411 | AA107: =+I107/I95*100-100 -> -9.1834137 | AB107: =+J107/J95*100-100 -> 49.786249 | AC107: =+K107/K95*100-100 -> 4.9469112 | ... AK107: =+S107/S95*100-100 -> -13.442641 | AN107: =+(1+V107/100)/(1+$B107/100)*100-100 -> 3.7237988 | AO107: =+(1+W107/100)/(1+$B107/100)*100-100 -> -32.2136 | AP107: =+(1+X107/100)/(1+$B107/100)*100-100 -> 13.662566 | AQ107: =+(1+Y107/100)/(1+$B107/100)*100-100 -> -4.2691558 | AR107: =+(1+Z107/100)/(1+$B107/100)*100-100 -> -17.402289 | AS107: =+(1+AA107/100)/(1+$B107/100)*100-100 -> -15.156403 | AT107: =+(1+AB107/100)/(1+$B107/100)*100-100 -> 39.934836 | AU107: =+(1+AC107/100)/(1+$B107/100)*100-100 -> -1.9554268 | ... BC107: =+(1+AK107/100)/(1+$B107/100)*100-100 -> -19.135501 | BF107: =+(E107/D107)*100 -> 3.2394588 | BG107: =+(G107/F107)*100 -> 5.5711094 | BH107: =+(I107/H107)*100 -> 24.470542 | BI107: =+(K107/J107)*100 -> 5.9715912 | BJ107: =+(M107/L107)*100 -> 21.715616 | BK107: =+(O107/N107)*100 -> 7.8723496 | BL107: =+(Q107/P107)*100 -> 7.6901017 | BM107: =+(S107/R107)*100 -> 7.7051077 | BN107: =+(D107/$N107)*100 -> 62.440188 | BO107: =+(E107/$O107)*100 -> 25.694034 | BP107: =+(F107/$N107)*100 -> 16.810892 | BQ107: =+(G107/$O107)*100 -> 11.896743 | BR107: =+(H107/$N107)*100 -> 19.860757 | BS107: =+(I107/$O107)*100 -> 61.735504 | BT107: =+(J107/$N107)*100 -> 0.8881638 | BU107: =+(K107/$O107)*100 -> 0.67371896 | BV107: ND | BW107: ND | BX107: =+(N107/$N107)*100 -> 100 | BY107: =+(O107/$O107)*100 -> 100 | BZ107: ND | CA107: ND
A108: 37834 | B108: =+'[1]Senda Inflación Total'!F592 -> 7.26 | C108: =+'[1]Senda Inflación Total'!D592 -> 52.42 | D108: ='[2]Ago-03'!$D$606/1000 -> 32413.135 | E108: ='[2]Ago-03'!$D$607/1000 -> 1053.8505 | F108: ='[2]Ago-03'!$D$617/1000 -> 8906.87 | G108: ='[2]Ago-03'!$D$618/1000 -> 519.35932 | H108: ='[2]Ago-03'!$D$630/1000 -> 10310.91 | I108: ='[2]Ago-03'!$D$631/1000 -> 2529.1488 | J108: ='[2]Ago-03'!$D$641/1000 -> 479.45822 | K108: ='[2]Ago-03'!$D$642/1000 -> 27.92097 | L108: =+H108+(Titularizaciones!C20/1000) -> 11636.173 | M108: =+I108+((Titularizaciones!C20/1000)*Titularizaciones!M20) -> 2539.5232 | N108: =+D108+F108+H108+J108 -> 52110.373 | O108: =+E108+G108+I108+K108 -> 4130.2796 | P108: =+L108+J108+F108+D108 -> 53435.636 | Q108: =+M108+K108+G108+E108 -> 4140.654 | R108: =+D108+F108+L108 -> 52956.178 | S108: =+E108+G108+M108 -> 4112.733 | V108: =+D108/D96*100-100 -> 10.609544 | W108: =+E108/E96*100-100 -> -25.582309 | X108: =+F108/F96*100-100 -> 22.05651 | Y108: =+G108/G96*100-100 -> 10.497417 | Z108: =+H108/H96*100-100 -> -10.940083 | AA108: =+I108/I96*100-100 -> -8.0746005 | AB108: =+J108/J96*100-100 -> 50.288317 | AC108: =+K108/K96*100-100 -> 8.3857451 | ... AK108: =+S108/S96*100-100 -> -11.339073 | AN108: =+(1+V108/100)/(1+$B108/100)*100-100 -> 3.1228268 | AO108: =+(1+W108/100)/(1+$B108/100)*100-100 -> -30.619344 | AP108: =+(1+X108/100)/(1+$B108/100)*100-100 -> 13.794994 | AQ108: =+(1+Y108/100)/(1+$B108/100)*100-100 -> 3.0182895 | AR108: =+(1+Z108/100)/(1+$B108/100)*100-100 -> -16.968193 | AS108: =+(1+AA108/100)/(1+$B108/100)*100-100 -> -14.296663 | AT108: =+(1+AB108/100)/(1+$B108/100)*100-100 -> 40.115902 | AU108: =+(1+AC108/100)/(1+$B108/100)*100-100 -> 1.0495479 | ... BC108: =+(1+AK108/100)/(1+$B108/100)*100-100 -> -17.340176 | BF108: =+(E108/D108)*100 -> 3.251307 | BG108: =+(G108/F108)*100 -> 5.830997 | BH108: =+(I108/H108)*100 -> 24.528861 | BI108: =+(K108/J108)*100 -> 5.8234417 | BJ108: =+(M108/L108)*100 -> 21.824384 | BK108: =+(O108/N108)*100 -> 7.926022 | BL108: =+(Q108/P108)*100 -> 7.7488625 | BM108: =+(S108/R108)*100 -> 7.766295 | BN108: =+(D108/$N108)*100 -> 62.200926 | BO108: =+(E108/$O108)*100 -> 25.515234 | BP108: =+(F108/$N108)*100 -> 17.092317 | BQ108: =+(G108/$O108)*100 -> 12.574435 | BR108: =+(H108/$N108)*100 -> 19.786675 | BS108: =+(I108/$O108)*100 -> 61.234324 | BT108: =+(J108/$N108)*100 -> 0.92008211 | BU108: =+(K108/$O108)*100 -> 0.67600677 | BV108: ND | BW108: ND | BX108: =+(N108/$N108)*100 -> 100 | BY108: =+(O108/$O108)*100 -> 100 | BZ108: ND | CA108: ND
A109: 37865 | B109: =+'[1]Senda Inflación Total'!F593 -> 7.11 | C109: =+'[1]Senda Inflación Total'!D593 -> 52.53 | D109: ='[2]Sep-03'!$D$606/1000 -> 32632.853 | E109: ='[2]Sep-03'!$D$607/1000 -> 999.57566 | F109: ='[2]Sep-03'!$D$617/1000 -> 9033.8044 | G109: ='[2]Sep-03'!$D$618/1000 -> 521.69082 | H109: ='[2]Sep-03'!$D$630/1000 -> 10241.6 | I109: ='[2]Sep-03'!$D$631/1000 -> 2498.2554 | J109: ='[2]Sep-03'!$D$641/1000 -> 512.24366 | K109: ='[2]Sep-03'!$D$642/1000 -> 27.11449 | L109: =+H109+(Titularizaciones!C21/1000) -> 11544.37 | M109: =+I109+((Titularizaciones!C21/1000)*Titularizaciones!M21) -> 2510.0165 | N109: =+D109+F109+H109+J109 -> 52420.501 | O109: =+E109+G109+I109+K109 -> 4046.6363 | P109: =+L109+J109+F109+D109 -> 53723.27 | Q109: =+M109+K109+G109+E109 -> 4058.3975 | R109: =+D109+F109+L109 -> 53211.027 | S109: =+E109+G109+M109 -> 4031.283 | V109: =+D109/D97*100-100 -> 8.9604567 | W109: =+E109/E97*100-100 -> -26.468496 | X109: =+F109/F97*100-100 -> 21.621139 | Y109: =+G109/G97*100-100 -> 5.6762151 | Z109: =+H109/H97*100-100 -> -10.956096 | AA109: =+I109/I97*100-100 -> -9.3188198 | AB109: =+J109/J97*100-100 -> 55.930194 | AC109: =+K109/K97*100-100 -> 1.9563274 | ... AK109: =+S109/S97*100-100 -> -12.552435 | AN109: =+(1+V109/100)/(1+$B109/100)*100-100 -> 1.7276227 | AO109: =+(1+W109/100)/(1+$B109/100)*100-100 -> -31.349544 | AP109: =+(1+X109/100)/(1+$B109/100)*100-100 -> 13.547885 | AQ109: =+(1+Y109/100)/(1+$B109/100)*100-100 -> -1.3386097 | AR109: =+(1+Z109/100)/(1+$B109/100)*100-100 -> -16.866862 | AS109: =+(1+AA109/100)/(1+$B109/100)*100-100 -> -15.338269 | AT109: =+(1+AB109/100)/(1+$B109/100)*100-100 -> 45.579492 | AU109: =+(1+AC109/100)/(1+$B109/100)*100-100 -> -4.81157 | ... BC109: =+(1+AK109/100)/(1+$B109/100)*100-100 -> -18.357235 | BF109: =+(E109/D109)*100 -> 3.0630962 | BG109: =+(G109/F109)*100 -> 5.774874 | BH109: =+(I109/H109)*100 -> 24.393213 | BI109: =+(K109/J109)*100 -> 5.2932798 | BJ109: =+(M109/L109)*100 -> 21.742344 | BK109: =+(O109/N109)*100 -> 7.7195683 | BL109: =+(Q109/P109)*100 -> 7.5542636 | BM109: =+(S109/R109)*100 -> 7.5760293 | BN109: =+(D109/$N109)*100 -> 62.252081 | BO109: =+(E109/$O109)*100 -> 24.701396 | BP109: =+(F109/$N109)*100 -> 17.233342 | BQ109: =+(G109/$O109)*100 -> 12.891962 | BR109: =+(H109/$N109)*100 -> 19.537395 | BS109: =+(I109/$O109)*100 -> 61.736592 | BT109: =+(J109/$N109)*100 -> 0.97718193 | BU109: =+(K109/$O109)*100 -> 0.67005008 | BV109: ND | BW109: ND | BX109: =+(N109/$N109)*100 -> 100 | BY109: =+(O109/$O109)*100 -> 100 | BZ109: ND | CA109: ND
A110: 37895 | B110: =+'[1]Senda Inflación Total'!F594 -> 6.58 | C110: =+'[1]Senda Inflación Total'!D594 -> 52.56 | D110: ='[2]Oct-03'!$D$606/1000 -> 33225.454 | E110: ='[2]Oct-03'!$D$607/1000 -> 973.80462 | F110: ='[2]Oct-03'!$D$617/1000 -> 9224.8045 | G110: ='[2]Oct-03'!$D$618/1000 -> 520.21058 | H110: ='[2]Oct-03'!$D$630/1000 -> 10211.755 | I110: ='[2]Oct-03'!$D$631/1000 -> 2477.793 | J110: ='[2]Oct-03'!$D$641/1000 -> 534.85188 | K110: ='[2]Oct-03'!$D$642/1000 -> 28.21631 | L110: =+H110+(Titularizaciones!C22/1000) -> 11494.597 | M110: =+I110+((Titularizaciones!C22/1000)*Titularizaciones!M22) -> 2491.3277 | N110: =+D110+F110+H110+J110 -> 53196.866 | O110: =+E110+G110+I110+K110 -> 4000.0245 | P110: =+L110+J110+F110+D110 -> 54479.708 | Q110: =+M110+K110+G110+E110 -> 4013.5592 | R110: =+D110+F110+L110 -> 53944.856 | S110: =+E110+G110+M110 -> 3985.3429 | V110: =+D110/D98*100-100 -> 10.544497 | W110: =+E110/E98*100-100 -> -27.002993 | X110: =+F110/F98*100-100 -> 21.67989 | Y110: =+G110/G98*100-100 -> 5.5963935 | Z110: =+H110/H98*100-100 -> -10.550598 | AA110: =+I110/I98*100-100 -> -9.3416263 | AB110: =+J110/J98*100-100 -> 54.072348 | AC110: =+K110/K98*100-100 -> 0.51271036 | ... AK110: =+S110/S98*100-100 -> -12.643403 | AN110: =+(1+V110/100)/(1+$B110/100)*100-100 -> 3.7197378 | AO110: =+(1+W110/100)/(1+$B110/100)*100-100 -> -31.509657 | AP110: =+(1+X110/100)/(1+$B110/100)*100-100 -> 14.167658 | AQ110: =+(1+Y110/100)/(1+$B110/100)*100-100 -> -0.9228809 | AR110: =+(1+Z110/100)/(1+$B110/100)*100-100 -> -16.072995 | AS110: =+(1+AA110/100)/(1+$B110/100)*100-100 -> -14.938662 | AT110: =+(1+AB110/100)/(1+$B110/100)*100-100 -> 44.560282 | AU110: =+(1+AC110/100)/(1+$B110/100)*100-100 -> -5.6927094 | ... BC110: =+(1+AK110/100)/(1+$B110/100)*100-100 -> -18.036595 | BF110: =+(E110/D110)*100 -> 2.9308993 | BG110: =+(G110/F110)*100 -> 5.6392586 | BH110: =+(I110/H110)*100 -> 24.264124 | BI110: =+(K110/J110)*100 -> 5.2755372 | BJ110: =+(M110/L110)*100 -> 21.673901 | BK110: =+(O110/N110)*100 -> 7.519286 | BL110: =+(Q110/P110)*100 -> 7.3670717 | BM110: =+(S110/R110)*100 -> 7.3878089 | BN110: =+(D110/$N110)*100 -> 62.457541 | BO110: =+(E110/$O110)*100 -> 24.344967 | BP110: =+(F110/$N110)*100 -> 17.34088 | BQ110: =+(G110/$O110)*100 -> 13.005185 | BR110: =+(H110/$N110)*100 -> 19.196159 | BS110: =+(I110/$O110)*100 -> 61.944445 | BT110: =+(J110/$N110)*100 -> 1.0054199 | BU110: =+(K110/$O110)*100 -> 0.70540343 | BV110: ND | BW110: ND | BX110: =+(N110/$N110)*100 -> 100 | BY110: =+(O110/$O110)*100 -> 100 | BZ110: ND | CA110: ND
A111: 37926 | B111: =+'[1]Senda Inflación Total'!F595 -> 6.13 | C111: =+'[1]Senda Inflación Total'!D595 -> 52.75 | D111: ='[2]Nov-03'!$D$839/1000 -> 33431.128 | E111: ='[2]Nov-03'!$D$840/1000 -> 896.79463 | F111: ='[2]Nov-03'!$D$851/1000 -> 9434.4821 | G111: ='[2]Nov-03'!$D$852/1000 -> 549.54759 | H111: ='[2]Nov-03'!$D$865/1000 -> 9829.3031 | I111: ='[2]Nov-03'!$D$866/1000 -> 2442.5459 | J111: ='[2]Nov-03'!$D$877/1000 -> 557.05669 | K111: ='[2]Oct-03'!$D$642/1000 -> 28.21631 | L111: =+H111+(Titularizaciones!C23/1000) -> 11410.56 | M111: =+I111+((Titularizaciones!C23/1000)*Titularizaciones!M23) -> 2458.337 | N111: =+D111+F111+H111+J111 -> 53251.97 | O111: =+E111+G111+I111+K111 -> 3917.1044 | P111: =+L111+J111+F111+D111 -> 54833.228 | Q111: =+M111+K111+G111+E111 -> 3932.8955 | R111: =+D111+F111+L111 -> 54276.171 | S111: =+E111+G111+M111 -> 3904.6792 | V111: =+D111/D99*100-100 -> 8.9372371 | W111: =+E111/E99*100-100 -> -33.120671 | X111: =+F111/F99*100-100 -> 21.968716 | Y111: =+G111/G99*100-100 -> 6.014877 | Z111: =+H111/H99*100-100 -> -9.0700123 | AA111: =+I111/I99*100-100 -> -10.656397 | AB111: =+J111/J99*100-100 -> 57.149951 | AC111: =+K111/K99*100-100 -> -2.1700155 | ... AK111: =+S111/S99*100-100 -> -15.042441 | AN111: =+(1+V111/100)/(1+$B111/100)*100-100 -> 2.6450929 | AO111: =+(1+W111/100)/(1+$B111/100)*100-100 -> -36.983578 | AP111: =+(1+X111/100)/(1+$B111/100)*100-100 -> 14.923882 | AQ111: =+(1+Y111/100)/(1+$B111/100)*100-100 -> -0.10847355 | AR111: =+(1+Z111/100)/(1+$B111/100)*100-100 -> -14.322069 | AS111: =+(1+AA111/100)/(1+$B111/100)*100-100 -> -15.816825 | AT111: =+(1+AB111/100)/(1+$B111/100)*100-100 -> 48.073071 | AU111: =+(1+AC111/100)/(1+$B111/100)*100-100 -> -7.820612 | ... BC111: =+(1+AK111/100)/(1+$B111/100)*100-100 -> -19.949534 | BF111: =+(E111/D111)*100 -> 2.6825138 | BG111: =+(G111/F111)*100 -> 5.8248835 | BH111: =+(I111/H111)*100 -> 24.849635 | BI111: =+(K111/J111)*100 -> 5.0652493 | BJ111: =+(M111/L111)*100 -> 21.544402 | BK111: =+(O111/N111)*100 -> 7.3557925 | BL111: =+(Q111/P111)*100 -> 7.1724677 | BM111: =+(S111/R111)*100 -> 7.1940949 | BN111: =+(D111/$N111)*100 -> 62.779139 | BO111: =+(E111/$O111)*100 -> 22.894325 | BP111: =+(F111/$N111)*100 -> 17.716682 | BQ111: =+(G111/$O111)*100 -> 14.029434 | BR111: =+(H111/$N111)*100 -> 18.458102 | BS111: =+(I111/$O111)*100 -> 62.355905 | BT111: =+(J111/$N111)*100 -> 1.0460771 | BU111: =+(K111/$O111)*100 -> 0.72033591 | BV111: ND | BW111: ND | BX111: =+(N111/$N111)*100 -> 100 | BY111: =+(O111/$O111)*100 -> 100 | BZ111: ND | CA111: ND
A112: 37956 | B112: =+'[1]Senda Inflación Total'!F596 -> 6.49 | C112: =+'[1]Senda Inflación Total'!D596 -> 53.07 | D112: ='[2]Dic-03'!$D$606/1000 -> 33381.563 | E112: ='[2]Dic-03'!$D$607/1000 -> 819.22153 | F112: ='[2]Dic-03'!$D$617/1000 -> 9586.7248 | G112: ='[2]Dic-03'!$D$618/1000 -> 487.03234 | H112: ='[2]Dic-03'!$D$630/1000 -> 9626.2955 | I112: ='[2]Dic-03'!$D$631/1000 -> 2267.163 | J112: ='[2]Dic-03'!$D$641/1000 -> 568.0288 | K112: ='[2]Dic-03'!$D$642/1000 -> 30.40558 | L112: =+H112+(Titularizaciones!C24/1000) -> 11179.672 | M112: =+I112+((Titularizaciones!C24/1000)*Titularizaciones!M24) -> 2283.3535 | N112: =+D112+F112+H112+J112 -> 53162.612 | O112: =+E112+G112+I112+K112 -> 3603.8225 | P112: =+L112+J112+F112+D112 -> 54715.988 | Q112: =+M112+K112+G112+E112 -> 3620.0129 | R112: =+D112+F112+L112 -> 54147.959 | S112: =+E112+G112+M112 -> 3589.6074 | V112: =+D112/D100*100-100 -> 7.4321048 | W112: =+E112/E100*100-100 -> -32.358834 | X112: =+F112/F100*100-100 -> 22.049917 | Y112: =+G112/G100*100-100 -> 5.534629 | Z112: =+H112/H100*100-100 -> -11.805606 | AA112: =+I112/I100*100-100 -> -15.658278 | AB112: =+J112/J100*100-100 -> 45.755556 | AC112: =+K112/K100*100-100 -> 18.948919 | ... AK112: =+S112/S100*100-100 -> -17.739127 | AN112: =+(1+V112/100)/(1+$B112/100)*100-100 -> 0.88468854 | AO112: =+(1+W112/100)/(1+$B112/100)*100-100 -> -36.481204 | AP112: =+(1+X112/100)/(1+$B112/100)*100-100 -> 14.611623 | AQ112: =+(1+Y112/100)/(1+$B112/100)*100-100 -> -0.89714617 | AR112: =+(1+Z112/100)/(1+$B112/100)*100-100 -> -17.180586 | AS112: =+(1+AA112/100)/(1+$B112/100)*100-100 -> -20.798458 | AT112: =+(1+AB112/100)/(1+$B112/100)*100-100 -> 36.872528 | AU112: =+(1+AC112/100)/(1+$B112/100)*100-100 -> 11.699614 | ... BC112: =+(1+AK112/100)/(1+$B112/100)*100-100 -> -22.75249 | BF112: =+(E112/D112)*100 -> 2.4541138 | BG112: =+(G112/F112)*100 -> 5.0802787 | BH112: =+(I112/H112)*100 -> 23.55177 | BI112: =+(K112/J112)*100 -> 5.3528237 | BJ112: =+(M112/L112)*100 -> 20.424155 | BK112: =+(O112/N112)*100 -> 6.7788664 | BL112: =+(Q112/P112)*100 -> 6.6160058 | BM112: =+(S112/R112)*100 -> 6.629257 | BN112: =+(D112/$N112)*100 -> 62.791427 | BO112: =+(E112/$O112)*100 -> 22.732017 | BP112: =+(F112/$N112)*100 -> 18.032833 | BQ112: =+(G112/$O112)*100 -> 13.514327 | BR112: =+(H112/$N112)*100 -> 18.107266 | BS112: =+(I112/$O112)*100 -> 62.909953 | BT112: =+(J112/$N112)*100 -> 1.0684742 | BU112: =+(K112/$O112)*100 -> 0.8437036 | BV112: ND | BW112: ND | BX112: =+(N112/$N112)*100 -> 100 | BY112: =+(O112/$O112)*100 -> 100 | BZ112: ND | CA112: ND
A113: 37987 | B113: =+'[1]Senda Inflación Total'!F597 -> 6.19 | C113: =+'[1]Senda Inflación Total'!D597 -> 53.54 | D113: ='[2]Ene-04'!$D$834/1000 -> 35774.11 | E113: ='[2]Ene-04'!$D$835/1000 -> 1006.98 | F113: ='[2]Ene-04'!$D$846/1000 -> 9907.1938 | G113: ='[2]Ene-04'!$D$847/1000 -> 524.72935 | H113: ='[2]Ene-04'!$D$860/1000 -> 9606.4811 | I113: ='[2]Ene-04'!$D$861/1000 -> 2269.5299 | J113: ='[2]Ene-04'!$D$872/1000 -> 578.94287 | K113: ='[2]Ene-04'!$D$873/1000 -> 32.4956 | L113: =+H113+(Titularizaciones!C25/1000) -> 11141.285 | M113: =+I113+((Titularizaciones!C25/1000)*Titularizaciones!M25) -> 2287.5729 | N113: =+D113+F113+H113+J113 -> 55866.728 | O113: =+E113+G113+I113+K113 -> 3833.7349 | P113: =+L113+J113+F113+D113 -> 57401.532 | Q113: =+M113+K113+G113+E113 -> 3851.7779 | R113: =+D113+F113+L113 -> 56822.589 | S113: =+E113+G113+M113 -> 3819.2823 | V113: =+D113/D101*100-100 -> 15.045606 | W113: =+E113/E101*100-100 -> -16.061723 | X113: =+F113/F101*100-100 -> 23.596885 | Y113: =+G113/G101*100-100 -> 7.4301932 | Z113: =+H113/H101*100-100 -> -11.795549 | AA113: =+I113/I101*100-100 -> -15.584858 | AB113: =+J113/J101*100-100 -> 42.584141 | AC113: =+K113/K101*100-100 -> 22.8877 | ... AK113: =+S113/S101*100-100 -> -12.815583 | AN113: =+(1+V113/100)/(1+$B113/100)*100-100 -> 8.3393976 | AO113: =+(1+W113/100)/(1+$B113/100)*100-100 -> -20.954631 | AP113: =+(1+X113/100)/(1+$B113/100)*100-100 -> 16.392207 | AQ113: =+(1+Y113/100)/(1+$B113/100)*100-100 -> 1.1679002 | AR113: =+(1+Z113/100)/(1+$B113/100)*100-100 -> -16.93714 | AS113: =+(1+AA113/100)/(1+$B113/100)*100-100 -> -20.505564 | AT113: =+(1+AB113/100)/(1+$B113/100)*100-100 -> 34.272663 | AU113: =+(1+AC113/100)/(1+$B113/100)*100-100 -> 15.724362 | ... BC113: =+(1+AK113/100)/(1+$B113/100)*100-100 -> -17.897714 | BF113: =+(E113/D113)*100 -> 2.814829 | BG113: =+(G113/F113)*100 -> 5.2964478 | BH113: =+(I113/H113)*100 -> 23.624987 | BI113: =+(K113/J113)*100 -> 5.61292 | BJ113: =+(M113/L113)*100 -> 20.532397 | BK113: =+(O113/N113)*100 -> 6.8622864 | BL113: =+(Q113/P113)*100 -> 6.7102354 | BM113: =+(S113/R113)*100 -> 6.7214155 | BN113: =+(D113/$N113)*100 -> 64.034733 | BO113: =+(E113/$O113)*100 -> 26.266293 | BP113: =+(F113/$N113)*100 -> 17.733621 | BQ113: =+(G113/$O113)*100 -> 13.687158 | BR113: =+(H113/$N113)*100 -> 17.195353 | BS113: =+(I113/$O113)*100 -> 59.198927 | BT113: =+(J113/$N113)*100 -> 1.0362928 | BU113: =+(K113/$O113)*100 -> 0.84762251 | BV113: ND | BW113: ND | BX113: =+(N113/$N113)*100 -> 100 | BY113: =+(O113/$O113)*100 -> 100 | BZ113: ND | CA113: ND
A114: 38018 | B114: =+'[1]Senda Inflación Total'!F598 -> 6.28 | C114: =+'[1]Senda Inflación Total'!D598 -> 54.18 | D114: ='[2]Feb-04'!$D$834/1000 -> 36291.919 | E114: ='[2]Feb-04'!$D$835/1000 -> 988.10156 | F114: ='[2]Feb-04'!$D$846/1000 -> 10001.196 | G114: ='[2]Feb-04'!$D$847/1000 -> 551.20073 | H114: ='[2]Feb-04'!$D$860/1000 -> 9590.3602 | I114: ='[2]Feb-04'!$D$861/1000 -> 2224.4871 | J114: ='[2]Feb-04'!$D$872/1000 -> 599.03734 | K114: ='[2]Feb-04'!$D$873/1000 -> 33.45106 | L114: =+H114+(Titularizaciones!C26/1000) -> 11108.743 | M114: =+I114+((Titularizaciones!C26/1000)*Titularizaciones!M26) -> 2242.7748 | N114: =+D114+F114+H114+J114 -> 56482.513 | O114: =+E114+G114+I114+K114 -> 3797.2404 | P114: =+L114+J114+F114+D114 -> 58000.895 | Q114: =+M114+K114+G114+E114 -> 3815.5281 | R114: =+D114+F114+L114 -> 57401.858 | S114: =+E114+G114+M114 -> 3782.077 | V114: =+D114/D102*100-100 -> 15.520574 | W114: =+E114/E102*100-100 -> -20.504123 | X114: =+F114/F102*100-100 -> 24.031576 | Y114: =+G114/G102*100-100 -> 7.299072 | Z114: =+H114/H102*100-100 -> -11.60682 | AA114: =+I114/I102*100-100 -> -15.948539 | AB114: =+J114/J102*100-100 -> 43.887685 | AC114: =+K114/K102*100-100 -> 22.194492 | ... AK114: =+S114/S102*100-100 -> -14.202531 | AN114: =+(1+V114/100)/(1+$B114/100)*100-100 -> 8.6945563 | AO114: =+(1+W114/100)/(1+$B114/100)*100-100 -> -25.201471 | AP114: =+(1+X114/100)/(1+$B114/100)*100-100 -> 16.702649 | AQ114: =+(1+Y114/100)/(1+$B114/100)*100-100 -> 0.95885585 | AR114: =+(1+Z114/100)/(1+$B114/100)*100-100 -> -16.829902 | AS114: =+(1+AA114/100)/(1+$B114/100)*100-100 -> -20.915073 | AT114: =+(1+AB114/100)/(1+$B114/100)*100-100 -> 35.385477 | AU114: =+(1+AC114/100)/(1+$B114/100)*100-100 -> 14.974118 | ... BC114: =+(1+AK114/100)/(1+$B114/100)*100-100 -> -19.272234 | BF114: =+(E114/D114)*100 -> 2.722649 | BG114: =+(G114/F114)*100 -> 5.5113481 | BH114: =+(I114/H114)*100 -> 23.195031 | BI114: =+(K114/J114)*100 -> 5.584136 | BJ114: =+(M114/L114)*100 -> 20.189276 | BK114: =+(O114/N114)*100 -> 6.7228603 | BL114: =+(Q114/P114)*100 -> 6.5783952 | BM114: =+(S114/R114)*100 -> 6.5887711 | BN114: =+(D114/$N114)*100 -> 64.253372 | BO114: =+(E114/$O114)*100 -> 26.02157 | BP114: =+(F114/$N114)*100 -> 17.706712 | BQ114: =+(G114/$O114)*100 -> 14.515824 | BR114: =+(H114/$N114)*100 -> 16.979344 | BS114: =+(I114/$O114)*100 -> 58.581676 | BT114: =+(J114/$N114)*100 -> 1.0605713 | BU114: =+(K114/$O114)*100 -> 0.88093079 | BV114: ND | BW114: ND | BX114: =+(N114/$N114)*100 -> 100 | BY114: =+(O114/$O114)*100 -> 100 | BZ114: ND | CA114: ND
A115: 38047 | B115: =+'[1]Senda Inflación Total'!F599 -> 6.21 | C115: =+'[1]Senda Inflación Total'!D599 -> 54.71 | D115: ='[2]Mar-04'!$D$834/1000 -> 35877.559 | E115: ='[2]Mar-04'!$D$835/1000 -> 950.16775 | F115: ='[2]Mar-04'!$D$846/1000 -> 10175.358 | G115: ='[2]Mar-04'!$D$847/1000 -> 564.62975 | H115: ='[2]Mar-04'!$D$860/1000 -> 9590.1302 | I115: ='[2]Mar-04'!$D$861/1000 -> 2176.7232 | J115: ='[2]Mar-04'!$D$872/1000 -> 603.82976 | K115: ='[2]Mar-04'!$D$873/1000 -> 35.97806 | L115: =+H115+(Titularizaciones!C27/1000) -> 11086.574 | M115: =+I115+((Titularizaciones!C27/1000)*Titularizaciones!M27) -> 2194.1256 | N115: =+D115+F115+H115+J115 -> 56246.878 | O115: =+E115+G115+I115+K115 -> 3727.4988 | P115: =+L115+J115+F115+D115 -> 57743.322 | Q115: =+M115+K115+G115+E115 -> 3744.9012 | R115: =+D115+F115+L115 -> 57139.492 | S115: =+E115+G115+M115 -> 3708.9231 | V115: =+D115/D103*100-100 -> 12.966161 | W115: =+E115/E103*100-100 -> -20.30922 | X115: =+F115/F103*100-100 -> 25.654617 | Y115: =+G115/G103*100-100 -> 6.3025666 | Z115: =+H115/H103*100-100 -> -12.077389 | AA115: =+I115/I103*100-100 -> -17.702316 | AB115: =+J115/J103*100-100 -> 41.768775 | AC115: =+K115/K103*100-100 -> 30.968993 | ... AK115: =+S115/S103*100-100 -> -15.211373 | AN115: =+(1+V115/100)/(1+$B115/100)*100-100 -> 6.3611349 | AO115: =+(1+W115/100)/(1+$B115/100)*100-100 -> -24.968666 | AP115: =+(1+X115/100)/(1+$B115/100)*100-100 -> 18.307708 | AQ115: =+(1+Y115/100)/(1+$B115/100)*100-100 -> 0.087154329 | AR115: =+(1+Z115/100)/(1+$B115/100)*100-100 -> -17.218142 | AS115: =+(1+AA115/100)/(1+$B115/100)*100-100 -> -22.514185 | AT115: =+(1+AB115/100)/(1+$B115/100)*100-100 -> 33.479686 | AU115: =+(1+AC115/100)/(1+$B115/100)*100-100 -> 23.311358 | ... BC115: =+(1+AK115/100)/(1+$B115/100)*100-100 -> -20.168885 | BF115: =+(E115/D115)*100 -> 2.6483623 | BG115: =+(G115/F115)*100 -> 5.5489912 | BH115: =+(I115/H115)*100 -> 22.697535 | BI115: =+(K115/J115)*100 -> 5.9583118 | BJ115: =+(M115/L115)*100 -> 19.790836 | BK115: =+(O115/N115)*100 -> 6.6270323 | BL115: =+(Q115/P115)*100 -> 6.4854274 | BM115: =+(S115/R115)*100 -> 6.4909978 | BN115: =+(D115/$N115)*100 -> 63.785868 | BO115: =+(E115/$O115)*100 -> 25.49076 | BP115: =+(F115/$N115)*100 -> 18.09053 | BQ115: =+(G115/$O115)*100 -> 15.147684 | BR115: =+(H115/$N115)*100 -> 17.050067 | BS115: =+(I115/$O115)*100 -> 58.39635 | BT115: =+(J115/$N115)*100 -> 1.0735347 | BU115: =+(K115/$O115)*100 -> 0.96520649 | BV115: ND | BW115: ND | BX115: =+(N115/$N115)*100 -> 100 | BY115: =+(O115/$O115)*100 -> 100 | BZ115: ND | CA115: ND
A116: 38078 | B116: =+'[1]Senda Inflación Total'!F600 -> 5.49 | C116: =+'[1]Senda Inflación Total'!D600 -> 54.96 | D116: ='[2]Abr-04'!$D$834/1000 -> 36279.01 | E116: ='[2]Abr-04'!$D$835/1000 -> 980.00904 | F116: ='[2]Abr-04'!$D$846/1000 -> 10459.348 | G116: ='[2]Abr-04'!$D$847/1000 -> 587.74998 | H116: ='[2]Abr-04'!$D$860/1000 -> 9600.0151 | I116: ='[2]Abr-04'!$D$861/1000 -> 2149.8823 | J116: ='[2]Abr-04'!$D$872/1000 -> 598.98181 | K116: ='[2]Abr-04'!$D$873/1000 -> 39.03819 | L116: =+H116+(Titularizaciones!C28/1000) -> 11083.721 | M116: =+I116+((Titularizaciones!C28/1000)*Titularizaciones!M28) -> 2165.0673 | N116: =+D116+F116+H116+J116 -> 56937.354 | O116: =+E116+G116+I116+K116 -> 3756.6795 | P116: =+L116+J116+F116+D116 -> 58421.06 | Q116: =+M116+K116+G116+E116 -> 3771.8645 | R116: =+D116+F116+L116 -> 57822.078 | S116: =+E116+G116+M116 -> 3732.8263 | V116: =+D116/D104*100-100 -> 12.845006 | W116: =+E116/E104*100-100 -> -15.01327 | X116: =+F116/F104*100-100 -> 26.473335 | Y116: =+G116/G104*100-100 -> 11.933562 | Z116: =+H116/H104*100-100 -> -11.959189 | AA116: =+I116/I104*100-100 -> -18.409765 | AB116: =+J116/J104*100-100 -> 50.349874 | AC116: =+K116/K104*100-100 -> 43.457832 | ... AK116: =+S116/S104*100-100 -> -13.590756 | AN116: =+(1+V116/100)/(1+$B116/100)*100-100 -> 6.9722305 | AO116: =+(1+W116/100)/(1+$B116/100)*100-100 -> -19.436222 | AP116: =+(1+X116/100)/(1+$B116/100)*100-100 -> 19.891303 | AQ116: =+(1+Y116/100)/(1+$B116/100)*100-100 -> 6.1082203 | AR116: =+(1+Z116/100)/(1+$B116/100)*100-100 -> -16.541084 | AS116: =+(1+AA116/100)/(1+$B116/100)*100-100 -> -22.655954 | AT116: =+(1+AB116/100)/(1+$B116/100)*100-100 -> 42.525238 | AU116: =+(1+AC116/100)/(1+$B116/100)*100-100 -> 35.991878 | ... BC116: =+(1+AK116/100)/(1+$B116/100)*100-100 -> -18.087739 | BF116: =+(E116/D116)*100 -> 2.7013114 | BG116: =+(G116/F116)*100 -> 5.619375 | BH116: =+(I116/H116)*100 -> 22.394573 | BI116: =+(K116/J116)*100 -> 6.517425 | BJ116: =+(M116/L116)*100 -> 19.533759 | BK116: =+(O116/N116)*100 -> 6.5979173 | BL116: =+(Q116/P116)*100 -> 6.4563438 | BM116: =+(S116/R116)*100 -> 6.4557111 | BN116: =+(D116/$N116)*100 -> 63.717414 | BO116: =+(E116/$O116)*100 -> 26.087108 | BP116: =+(F116/$N116)*100 -> 18.369922 | BQ116: =+(G116/$O116)*100 -> 15.645465 | BR116: =+(H116/$N116)*100 -> 16.860662 | BS116: =+(I116/$O116)*100 -> 57.22826 | BT116: =+(J116/$N116)*100 -> 1.0520015 | BU116: =+(K116/$O116)*100 -> 1.0391674 | BV116: ND | BW116: ND | BX116: =+(N116/$N116)*100 -> 100 | BY116: =+(O116/$O116)*100 -> 100 | BZ116: ND | CA116: ND
A117: 38108 | B117: =+'[1]Senda Inflación Total'!F601 -> 5.37 | C117: =+'[1]Senda Inflación Total'!D601 -> 55.17 | D117: ='[2]May-04'!$D$836/1000 -> 37102.868 | E117: ='[2]May-04'!$D$837/1000 -> 945.14165 | F117: ='[2]May-04'!$D$848/1000 -> 10658.408 | G117: ='[2]May-04'!$D$849/1000 -> 593.27101 | H117: ='[2]May-04'!$D$862/1000 -> 9444.6324 | I117: ='[2]May-04'!$D$863/1000 -> 2011.5713 | J117: ='[2]May-04'!$D$874/1000 -> 600.89481 | K117: ='[2]May-04'!$D$875/1000 -> 39.73633 | L117: =+H117+(Titularizaciones!C29/1000) -> 10917.332 | M117: =+I117+((Titularizaciones!C29/1000)*Titularizaciones!M29) -> 2031.6395 | N117: =+D117+F117+H117+J117 -> 57806.803 | O117: =+E117+G117+I117+K117 -> 3589.7203 | P117: =+L117+J117+F117+D117 -> 59279.503 | Q117: =+M117+K117+G117+E117 -> 3609.7884 | R117: =+D117+F117+L117 -> 58678.608 | S117: =+E117+G117+M117 -> 3570.0521 | V117: =+D117/D105*100-100 -> 14.564324 | W117: =+E117/E105*100-100 -> -20.432315 | X117: =+F117/F105*100-100 -> 26.594247 | Y117: =+G117/G105*100-100 -> 14.531435 | Z117: =+H117/H105*100-100 -> -13.298306 | AA117: =+I117/I105*100-100 -> -23.255408 | AB117: =+J117/J105*100-100 -> 45.224449 | AC117: =+K117/K105*100-100 -> 49.243087 | ... AK117: =+S117/S105*100-100 -> -17.634964 | AN117: =+(1+V117/100)/(1+$B117/100)*100-100 -> 8.7257511 | AO117: =+(1+W117/100)/(1+$B117/100)*100-100 -> -24.487345 | AP117: =+(1+X117/100)/(1+$B117/100)*100-100 -> 20.14259 | AQ117: =+(1+Y117/100)/(1+$B117/100)*100-100 -> 8.6945379 | AR117: =+(1+Z117/100)/(1+$B117/100)*100-100 -> -17.716908 | AS117: =+(1+AA117/100)/(1+$B117/100)*100-100 -> -27.166563 | AT117: =+(1+AB117/100)/(1+$B117/100)*100-100 -> 37.823336 | AU117: =+(1+AC117/100)/(1+$B117/100)*100-100 -> 41.637171 | ... BC117: =+(1+AK117/100)/(1+$B117/100)*100-100 -> -21.832555 | BF117: =+(E117/D117)*100 -> 2.5473547 | BG117: =+(G117/F117)*100 -> 5.5662255 | BH117: =+(I117/H117)*100 -> 21.298566 | BI117: =+(K117/J117)*100 -> 6.6128596 | BJ117: =+(M117/L117)*100 -> 18.609304 | BK117: =+(O117/N117)*100 -> 6.2098578 | BL117: =+(Q117/P117)*100 -> 6.0894378 | BM117: =+(S117/R117)*100 -> 6.0840777 | BN117: =+(D117/$N117)*100 -> 64.184259 | BO117: =+(E117/$O117)*100 -> 26.329117 | BP117: =+(F117/$N117)*100 -> 18.437982 | BQ117: =+(G117/$O117)*100 -> 16.526943 | BR117: =+(H117/$N117)*100 -> 16.338271 | BS117: =+(I117/$O117)*100 -> 56.036993 | BT117: =+(J117/$N117)*100 -> 1.039488 | BU117: =+(K117/$O117)*100 -> 1.1069478 | BV117: ND | BW117: ND | BX117: =+(N117/$N117)*100 -> 100 | BY117: =+(O117/$O117)*100 -> 100 | BZ117: ND | CA117: ND
A118: 38139 | B118: =+'[1]Senda Inflación Total'!F602 -> 6.07 | C118: =+'[1]Senda Inflación Total'!D602 -> 55.51 | D118: ='[2]Jun-04'!$D$836/1000 -> 38107.653 | E118: ='[2]Jun-04'!$D$837/1000 -> 930.83702 | F118: ='[2]Jun-04'!$D$848/1000 -> 10844.951 | G118: ='[2]Jun-04'!$D$849/1000 -> 575.6627 | H118: ='[2]Jun-04'!$D$862/1000 -> 9008.293 | I118: ='[2]Jun-04'!$D$863/1000 -> 1574.6197 | J118: ='[2]Jun-04'!$D$874/1000 -> 617.16078 | K118: ='[2]Jun-04'!$D$875/1000 -> 40.34552 | L118: =+H118+(Titularizaciones!C30/1000) -> 10980.704 | M118: =+I118+((Titularizaciones!C30/1000)*Titularizaciones!M30) -> 2113.9898 | N118: =+D118+F118+H118+J118 -> 58578.058 | O118: =+E118+G118+I118+K118 -> 3121.4649 | P118: =+L118+J118+F118+D118 -> 60550.47 | Q118: =+M118+K118+G118+E118 -> 3660.835 | R118: =+D118+F118+L118 -> 59933.309 | S118: =+E118+G118+M118 -> 3620.4895 | V118: =+D118/D106*100-100 -> 18.464231 | W118: =+E118/E106*100-100 -> -13.694056 | X118: =+F118/F106*100-100 -> 26.414812 | Y118: =+G118/G106*100-100 -> 10.072078 | Z118: =+H118/H106*100-100 -> -13.217362 | AA118: =+I118/I106*100-100 -> -38.274312 | AB118: =+J118/J106*100-100 -> 43.83998 | AC118: =+K118/K106*100-100 -> 45.820944 | ... AK118: =+S118/S106*100-100 -> -12.997492 | AN118: =+(1+V118/100)/(1+$B118/100)*100-100 -> 11.684955 | AO118: =+(1+W118/100)/(1+$B118/100)*100-100 -> -18.633031 | AP118: =+(1+X118/100)/(1+$B118/100)*100-100 -> 19.180552 | AQ118: =+(1+Y118/100)/(1+$B118/100)*100-100 -> 3.7730532 | AR118: =+(1+Z118/100)/(1+$B118/100)*100-100 -> -18.183617 | AS118: =+(1+AA118/100)/(1+$B118/100)*100-100 -> -41.806648 | AT118: =+(1+AB118/100)/(1+$B118/100)*100-100 -> 35.608541 | AU118: =+(1+AC118/100)/(1+$B118/100)*100-100 -> 37.476142 | ... BC118: =+(1+AK118/100)/(1+$B118/100)*100-100 -> -17.976329 | BF118: =+(E118/D118)*100 -> 2.4426511 | BG118: =+(G118/F118)*100 -> 5.3081172 | BH118: =+(I118/H118)*100 -> 17.479667 | BI118: =+(K118/J118)*100 -> 6.5372787 | BJ118: =+(M118/L118)*100 -> 19.251859 | BK118: =+(O118/N118)*100 -> 5.3287272 | BL118: =+(Q118/P118)*100 -> 6.0459234 | BM118: =+(S118/R118)*100 -> 6.0408637 | BN118: =+(D118/$N118)*100 -> 65.054484 | BO118: =+(E118/$O118)*100 -> 29.820519 | BP118: =+(F118/$N118)*100 -> 18.513674 | BQ118: =+(G118/$O118)*100 -> 18.442069 | BR118: =+(H118/$N118)*100 -> 15.378272 | BS118: =+(I118/$O118)*100 -> 50.444894 | BT118: =+(J118/$N118)*100 -> 1.0535699 | BU118: =+(K118/$O118)*100 -> 1.2925188 | BV118: ND | BW118: ND | BX118: =+(N118/$N118)*100 -> 100 | BY118: =+(O118/$O118)*100 -> 100 | BZ118: ND | CA118: ND
A119: 38169 | B119: =+'[1]Senda Inflación Total'!F603 -> 6.19 | C119: =+'[1]Senda Inflación Total'!D603 -> 55.49 | D119: ='[2]Jul-04'!$D$836/1000 -> 38837.152 | E119: ='[2]Jul-04'!$D$837/1000 -> 987.20886 | F119: ='[2]Jul-04'!$D$848/1000 -> 11093.632 | G119: ='[2]Jul-04'!$D$849/1000 -> 595.02619 | H119: ='[2]Jul-04'!$D$862/1000 -> 8985.8155 | I119: ='[2]Jul-04'!$D$863/1000 -> 1555.3128 | J119: ='[2]Jul-04'!$D$874/1000 -> 637.85882 | K119: ='[2]Jul-04'!$D$875/1000 -> 42.37575 | L119: =+H119+(Titularizaciones!C31/1000) -> 10932.065 | M119: =+I119+((Titularizaciones!C31/1000)*Titularizaciones!M31) -> 2086.1533 | N119: =+D119+F119+H119+J119 -> 59554.458 | O119: =+E119+G119+I119+K119 -> 3179.9236 | P119: =+L119+J119+F119+D119 -> 61500.707 | Q119: =+M119+K119+G119+E119 -> 3710.7641 | R119: =+D119+F119+L119 -> 60862.849 | S119: =+E119+G119+M119 -> 3668.3884 | V119: =+D119/D107*100-100 -> 19.819179 | W119: =+E119/E107*100-100 -> -5.9810165 | X119: =+F119/F107*100-100 -> 27.123594 | Y119: =+G119/G107*100-100 -> 22.390246 | Z119: =+H119/H107*100-100 -> -12.842478 | AA119: =+I119/I107*100-100 -> -38.351639 | AB119: =+J119/J107*100-100 -> 38.348567 | AC119: =+K119/K107*100-100 -> 53.913753 | ... AK119: =+S119/S107*100-100 -> -9.8302155 | AN119: =+(1+V119/100)/(1+$B119/100)*100-100 -> 12.83471 | AO119: =+(1+W119/100)/(1+$B119/100)*100-100 -> -11.461547 | AP119: =+(1+X119/100)/(1+$B119/100)*100-100 -> 19.713339 | AQ119: =+(1+Y119/100)/(1+$B119/100)*100-100 -> 15.255906 | AR119: =+(1+Z119/100)/(1+$B119/100)*100-100 -> -17.923042 | AS119: =+(1+AA119/100)/(1+$B119/100)*100-100 -> -41.945229 | AT119: =+(1+AB119/100)/(1+$B119/100)*100-100 -> 30.283988 | AU119: =+(1+AC119/100)/(1+$B119/100)*100-100 -> 44.941852 | ... BC119: =+(1+AK119/100)/(1+$B119/100)*100-100 -> -15.086369 | BF119: =+(E119/D119)*100 -> 2.5419188 | BG119: =+(G119/F119)*100 -> 5.3636735 | BH119: =+(I119/H119)*100 -> 17.308532 | BI119: =+(K119/J119)*100 -> 6.6434372 | BJ119: =+(M119/L119)*100 -> 19.082884 | BK119: =+(O119/N119)*100 -> 5.3395223 | BL119: =+(Q119/P119)*100 -> 6.0336934 | BM119: =+(S119/R119)*100 -> 6.0273032 | BN119: =+(D119/$N119)*100 -> 65.212837 | BO119: =+(E119/$O119)*100 -> 31.04505 | BP119: =+(F119/$N119)*100 -> 18.62771 | BQ119: =+(G119/$O119)*100 -> 18.711965 | BR119: =+(H119/$N119)*100 -> 15.088401 | BS119: =+(I119/$O119)*100 -> 48.910382 | BT119: =+(J119/$N119)*100 -> 1.0710513 | BU119: =+(K119/$O119)*100 -> 1.3326028 | BV119: ND | BW119: ND | BX119: =+(N119/$N119)*100 -> 100 | BY119: =+(O119/$O119)*100 -> 100 | BZ119: ND | CA119: ND
A120: 38200 | B120: =+'[1]Senda Inflación Total'!F604 -> 5.89 | C120: =+'[1]Senda Inflación Total'!D604 -> 55.51 | D120: ='[2]Ago-04'!$D$836/1000 -> 39335.914 | E120: ='[2]Ago-04'!$D$837/1000 -> 975.56513 | F120: ='[2]Ago-04'!$D$848/1000 -> 11337.762 | G120: ='[2]Ago-04'!$D$849/1000 -> 580.54845 | H120: ='[2]Ago-04'!$D$862/1000 -> 8753.4171 | I120: ='[2]Ago-04'!$D$863/1000 -> 1330.7871 | J120: ='[2]Ago-04'!$D$874/1000 -> 663.55707 | K120: ='[2]Ago-04'!$D$875/1000 -> 40.4413 | L120: =+H120+(Titularizaciones!C32/1000) -> 11184.637 | M120: =+I120+((Titularizaciones!C32/1000)*Titularizaciones!M32) -> 2360.606 | N120: =+D120+F120+H120+J120 -> 60090.65 | O120: =+E120+G120+I120+K120 -> 2927.3419 | P120: =+L120+J120+F120+D120 -> 62521.871 | Q120: =+M120+K120+G120+E120 -> 3957.1609 | R120: =+D120+F120+L120 -> 61858.314 | S120: =+E120+G120+M120 -> 3916.7196 | V120: =+D120/D108*100-100 -> 21.357945 | W120: =+E120/E108*100-100 -> -7.4285108 | X120: =+F120/F108*100-100 -> 27.292325 | Y120: =+G120/G108*100-100 -> 11.781656 | Z120: =+H120/H108*100-100 -> -15.105292 | AA120: =+I120/I108*100-100 -> -47.382018 | AB120: =+J120/J108*100-100 -> 38.397266 | AC120: =+K120/K108*100-100 -> 44.842031 | ... AK120: =+S120/S108*100-100 -> -4.7660138 | AN120: =+(1+V120/100)/(1+$B120/100)*100-100 -> 14.60756 | AO120: =+(1+W120/100)/(1+$B120/100)*100-100 -> -12.577685 | AP120: =+(1+X120/100)/(1+$B120/100)*100-100 -> 20.211847 | AQ120: =+(1+Y120/100)/(1+$B120/100)*100-100 -> 5.5639402 | AR120: =+(1+Z120/100)/(1+$B120/100)*100-100 -> -19.827455 | AS120: =+(1+AA120/100)/(1+$B120/100)*100-100 -> -50.308828 | AT120: =+(1+AB120/100)/(1+$B120/100)*100-100 -> 30.69909 | AU120: =+(1+AC120/100)/(1+$B120/100)*100-100 -> 36.785372 | ... BC120: =+(1+AK120/100)/(1+$B120/100)*100-100 -> -10.063286 | BF120: =+(E120/D120)*100 -> 2.4800876 | BG120: =+(G120/F120)*100 -> 5.1204855 | BH120: =+(I120/H120)*100 -> 15.203058 | BI120: =+(K120/J120)*100 -> 6.0946227 | BJ120: =+(M120/L120)*100 -> 21.105789 | BK120: =+(O120/N120)*100 -> 4.8715431 | BL120: =+(Q120/P120)*100 -> 6.3292426 | BM120: =+(S120/R120)*100 -> 6.3317594 | BN120: =+(D120/$N120)*100 -> 65.460956 | BO120: =+(E120/$O120)*100 -> 33.325971 | BP120: =+(F120/$N120)*100 -> 18.867764 | BQ120: =+(G120/$O120)*100 -> 19.831931 | BR120: =+(H120/$N120)*100 -> 14.56702 | BS120: =+(I120/$O120)*100 -> 45.460595 | BT120: =+(J120/$N120)*100 -> 1.1042601 | BU120: =+(K120/$O120)*100 -> 1.3815024 | BV120: ND | BW120: ND | BX120: =+(N120/$N120)*100 -> 100 | BY120: =+(O120/$O120)*100 -> 100 | BZ120: ND | CA120: ND
A121: 38231 | B121: =+'[1]Senda Inflación Total'!F605 -> 5.97 | C121: =+'[1]Senda Inflación Total'!D605 -> 55.67 | D121: ='[2]Sep-04'!$D$836/1000 -> 40038.325 | E121: ='[2]Sep-04'!$D$837/1000 -> 922.5063 | F121: ='[2]Sep-04'!$D$848/1000 -> 11656.893 | G121: ='[2]Sep-04'!$D$849/1000 -> 607.48553 | H121: ='[2]Sep-04'!$D$862/1000 -> 8501.0597 | I121: ='[2]Sep-04'!$D$863/1000 -> 1088.6313 | J121: ='[2]Sep-04'!$D$874/1000 -> 697.92161 | K121: ='[2]Sep-04'!$D$875/1000 -> 41.13537 | L121: =+H121+(Titularizaciones!C33/1000) -> 10869.595 | M121: =+I121+((Titularizaciones!C33/1000)*Titularizaciones!M33) -> 2087.2889 | N121: =+D121+F121+H121+J121 -> 60894.2 | O121: =+E121+G121+I121+K121 -> 2659.7585 | P121: =+L121+J121+F121+D121 -> 63262.735 | Q121: =+M121+K121+G121+E121 -> 3658.4161 | R121: =+D121+F121+L121 -> 62564.814 | S121: =+E121+G121+M121 -> 3617.2807 | V121: =+D121/D109*100-100 -> 22.693305 | W121: =+E121/E109*100-100 -> -7.7102077 | X121: =+F121/F109*100-100 -> 29.03637 | Y121: =+G121/G109*100-100 -> 16.445509 | Z121: =+H121/H109*100-100 -> -16.99481 | AA121: =+I121/I109*100-100 -> -56.424337 | AB121: =+J121/J109*100-100 -> 36.247974 | AC121: =+K121/K109*100-100 -> 51.709916 | ... AK121: =+S121/S109*100-100 -> -10.26974 | AN121: =+(1+V121/100)/(1+$B121/100)*100-100 -> 15.781169 | AO121: =+(1+W121/100)/(1+$B121/100)*100-100 -> -12.90951 | AP121: =+(1+X121/100)/(1+$B121/100)*100-100 -> 21.766887 | AQ121: =+(1+Y121/100)/(1+$B121/100)*100-100 -> 9.8853533 | AR121: =+(1+Z121/100)/(1+$B121/100)*100-100 -> -21.671048 | AS121: =+(1+AA121/100)/(1+$B121/100)*100-100 -> -58.879246 | AT121: =+(1+AB121/100)/(1+$B121/100)*100-100 -> 28.572213 | AU121: =+(1+AC121/100)/(1+$B121/100)*100-100 -> 43.16308 | ... BC121: =+(1+AK121/100)/(1+$B121/100)*100-100 -> -15.324847 | BF121: =+(E121/D121)*100 -> 2.3040582 | BG121: =+(G121/F121)*100 -> 5.2113845 | BH121: =+(I121/H121)*100 -> 12.805831 | BI121: =+(K121/J121)*100 -> 5.8939814 | BJ121: =+(M121/L121)*100 -> 19.203005 | BK121: =+(O121/N121)*100 -> 4.3678356 | BL121: =+(Q121/P121)*100 -> 5.7828926 | BM121: =+(S121/R121)*100 -> 5.7816534 | BN121: =+(D121/$N121)*100 -> 65.750639 | BO121: =+(E121/$O121)*100 -> 34.683837 | BP121: =+(F121/$N121)*100 -> 19.142863 | BQ121: =+(G121/$O121)*100 -> 22.839875 | BR121: =+(H121/$N121)*100 -> 13.960377 | BS121: =+(I121/$O121)*100 -> 40.929705 | BT121: =+(J121/$N121)*100 -> 1.1461217 | BU121: =+(K121/$O121)*100 -> 1.5465829 | BV121: ND | BW121: ND | BX121: =+(N121/$N121)*100 -> 100 | BY121: =+(O121/$O121)*100 -> 100 | BZ121: ND | CA121: ND
A122: 38261 | B122: =+'[1]Senda Inflación Total'!F606 -> 5.9 | C122: =+'[1]Senda Inflación Total'!D606 -> 55.66 | D122: ='[2]Oct-04'!$D$836/1000 -> 40444.385 | E122: ='[2]Oct-04'!$D$837/1000 -> 917.18484 | F122: ='[2]Oct-04'!$D$848/1000 -> 11953.779 | G122: ='[2]Oct-04'!$D$849/1000 -> 612.93899 | H122: ='[2]Oct-04'!$D$862/1000 -> 8455.2122 | I122: ='[2]Oct-04'!$D$863/1000 -> 1082.7277 | J122: ='[2]Oct-04'!$D$874/1000 -> 733.98199 | K122: ='[2]Oct-04'!$D$875/1000 -> 43.20914 | L122: =+H122+(Titularizaciones!C34/1000) -> 10774.569 | M122: =+I122+((Titularizaciones!C34/1000)*Titularizaciones!M34) -> 2054.5334 | N122: =+D122+F122+H122+J122 -> 61587.359 | O122: =+E122+G122+I122+K122 -> 2656.0607 | P122: =+L122+J122+F122+D122 -> 63906.715 | Q122: =+M122+K122+G122+E122 -> 3627.8663 | R122: =+D122+F122+L122 -> 63172.734 | S122: =+E122+G122+M122 -> 3584.6572 | V122: =+D122/D110*100-100 -> 21.72711 | W122: =+E122/E110*100-100 -> -5.8142854 | X122: =+F122/F110*100-100 -> 29.583005 | Y122: =+G122/G110*100-100 -> 17.825168 | Z122: =+H122/H110*100-100 -> -17.201185 | AA122: =+I122/I110*100-100 -> -56.302737 | AB122: =+J122/J110*100-100 -> 37.230889 | AC122: =+K122/K110*100-100 -> 53.135332 | ... AK122: =+S122/S110*100-100 -> -10.053982 | AN122: =+(1+V122/100)/(1+$B122/100)*100-100 -> 14.945335 | AO122: =+(1+W122/100)/(1+$B122/100)*100-100 -> -11.061648 | AP122: =+(1+X122/100)/(1+$B122/100)*100-100 -> 22.363555 | AQ122: =+(1+Y122/100)/(1+$B122/100)*100-100 -> 11.260782 | AR122: =+(1+Z122/100)/(1+$B122/100)*100-100 -> -21.81415 | AS122: =+(1+AA122/100)/(1+$B122/100)*100-100 -> -58.73724 | AT122: =+(1+AB122/100)/(1+$B122/100)*100-100 -> 29.585353 | AU122: =+(1+AC122/100)/(1+$B122/100)*100-100 -> 44.603713 | ... BC122: =+(1+AK122/100)/(1+$B122/100)*100-100 -> -15.065139 | BF122: =+(E122/D122)*100 -> 2.267768 | BG122: =+(G122/F122)*100 -> 5.1275751 | BH122: =+(I122/H122)*100 -> 12.805447 | BI122: =+(K122/J122)*100 -> 5.8869483 | BJ122: =+(M122/L122)*100 -> 19.068358 | BK122: =+(O122/N122)*100 -> 4.3126718 | BL122: =+(Q122/P122)*100 -> 5.6768155 | BM122: =+(S122/R122)*100 -> 5.6743741 | BN122: =+(D122/$N122)*100 -> 65.669947 | BO122: =+(E122/$O122)*100 -> 34.531773 | BP122: =+(F122/$N122)*100 -> 19.409468 | BQ122: =+(G122/$O122)*100 -> 23.076995 | BR122: =+(H122/$N122)*100 -> 13.728811 | BS122: =+(I122/$O122)*100 -> 40.764419 | BT122: =+(J122/$N122)*100 -> 1.1917738 | BU122: =+(K122/$O122)*100 -> 1.626813 | BV122: ND | BW122: ND | BX122: =+(N122/$N122)*100 -> 100 | BY122: =+(O122/$O122)*100 -> 100 | BZ122: ND | CA122: ND
A123: 38292 | B123: =+'[1]Senda Inflación Total'!F607 -> 5.82 | C123: =+'[1]Senda Inflación Total'!D607 -> 55.82 | D123: ='[2]Nov-04'!$D$836/1000 -> 41419.353 | E123: ='[2]Nov-04'!$D$837/1000 -> 886.27696 | F123: ='[2]Nov-04'!$D$848/1000 -> 12297.905 | G123: ='[2]Nov-04'!$D$849/1000 -> 615.30942 | H123: ='[2]Nov-04'!$D$862/1000 -> 7981.1215 | I123: ='[2]Nov-04'!$D$863/1000 -> 957.19743 | J123: ='[2]Nov-04'!$D$874/1000 -> 815.63598 | K123: ='[2]Nov-04'!$D$875/1000 -> 48.26043 | L123: =+H123+(Titularizaciones!C35/1000) -> 10596.859 | M123: =+I123+((Titularizaciones!C35/1000)*Titularizaciones!M35) -> 1905.5672 | N123: =+D123+F123+H123+J123 -> 62514.016 | O123: =+E123+G123+I123+K123 -> 2507.0442 | P123: =+L123+J123+F123+D123 -> 65129.754 | Q123: =+M123+K123+G123+E123 -> 3455.414 | R123: =+D123+F123+L123 -> 64314.118 | S123: =+E123+G123+M123 -> 3407.1536 | V123: =+D123/D111*100-100 -> 23.894572 | W123: =+E123/E111*100-100 -> -1.172807 | X123: =+F123/F111*100-100 -> 30.350613 | Y123: =+G123/G111*100-100 -> 11.96654 | Z123: =+H123/H111*100-100 -> -18.802773 | AA123: =+I123/I111*100-100 -> -60.811487 | AB123: =+J123/J111*100-100 -> 46.418847 | AC123: =+K123/K111*100-100 -> 71.037354 | ... AK123: =+S123/S111*100-100 -> -12.741779 | AN123: =+(1+V123/100)/(1+$B123/100)*100-100 -> 17.080488 | AO123: =+(1+W123/100)/(1+$B123/100)*100-100 -> -6.6082092 | AP123: =+(1+X123/100)/(1+$B123/100)*100-100 -> 23.181452 | AQ123: =+(1+Y123/100)/(1+$B123/100)*100-100 -> 5.8084857 | AR123: =+(1+Z123/100)/(1+$B123/100)*100-100 -> -23.268544 | AS123: =+(1+AA123/100)/(1+$B123/100)*100-100 -> -62.966818 | AT123: =+(1+AB123/100)/(1+$B123/100)*100-100 -> 38.365948 | AU123: =+(1+AC123/100)/(1+$B123/100)*100-100 -> 61.630461 | ... BC123: =+(1+AK123/100)/(1+$B123/100)*100-100 -> -17.540899 | BF123: =+(E123/D123)*100 -> 2.1397653 | BG123: =+(G123/F123)*100 -> 5.0033677 | BH123: =+(I123/H123)*100 -> 11.99327 | BI123: =+(K123/J123)*100 -> 5.9169079 | BJ123: =+(M123/L123)*100 -> 17.982378 | BK123: =+(O123/N123)*100 -> 4.0103714 | BL123: =+(Q123/P123)*100 -> 5.3054308 | BM123: =+(S123/R123)*100 -> 5.297676 | BN123: =+(D123/$N123)*100 -> 66.256107 | BO123: =+(E123/$O123)*100 -> 35.351469 | BP123: =+(F123/$N123)*100 -> 19.672237 | BQ123: =+(G123/$O123)*100 -> 24.543221 | BR123: =+(H123/$N123)*100 -> 12.766931 | BS123: =+(I123/$O123)*100 -> 38.180317 | BT123: =+(J123/$N123)*100 -> 1.304725 | BU123: =+(K123/$O123)*100 -> 1.9249932 | BV123: ND | BW123: ND | BX123: =+(N123/$N123)*100 -> 100 | BY123: =+(O123/$O123)*100 -> 100 | BZ123: ND | CA123: ND
A124: 38322 | B124: =+'[1]Senda Inflación Total'!F608 -> 5.5 | C124: =+'[1]Senda Inflación Total'!D608 -> 55.99 | D124: ='[2]Dic-04'!$D$836/1000 -> 42213.989 | E124: ='[2]Dic-04'!$D$837/1000 -> 783.71628 | F124: ='[2]Dic-04'!$D$848/1000 -> 12673.771 | G124: ='[2]Dic-04'!$D$849/1000 -> 532.12474 | H124: ='[2]Dic-04'!$D$862/1000 -> 7087.8837 | I124: ='[2]Dic-04'!$D$863/1000 -> 695.96217 | J124: ='[2]Dic-04'!$D$874/1000 -> 841.08078 | K124: ='[2]Dic-04'!$D$875/1000 -> 45.54752 | L124: =+H124+(Titularizaciones!C36/1000) -> 10222.539 | M124: =+I124+((Titularizaciones!C36/1000)*Titularizaciones!M36) -> 1621.226 | N124: =+D124+F124+H124+J124 -> 62816.724 | O124: =+E124+G124+I124+K124 -> 2057.3507 | P124: =+L124+J124+F124+D124 -> 65951.379 | Q124: =+M124+K124+G124+E124 -> 2982.6145 | R124: =+D124+F124+L124 -> 65110.298 | S124: =+E124+G124+M124 -> 2937.067 | V124: =+D124/D112*100-100 -> 26.458994 | W124: =+E124/E112*100-100 -> -4.3340231 | X124: =+F124/F112*100-100 -> 32.201259 | Y124: =+G124/G112*100-100 -> 9.2586049 | Z124: =+H124/H112*100-100 -> -26.36956 | AA124: =+I124/I112*100-100 -> -69.302509 | AB124: =+J124/J112*100-100 -> 48.070094 | AC124: =+K124/K112*100-100 -> 49.799872 | ... AK124: =+S124/S112*100-100 -> -18.1786 | AN124: =+(1+V124/100)/(1+$B124/100)*100-100 -> 19.866345 | AO124: =+(1+W124/100)/(1+$B124/100)*100-100 -> -9.3213489 | AP124: =+(1+X124/100)/(1+$B124/100)*100-100 -> 25.30925 | AQ124: =+(1+Y124/100)/(1+$B124/100)*100-100 -> 3.5626587 | AR124: =+(1+Z124/100)/(1+$B124/100)*100-100 -> -30.208114 | AS124: =+(1+AA124/100)/(1+$B124/100)*100-100 -> -70.902852 | AT124: =+(1+AB124/100)/(1+$B124/100)*100-100 -> 40.3508 | AU124: =+(1+AC124/100)/(1+$B124/100)*100-100 -> 41.9904 | ... BC124: =+(1+AK124/100)/(1+$B124/100)*100-100 -> -22.444171 | BF124: =+(E124/D124)*100 -> 1.8565322 | BG124: =+(G124/F124)*100 -> 4.19863 | BH124: =+(I124/H124)*100 -> 9.8190405 | BI124: =+(K124/J124)*100 -> 5.4153562 | BJ124: =+(M124/L124)*100 -> 15.859328 | BK124: =+(O124/N124)*100 -> 3.275164 | BL124: =+(Q124/P124)*100 -> 4.5224445 | BM124: =+(S124/R124)*100 -> 4.51091 | BN124: =+(D124/$N124)*100 -> 67.201831 | BO124: =+(E124/$O124)*100 -> 38.09347 | BP124: =+(F124/$N124)*100 -> 20.175791 | BQ124: =+(G124/$O124)*100 -> 25.864562 | BR124: =+(H124/$N124)*100 -> 11.283434 | BS124: =+(I124/$O124)*100 -> 33.828076 | BT124: =+(J124/$N124)*100 -> 1.338944 | BU124: =+(K124/$O124)*100 -> 2.2138919 | BV124: ND | BW124: ND | BX124: =+(N124/$N124)*100 -> 100 | BY124: =+(O124/$O124)*100 -> 100 | BZ124: ND | CA124: ND
A125: 38353 | B125: =+'[1]Senda Inflación Total'!F609 -> 5.43 | C125: =+'[1]Senda Inflación Total'!D609 -> 56.45 | D125: ='[2]Ene-05'!$D$836/1000 -> 42157.116 | E125: ='[2]Ene-05'!$D$837/1000 -> 858.46766 | F125: ='[2]Ene-05'!$D$848/1000 -> 12895.68 | G125: ='[2]Ene-05'!$D$849/1000 -> 573.69824 | H125: ='[2]Ene-05'!$D$862/1000 -> 7139.6114 | I125: ='[2]Ene-05'!$D$863/1000 -> 717.47592 | J125: ='[2]Ene-05'!$D$874/1000 -> 873.03009 | K125: ='[2]Ene-05'!$D$875/1000 -> 51.20149 | L125: =+H125+(Titularizaciones!C37/1000) -> 10227.716 | M125: =+I125+((Titularizaciones!C37/1000)*Titularizaciones!M37) -> 1632.108 | N125: =+D125+F125+H125+J125 -> 63065.437 | O125: =+E125+G125+I125+K125 -> 2200.8433 | P125: =+L125+J125+F125+D125 -> 66153.541 | Q125: =+M125+K125+G125+E125 -> 3115.4754 | R125: =+D125+F125+L125 -> 65280.511 | S125: =+E125+G125+M125 -> 3064.2739 | V125: =+D125/D113*100-100 -> 17.84253 | W125: =+E125/E113*100-100 -> -14.748293 | X125: =+F125/F113*100-100 -> 30.164805 | Y125: =+G125/G113*100-100 -> 9.3322186 | Z125: =+H125/H113*100-100 -> -25.679223 | AA125: =+I125/I113*100-100 -> -68.386584 | AB125: =+J125/J113*100-100 -> 50.797278 | AC125: =+K125/K113*100-100 -> 57.564378 | ... AK125: =+S125/S113*100-100 -> -19.768332 | AN125: =+(1+V125/100)/(1+$B125/100)*100-100 -> 11.773243 | AO125: =+(1+W125/100)/(1+$B125/100)*100-100 -> -19.139043 | AP125: =+(1+X125/100)/(1+$B125/100)*100-100 -> 23.46088 | AQ125: =+(1+Y125/100)/(1+$B125/100)*100-100 -> 3.7012412 | AR125: =+(1+Z125/100)/(1+$B125/100)*100-100 -> -29.506993 | AS125: =+(1+AA125/100)/(1+$B125/100)*100-100 -> -70.014782 | AT125: =+(1+AB125/100)/(1+$B125/100)*100-100 -> 43.030711 | AU125: =+(1+AC125/100)/(1+$B125/100)*100-100 -> 49.449282 | ... BC125: =+(1+AK125/100)/(1+$B125/100)*100-100 -> -23.900533 | BF125: =+(E125/D125)*100 -> 2.0363529 | BG125: =+(G125/F125)*100 -> 4.4487632 | BH125: =+(I125/H125)*100 -> 10.049229 | BI125: =+(K125/J125)*100 -> 5.8648024 | BJ125: =+(M125/L125)*100 -> 15.957698 | BK125: =+(O125/N125)*100 -> 3.4897773 | BL125: =+(Q125/P125)*100 -> 4.7094612 | BM125: =+(S125/R125)*100 -> 4.6940102 | BN125: =+(D125/$N125)*100 -> 66.846625 | BO125: =+(E125/$O125)*100 -> 39.006305 | BP125: =+(F125/$N125)*100 -> 20.448093 | BQ125: =+(G125/$O125)*100 -> 26.067201 | BR125: =+(H125/$N125)*100 -> 11.320958 | BS125: =+(I125/$O125)*100 -> 32.600045 | BT125: =+(J125/$N125)*100 -> 1.3843242 | BU125: =+(K125/$O125)*100 -> 2.3264487 | BV125: ND | BW125: ND | BX125: =+(N125/$N125)*100 -> 100 | BY125: =+(O125/$O125)*100 -> 100 | BZ125: ND | CA125: ND
A126: 38384 | B126: =+'[1]Senda Inflación Total'!F610 -> 5.25 | C126: =+'[1]Senda Inflación Total'!D610 -> 57.02 | D126: ='[2]Feb-05'!$D$836/1000 -> 42460.377 | E126: ='[2]Feb-05'!$D$837/1000 -> 835.13521 | F126: ='[2]Feb-05'!$D$848/1000 -> 13144.841 | G126: ='[2]Feb-05'!$D$849/1000 -> 632.38718 | H126: ='[2]Feb-05'!$D$862/1000 -> 7161.43 | I126: ='[2]Feb-05'!$D$863/1000 -> 707.96603 | J126: ='[2]Feb-05'!$D$874/1000 -> 914.54786 | K126: ='[2]Feb-05'!$D$875/1000 -> 53.13966 | L126: =+H126+(Titularizaciones!C38/1000) -> 10200.751 | M126: =+I126+((Titularizaciones!C38/1000)*Titularizaciones!M38) -> 1607.7364 | N126: =+D126+F126+H126+J126 -> 63681.196 | O126: =+E126+G126+I126+K126 -> 2228.6281 | P126: =+L126+J126+F126+D126 -> 66720.517 | Q126: =+M126+K126+G126+E126 -> 3128.3985 | R126: =+D126+F126+L126 -> 65805.969 | S126: =+E126+G126+M126 -> 3075.2588 | V126: =+D126/D114*100-100 -> 16.996782 | W126: =+E126/E114*100-100 -> -15.480833 | X126: =+F126/F114*100-100 -> 31.432688 | Y126: =+G126/G114*100-100 -> 14.729017 | Z126: =+H126/H114*100-100 -> -25.326788 | AA126: =+I126/I114*100-100 -> -68.173965 | AB126: =+J126/J114*100-100 -> 52.669592 | AC126: =+K126/K114*100-100 -> 58.857926 | ... AK126: =+S126/S114*100-100 -> -18.688626 | AN126: =+(1+V126/100)/(1+$B126/100)*100-100 -> 11.160838 | AO126: =+(1+W126/100)/(1+$B126/100)*100-100 -> -19.696753 | AP126: =+(1+X126/100)/(1+$B126/100)*100-100 -> 24.876663 | AQ126: =+(1+Y126/100)/(1+$B126/100)*100-100 -> 9.0061921 | AR126: =+(1+Z126/100)/(1+$B126/100)*100-100 -> -29.05158 | AS126: =+(1+AA126/100)/(1+$B126/100)*100-100 -> -69.761487 | AT126: =+(1+AB126/100)/(1+$B126/100)*100-100 -> 45.054244 | AU126: =+(1+AC126/100)/(1+$B126/100)*100-100 -> 50.933896 | ... BC126: =+(1+AK126/100)/(1+$B126/100)*100-100 -> -22.744538 | BF126: =+(E126/D126)*100 -> 1.9668577 | BG126: =+(G126/F126)*100 -> 4.8109155 | BH126: =+(I126/H126)*100 -> 9.8858193 | BI126: =+(K126/J126)*100 -> 5.8104843 | BJ126: =+(M126/L126)*100 -> 15.760961 | BK126: =+(O126/N126)*100 -> 3.4996643 | BL126: =+(Q126/P126)*100 -> 4.6888103 | BM126: =+(S126/R126)*100 -> 4.6732217 | BN126: =+(D126/$N126)*100 -> 66.676476 | BO126: =+(E126/$O126)*100 -> 37.473063 | BP126: =+(F126/$N126)*100 -> 20.641636 | BQ126: =+(G126/$O126)*100 -> 28.375626 | BR126: =+(H126/$N126)*100 -> 11.245753 | BS126: =+(I126/$O126)*100 -> 31.766899 | BT126: =+(J126/$N126)*100 -> 1.4361349 | BU126: =+(K126/$O126)*100 -> 2.3844113 | BV126: ND | BW126: ND | BX126: =+(N126/$N126)*100 -> 100 | BY126: =+(O126/$O126)*100 -> 100 | BZ126: ND | CA126: ND
A127: 38412 | B127: =+'[1]Senda Inflación Total'!F611 -> 5.03 | C127: =+'[1]Senda Inflación Total'!D611 -> 57.46 | D127: ='[2]Mar-05'!$D$836/1000 -> 43411.47 | E127: ='[2]Mar-05'!$D$837/1000 -> 869.527 | F127: ='[2]Mar-05'!$D$848/1000 -> 13346.75 | G127: ='[2]Mar-05'!$D$849/1000 -> 664.26585 | H127: ='[2]Mar-05'!$D$862/1000 -> 7131.5132 | I127: ='[2]Mar-05'!$D$863/1000 -> 636.87837 | J127: ='[2]Mar-05'!$D$874/1000 -> 946.91729 | K127: ='[2]Mar-05'!$D$875/1000 -> 52.69685 | L127: =+H127+(Titularizaciones!C39/1000) -> 10129.608 | M127: =+I127+((Titularizaciones!C39/1000)*Titularizaciones!M39) -> 1523.7543 | N127: =+D127+F127+H127+J127 -> 64836.651 | O127: =+E127+G127+I127+K127 -> 2223.3681 | P127: =+L127+J127+F127+D127 -> 67834.745 | Q127: =+M127+K127+G127+E127 -> 3110.244 | R127: =+D127+F127+L127 -> 66887.828 | S127: =+E127+G127+M127 -> 3057.5471 | V127: =+D127/D115*100-100 -> 20.99895 | W127: =+E127/E115*100-100 -> -8.4870014 | X127: =+F127/F115*100-100 -> 31.16737 | Y127: =+G127/G115*100-100 -> 17.646272 | Z127: =+H127/H115*100-100 -> -25.636951 | AA127: =+I127/I115*100-100 -> -70.741417 | AB127: =+J127/J115*100-100 -> 56.818586 | AC127: =+K127/K115*100-100 -> 46.469404 | ... AK127: =+S127/S115*100-100 -> -17.562402 | AN127: =+(1+V127/100)/(1+$B127/100)*100-100 -> 15.204179 | AO127: =+(1+W127/100)/(1+$B127/100)*100-100 -> -12.869658 | AP127: =+(1+X127/100)/(1+$B127/100)*100-100 -> 24.885623 | AQ127: =+(1+Y127/100)/(1+$B127/100)*100-100 -> 12.012065 | AR127: =+(1+Z127/100)/(1+$B127/100)*100-100 -> -29.198278 | AS127: =+(1+AA127/100)/(1+$B127/100)*100-100 -> -72.142642 | AT127: =+(1+AB127/100)/(1+$B127/100)*100-100 -> 49.308375 | AU127: =+(1+AC127/100)/(1+$B127/100)*100-100 -> 39.454826 | ... BC127: =+(1+AK127/100)/(1+$B127/100)*100-100 -> -21.510428 | BF127: =+(E127/D127)*100 -> 2.0029891 | BG127: =+(G127/F127)*100 -> 4.9769858 | BH127: =+(I127/H127)*100 -> 8.9304801 | BI127: =+(K127/J127)*100 -> 5.5650953 | BJ127: =+(M127/L127)*100 -> 15.042579 | BK127: =+(O127/N127)*100 -> 3.429184 | BL127: =+(Q127/P127)*100 -> 4.5850308 | BM127: =+(S127/R127)*100 -> 4.5711562 | BN127: =+(D127/$N127)*100 -> 66.95514 | BO127: =+(E127/$O127)*100 -> 39.108549 | BP127: =+(F127/$N127)*100 -> 20.585194 | BQ127: =+(G127/$O127)*100 -> 29.876558 | BR127: =+(H127/$N127)*100 -> 10.999201 | BS127: =+(I127/$O127)*100 -> 28.644757 | BT127: =+(J127/$N127)*100 -> 1.4604661 | BU127: =+(K127/$O127)*100 -> 2.3701361 | BV127: ND | BW127: ND | BX127: =+(N127/$N127)*100 -> 100 | BY127: =+(O127/$O127)*100 -> 100 | BZ127: ND | CA127: ND
A128: 38443 | B128: =+'[1]Senda Inflación Total'!F612 -> 5.01 | C128: =+'[1]Senda Inflación Total'!D612 -> 57.72 | D128: ='[2]Abr-05'!$D$836/1000 -> 43821.76 | E128: ='[2]Abr-05'!$D$837/1000 -> 875.10815 | F128: ='[2]Abr-05'!$D$848/1000 -> 13782.677 | G128: ='[2]Abr-05'!$D$849/1000 -> 670.73017 | H128: ='[2]Abr-05'!$D$862/1000 -> 7171.9619 | I128: ='[2]Abr-05'!$D$863/1000 -> 626.71996 | J128: ='[2]Abr-05'!$D$874/1000 -> 982.30165 | K128: ='[2]Abr-05'!$D$875/1000 -> 52.98838 | L128: =+H128+(Titularizaciones!C40/1000) -> 10126.684 | M128: =+I128+((Titularizaciones!C40/1000)*Titularizaciones!M40) -> 1496.143 | N128: =+D128+F128+H128+J128 -> 65758.7 | O128: =+E128+G128+I128+K128 -> 2225.5467 | P128: =+L128+J128+F128+D128 -> 68713.422 | Q128: =+M128+K128+G128+E128 -> 3094.9697 | R128: =+D128+F128+L128 -> 67731.121 | S128: =+E128+G128+M128 -> 3041.9813 | V128: =+D128/D116*100-100 -> 20.790948 | W128: =+E128/E116*100-100 -> -10.704074 | X128: =+F128/F116*100-100 -> 31.773768 | Y128: =+G128/G116*100-100 -> 14.11828 | Z128: =+H128/H116*100-100 -> -25.292181 | AA128: =+I128/I116*100-100 -> -70.848639 | AB128: =+J128/J116*100-100 -> 63.995239 | AC128: =+K128/K116*100-100 -> 35.734725 | ... AK128: =+S128/S116*100-100 -> -18.50729 | AN128: =+(1+V128/100)/(1+$B128/100)*100-100 -> 15.028043 | AO128: =+(1+W128/100)/(1+$B128/100)*100-100 -> -14.964359 | AP128: =+(1+X128/100)/(1+$B128/100)*100-100 -> 25.486875 | AQ128: =+(1+Y128/100)/(1+$B128/100)*100-100 -> 8.6737267 | AR128: =+(1+Z128/100)/(1+$B128/100)*100-100 -> -28.856472 | AS128: =+(1+AA128/100)/(1+$B128/100)*100-100 -> -72.239443 | AT128: =+(1+AB128/100)/(1+$B128/100)*100-100 -> 56.171068 | AU128: =+(1+AC128/100)/(1+$B128/100)*100-100 -> 29.258857 | ... BC128: =+(1+AK128/100)/(1+$B128/100)*100-100 -> -22.395286 | BF128: =+(E128/D128)*100 -> 1.9969717 | BG128: =+(G128/F128)*100 -> 4.8664725 | BH128: =+(I128/H128)*100 -> 8.7384731 | BI128: =+(K128/J128)*100 -> 5.3943084 | BJ128: =+(M128/L128)*100 -> 14.774263 | BK128: =+(O128/N128)*100 -> 3.384414 | BL128: =+(Q128/P128)*100 -> 4.5041705 | BM128: =+(S128/R128)*100 -> 4.4912608 | BN128: =+(D128/$N128)*100 -> 66.640247 | BO128: =+(E128/$O128)*100 -> 39.321043 | BP128: =+(F128/$N128)*100 -> 20.959473 | BQ128: =+(G128/$O128)*100 -> 30.137772 | BR128: =+(H128/$N128)*100 -> 10.906484 | BS128: =+(I128/$O128)*100 -> 28.160271 | BT128: =+(J128/$N128)*100 -> 1.4937972 | BU128: =+(K128/$O128)*100 -> 2.3809153 | BV128: ND | BW128: ND | BX128: =+(N128/$N128)*100 -> 100 | BY128: =+(O128/$O128)*100 -> 100 | BZ128: ND | CA128: ND
A129: 38473 | B129: =+'[1]Senda Inflación Total'!F613 -> 5.04 | C129: =+'[1]Senda Inflación Total'!D613 -> 57.95 | D129: ='[2]May-05'!$D$836/1000 -> 44315.805 | E129: ='[2]May-05'!$D$837/1000 -> 901.37436 | F129: ='[2]May-05'!$D$848/1000 -> 14106.984 | G129: ='[2]May-05'!$D$849/1000 -> 689.30632 | H129: ='[2]May-05'!$D$862/1000 -> 7186.2924 | I129: ='[2]May-05'!$D$863/1000 -> 633.52371 | J129: ='[2]May-05'!$D$874/1000 -> 1019.4446 | K129: ='[2]May-05'!$D$875/1000 -> 54.4559 | L129: =+H129+(Titularizaciones!C41/1000) -> 10086.102 | M129: =+I129+((Titularizaciones!C41/1000)*Titularizaciones!M41) -> 1484.9885 | N129: =+D129+F129+H129+J129 -> 66628.526 | O129: =+E129+G129+I129+K129 -> 2278.6603 | P129: =+L129+J129+F129+D129 -> 69528.335 | Q129: =+M129+K129+G129+E129 -> 3130.1251 | R129: =+D129+F129+L129 -> 68508.891 | S129: =+E129+G129+M129 -> 3075.6692 | V129: =+D129/D117*100-100 -> 19.440376 | W129: =+E129/E117*100-100 -> -4.6307651 | X129: =+F129/F117*100-100 -> 32.35545 | Y129: =+G129/G117*100-100 -> 16.187427 | Z129: =+H129/H117*100-100 -> -23.91136 | AA129: =+I129/I117*100-100 -> -68.506027 | AB129: =+J129/J117*100-100 -> 69.654424 | AC129: =+K129/K117*100-100 -> 37.043104 | ... AK129: =+S129/S117*100-100 -> -13.848059 | AN129: =+(1+V129/100)/(1+$B129/100)*100-100 -> 13.709421 | AO129: =+(1+W129/100)/(1+$B129/100)*100-100 -> -9.2067452 | AP129: =+(1+X129/100)/(1+$B129/100)*100-100 -> 26.004808 | AQ129: =+(1+Y129/100)/(1+$B129/100)*100-100 -> 10.612554 | AR129: =+(1+Z129/100)/(1+$B129/100)*100-100 -> -27.562224 | AS129: =+(1+AA129/100)/(1+$B129/100)*100-100 -> -70.017162 | AT129: =+(1+AB129/100)/(1+$B129/100)*100-100 -> 61.514113 | AU129: =+(1+AC129/100)/(1+$B129/100)*100-100 -> 30.46754 | ... BC129: =+(1+AK129/100)/(1+$B129/100)*100-100 -> -17.981777 | BF129: =+(E129/D129)*100 -> 2.0339794 | BG129: =+(G129/F129)*100 -> 4.8862772 | BH129: =+(I129/H129)*100 -> 8.8157241 | BI129: =+(K129/J129)*100 -> 5.3417222 | BJ129: =+(M129/L129)*100 -> 14.723117 | BK129: =+(O129/N129)*100 -> 3.419947 | BL129: =+(Q129/P129)*100 -> 4.5019417 | BM129: =+(S129/R129)*100 -> 4.4894453 | BN129: =+(D129/$N129)*100 -> 66.51176 | BO129: =+(E129/$O129)*100 -> 39.557207 | BP129: =+(F129/$N129)*100 -> 21.172588 | BQ129: =+(G129/$O129)*100 -> 30.250508 | BR129: =+(H129/$N129)*100 -> 10.785609 | BS129: =+(I129/$O129)*100 -> 27.802464 | BT129: =+(J129/$N129)*100 -> 1.5300423 | BU129: =+(K129/$O129)*100 -> 2.3898209 | BV129: ND | BW129: ND | BX129: =+(N129/$N129)*100 -> 100 | BY129: =+(O129/$O129)*100 -> 100 | BZ129: ND | CA129: ND
A130: 38504 | B130: =+'[1]Senda Inflación Total'!F614 -> 4.83 | C130: =+'[1]Senda Inflación Total'!D614 -> 58.18 | D130: ='[2]Jun-05'!$D$836/1000 -> 45245.625 | E130: ='[2]Jun-05'!$D$837/1000 -> 835.48904 | F130: ='[2]Jun-05'!$D$848/1000 -> 14460.473 | G130: ='[2]Jun-05'!$D$849/1000 -> 640.15531 | H130: ='[2]Jun-05'!$D$862/1000 -> 7208.5368 | I130: ='[2]Jun-05'!$D$863/1000 -> 618.00682 | J130: ='[2]Jun-05'!$D$874/1000 -> 1059.2095 | K130: ='[2]Jun-05'!$D$875/1000 -> 52.78926 | L130: =+H130+(Titularizaciones!C42/1000) -> 10043.433 | M130: =+I130+((Titularizaciones!C42/1000)*Titularizaciones!M42) -> 1444.1645 | N130: =+D130+F130+H130+J130 -> 67973.845 | O130: =+E130+G130+I130+K130 -> 2146.4404 | P130: =+L130+J130+F130+D130 -> 70808.741 | Q130: =+M130+K130+G130+E130 -> 2972.5981 | R130: =+D130+F130+L130 -> 69749.531 | S130: =+E130+G130+M130 -> 2919.8088 | V130: =+D130/D118*100-100 -> 18.731072 | W130: =+E130/E118*100-100 -> -10.243252 | X130: =+F130/F118*100-100 -> 33.338302 | Y130: =+G130/G118*100-100 -> 11.203194 | Z130: =+H130/H118*100-100 -> -19.978882 | AA130: =+I130/I118*100-100 -> -60.751994 | AB130: =+J130/J118*100-100 -> 71.62619 | AC130: =+K130/K118*100-100 -> 30.842929 | ... AK130: =+S130/S118*100-100 -> -19.353203 | AN130: =+(1+V130/100)/(1+$B130/100)*100-100 -> 13.260586 | AO130: =+(1+W130/100)/(1+$B130/100)*100-100 -> -14.378758 | AP130: =+(1+X130/100)/(1+$B130/100)*100-100 -> 27.194794 | AQ130: =+(1+Y130/100)/(1+$B130/100)*100-100 -> 6.0795518 | AR130: =+(1+Z130/100)/(1+$B130/100)*100-100 -> -23.665823 | AS130: =+(1+AA130/100)/(1+$B130/100)*100-100 -> -62.56033 | AT130: =+(1+AB130/100)/(1+$B130/100)*100-100 -> 63.718582 | AU130: =+(1+AC130/100)/(1+$B130/100)*100-100 -> 24.814394 | ... BC130: =+(1+AK130/100)/(1+$B130/100)*100-100 -> -23.068972 | BF130: =+(E130/D130)*100 -> 1.8465631 | BG130: =+(G130/F130)*100 -> 4.4269319 | BH130: =+(I130/H130)*100 -> 8.5732631 | BI130: =+(K130/J130)*100 -> 4.9838354 | BJ130: =+(M130/L130)*100 -> 14.379192 | BK130: =+(O130/N130)*100 -> 3.1577446 | BL130: =+(Q130/P130)*100 -> 4.1980666 | BM130: =+(S130/R130)*100 -> 4.186134 | BN130: =+(D130/$N130)*100 -> 66.563287 | BO130: =+(E130/$O130)*100 -> 38.924399 | BP130: =+(F130/$N130)*100 -> 21.273585 | BQ130: =+(G130/$O130)*100 -> 29.824043 | BR130: =+(H130/$N130)*100 -> 10.604868 | BS130: =+(I130/$O130)*100 -> 28.792172 | BT130: =+(J130/$N130)*100 -> 1.5582604 | BU130: =+(K130/$O130)*100 -> 2.4593862 | BV130: ND | BW130: ND | BX130: =+(N130/$N130)*100 -> 100 | BY130: =+(O130/$O130)*100 -> 100 | BZ130: ND | CA130: ND
A131: 38534 | B131: =+'[1]Senda Inflación Total'!F615 -> 4.91 | C131: =+'[1]Senda Inflación Total'!D615 -> 58.21 | D131: ='[2]Jul-05'!$D$836/1000 -> 45197.471 | E131: ='[2]Jul-05'!$D$837/1000 -> 915.57274 | F131: ='[2]Jul-05'!$D$848/1000 -> 14894.256 | G131: ='[2]Jul-05'!$D$849/1000 -> 671.11069 | H131: ='[2]Jul-05'!$D$862/1000 -> 7227.1849 | I131: ='[2]Jul-05'!$D$863/1000 -> 605.96602 | J131: ='[2]Jul-05'!$D$874/1000 -> 1091.7777 | K131: ='[2]Jul-05'!$D$875/1000 -> 55.51956 | L131: =+H131+(Titularizaciones!C43/1000) -> 10008.406 | M131: =+I131+((Titularizaciones!C43/1000)*Titularizaciones!M43) -> 1416.7422 | N131: =+D131+F131+H131+J131 -> 68410.69 | O131: =+E131+G131+I131+K131 -> 2248.169 | P131: =+L131+J131+F131+D131 -> 71191.91 | Q131: =+M131+K131+G131+E131 -> 3058.9452 | R131: =+D131+F131+L131 -> 70100.133 | S131: =+E131+G131+M131 -> 3003.4256 | V131: =+D131/D119*100-100 -> 16.376895 | W131: =+E131/E119*100-100 -> -7.25643 | X131: =+F131/F119*100-100 -> 34.25951 | Y131: =+G131/G119*100-100 -> 12.786748 | Z131: =+H131/H119*100-100 -> -19.571185 | AA131: =+I131/I119*100-100 -> -61.038961 | AB131: =+J131/J119*100-100 -> 71.162904 | AC131: =+K131/K119*100-100 -> 31.017292 | ... AK131: =+S131/S119*100-100 -> -18.126837 | AN131: =+(1+V131/100)/(1+$B131/100)*100-100 -> 10.930221 | AO131: =+(1+W131/100)/(1+$B131/100)*100-100 -> -11.597017 | AP131: =+(1+X131/100)/(1+$B131/100)*100-100 -> 27.975893 | AQ131: =+(1+Y131/100)/(1+$B131/100)*100-100 -> 7.5081004 | AR131: =+(1+Z131/100)/(1+$B131/100)*100-100 -> -23.335416 | AS131: =+(1+AA131/100)/(1+$B131/100)*100-100 -> -62.862416 | AT131: =+(1+AB131/100)/(1+$B131/100)*100-100 -> 63.152134 | AU131: =+(1+AC131/100)/(1+$B131/100)*100-100 -> 24.885418 | ... BC131: =+(1+AK131/100)/(1+$B131/100)*100-100 -> -21.958666 | BF131: =+(E131/D131)*100 -> 2.0257167 | BG131: =+(G131/F131)*100 -> 4.5058357 | BH131: =+(I131/H131)*100 -> 8.3845374 | BI131: =+(K131/J131)*100 -> 5.0852441 | BJ131: =+(M131/L131)*100 -> 14.155523 | BK131: =+(O131/N131)*100 -> 3.2862832 | BL131: =+(Q131/P131)*100 -> 4.2967595 | BM131: =+(S131/R131)*100 -> 4.2844792 | BN131: =+(D131/$N131)*100 -> 66.067849 | BO131: =+(E131/$O131)*100 -> 40.725263 | BP131: =+(F131/$N131)*100 -> 21.771825 | BQ131: =+(G131/$O131)*100 -> 29.851434 | BR131: =+(H131/$N131)*100 -> 10.564409 | BS131: =+(I131/$O131)*100 -> 26.953757 | BT131: =+(J131/$N131)*100 -> 1.5959168 | BU131: =+(K131/$O131)*100 -> 2.4695457 | BV131: ND | BW131: ND | BX131: =+(N131/$N131)*100 -> 100 | BY131: =+(O131/$O131)*100 -> 100 | BZ131: ND | CA131: ND
A132: 38565 | B132: =+'[1]Senda Inflación Total'!F616 -> 4.88 | C132: =+'[1]Senda Inflación Total'!D616 -> 58.21 | D132: ='[2]Ago-05'!$D$836/1000 -> 44906.192 | E132: ='[2]Ago-05'!$D$837/1000 -> 892.5438 | F132: ='[2]Ago-05'!$D$848/1000 -> 15345.71 | G132: ='[2]Ago-05'!$D$849/1000 -> 669.04168 | H132: ='[2]Ago-05'!$D$862/1000 -> 7245.8076 | I132: ='[2]Ago-05'!$D$863/1000 -> 604.97848 | J132: ='[2]Ago-05'!$D$874/1000 -> 1128.372 | K132: ='[2]Ago-05'!$D$875/1000 -> 56.21166 | L132: =+H132+(Titularizaciones!C44/1000) -> 9959.4115 | M132: =+I132+((Titularizaciones!C44/1000)*Titularizaciones!M44) -> 1391.6107 | N132: =+D132+F132+H132+J132 -> 68626.082 | O132: =+E132+G132+I132+K132 -> 2222.7756 | P132: =+L132+J132+F132+D132 -> 71339.686 | Q132: =+M132+K132+G132+E132 -> 3009.4078 | R132: =+D132+F132+L132 -> 70211.314 | S132: =+E132+G132+M132 -> 2953.1962 | V132: =+D132/D120*100-100 -> 14.160795 | W132: =+E132/E120*100-100 -> -8.5100756 | X132: =+F132/F120*100-100 -> 35.350436 | Y132: =+G132/G120*100-100 -> 15.24304 | Z132: =+H132/H120*100-100 -> -17.223097 | AA132: =+I132/I120*100-100 -> -54.539799 | AB132: =+J132/J120*100-100 -> 70.048983 | AC132: =+K132/K120*100-100 -> 38.99568 | ... AK132: =+S132/S120*100-100 -> -24.600265 | AN132: =+(1+V132/100)/(1+$B132/100)*100-100 -> 8.8489658 | AO132: =+(1+W132/100)/(1+$B132/100)*100-100 -> -12.767044 | AP132: =+(1+X132/100)/(1+$B132/100)*100-100 -> 29.052666 | AQ132: =+(1+Y132/100)/(1+$B132/100)*100-100 -> 9.8808539 | AR132: =+(1+Z132/100)/(1+$B132/100)*100-100 -> -21.074654 | AS132: =+(1+AA132/100)/(1+$B132/100)*100-100 -> -56.655033 | AT132: =+(1+AB132/100)/(1+$B132/100)*100-100 -> 62.136712 | AU132: =+(1+AC132/100)/(1+$B132/100)*100-100 -> 32.528299 | ... BC132: =+(1+AK132/100)/(1+$B132/100)*100-100 -> -28.108567 | BF132: =+(E132/D132)*100 -> 1.987574 | BG132: =+(G132/F132)*100 -> 4.3597962 | BH132: =+(I132/H132)*100 -> 8.3493589 | BI132: =+(K132/J132)*100 -> 4.9816601 | BJ132: =+(M132/L132)*100 -> 13.972821 | BK132: =+(O132/N132)*100 -> 3.2389662 | BL132: =+(Q132/P132)*100 -> 4.2184204 | BM132: =+(S132/R132)*100 -> 4.2061543 | BN132: =+(D132/$N132)*100 -> 65.436043 | BO132: =+(E132/$O132)*100 -> 40.154471 | BP132: =+(F132/$N132)*100 -> 22.361338 | BQ132: =+(G132/$O132)*100 -> 30.09938 | BR132: =+(H132/$N132)*100 -> 10.558387 | BS132: =+(I132/$O132)*100 -> 27.217254 | BT132: =+(J132/$N132)*100 -> 1.6442321 | BU132: =+(K132/$O132)*100 -> 2.5288949 | BV132: ND | BW132: ND | BX132: =+(N132/$N132)*100 -> 100 | BY132: =+(O132/$O132)*100 -> 100 | BZ132: ND | CA132: ND
A133: 38596 | B133: =+'[1]Senda Inflación Total'!F617 -> 5.02 | C133: =+'[1]Senda Inflación Total'!D617 -> 58.46 | D133: ='[2]Sep-05'!$D$836/1000 -> 45578.619 | E133: ='[2]Sep-05'!$D$837/1000 -> 879.81386 | F133: ='[2]Sep-05'!$D$848/1000 -> 15887.504 | G133: ='[2]Sep-05'!$D$849/1000 -> 674.19751 | H133: ='[2]Sep-05'!$D$862/1000 -> 6821.9309 | I133: ='[2]Sep-05'!$D$863/1000 -> 565.69566 | J133: ='[2]Sep-05'!$D$874/1000 -> 1167.723 | K133: ='[2]Sep-05'!$D$875/1000 -> 57.80119 | L133: =+H133+(Titularizaciones!C45/1000) -> 9890.4713 | M133: =+I133+((Titularizaciones!C45/1000)*Titularizaciones!M45) -> 1328.0878 | N133: =+D133+F133+H133+J133 -> 69455.778 | O133: =+E133+G133+I133+K133 -> 2177.5082 | P133: =+L133+J133+F133+D133 -> 72524.318 | Q133: =+M133+K133+G133+E133 -> 2939.9003 | R133: =+D133+F133+L133 -> 71356.595 | S133: =+E133+G133+M133 -> 2882.0991 | V133: =+D133/D121*100-100 -> 13.837477 | W133: =+E133/E121*100-100 -> -4.6278752 | X133: =+F133/F121*100-100 -> 36.292784 | Y133: =+G133/G121*100-100 -> 10.981657 | Z133: =+H133/H121*100-100 -> -19.751994 | AA133: =+I133/I121*100-100 -> -48.036067 | AB133: =+J133/J121*100-100 -> 67.314351 | AC133: =+K133/K121*100-100 -> 40.514574 | ... AK133: =+S133/S121*100-100 -> -20.32415 | AN133: =+(1+V133/100)/(1+$B133/100)*100-100 -> 8.3959979 | AO133: =+(1+W133/100)/(1+$B133/100)*100-100 -> -9.1867027 | AP133: =+(1+X133/100)/(1+$B133/100)*100-100 -> 29.777932 | AQ133: =+(1+Y133/100)/(1+$B133/100)*100-100 -> 5.6766877 | AR133: =+(1+Z133/100)/(1+$B133/100)*100-100 -> -23.587882 | AS133: =+(1+AA133/100)/(1+$B133/100)*100-100 -> -50.519964 | AT133: =+(1+AB133/100)/(1+$B133/100)*100-100 -> 59.316655 | AU133: =+(1+AC133/100)/(1+$B133/100)*100-100 -> 33.797919 | ... BC133: =+(1+AK133/100)/(1+$B133/100)*100-100 -> -24.132689 | BF133: =+(E133/D133)*100 -> 1.9303214 | BG133: =+(G133/F133)*100 -> 4.2435709 | BH133: =+(I133/H133)*100 -> 8.2923101 | BI133: =+(K133/J133)*100 -> 4.9499059 | BJ133: =+(M133/L133)*100 -> 13.427952 | BK133: =+(O133/N133)*100 -> 3.1351002 | BL133: =+(Q133/P133)*100 -> 4.0536752 | BM133: =+(S133/R133)*100 -> 4.0390088 | BN133: =+(D133/$N133)*100 -> 65.622502 | BO133: =+(E133/$O133)*100 -> 40.404617 | BP133: =+(F133/$N133)*100 -> 22.874273 | BQ133: =+(G133/$O133)*100 -> 30.961881 | BR133: =+(H133/$N133)*100 -> 9.8219775 | BS133: =+(I133/$O133)*100 -> 25.979037 | BT133: =+(J133/$N133)*100 -> 1.6812468 | BU133: =+(K133/$O133)*100 -> 2.6544648 | BV133: ND | BW133: ND | BX133: =+(N133/$N133)*100 -> 100 | BY133: =+(O133/$O133)*100 -> 100 | BZ133: ND | CA133: ND
A134: 38626 | B134: =+'[1]Senda Inflación Total'!F618 -> 5.27 | C134: =+'[1]Senda Inflación Total'!D618 -> 58.6 | D134: ='[2]Oct-05'!$D$836/1000 -> 46202.815 | E134: ='[2]Oct-05'!$D$837/1000 -> 899.19075 | F134: ='[2]Oct-05'!$D$848/1000 -> 16331.594 | G134: ='[2]Oct-05'!$D$849/1000 -> 752.59677 | H134: ='[2]Oct-05'!$D$862/1000 -> 6836.8214 | I134: ='[2]Oct-05'!$D$863/1000 -> 555.08001 | J134: ='[2]Oct-05'!$D$874/1000 -> 1170.1108 | K134: ='[2]Oct-05'!$D$875/1000 -> 55.86451 | L134: =+H134+(Titularizaciones!C46/1000) -> 9834.1471 | M134: =+I134+((Titularizaciones!C46/1000)*Titularizaciones!M46) -> 1296.7206 | N134: =+D134+F134+H134+J134 -> 70541.341 | O134: =+E134+G134+I134+K134 -> 2262.732 | P134: =+L134+J134+F134+D134 -> 73538.667 | Q134: =+M134+K134+G134+E134 -> 3004.3726 | R134: =+D134+F134+L134 -> 72368.556 | S134: =+E134+G134+M134 -> 2948.5081 | V134: =+D134/D122*100-100 -> 14.237896 | W134: =+E134/E122*100-100 -> -1.9618826 | X134: =+F134/F122*100-100 -> 36.622856 | Y134: =+G134/G122*100-100 -> 22.78494 | Z134: =+H134/H122*100-100 -> -19.140747 | AA134: =+I134/I122*100-100 -> -48.733185 | AB134: =+J134/J122*100-100 -> 59.419549 | AC134: =+K134/K122*100-100 -> 29.288641 | ... AK134: =+S134/S122*100-100 -> -17.746441 | AN134: =+(1+V134/100)/(1+$B134/100)*100-100 -> 8.5189473 | AO134: =+(1+W134/100)/(1+$B134/100)*100-100 -> -6.869842 | AP134: =+(1+X134/100)/(1+$B134/100)*100-100 -> 29.783277 | AQ134: =+(1+Y134/100)/(1+$B134/100)*100-100 -> 16.638111 | AR134: =+(1+Z134/100)/(1+$B134/100)*100-100 -> -23.188703 | AS134: =+(1+AA134/100)/(1+$B134/100)*100-100 -> -51.299691 | AT134: =+(1+AB134/100)/(1+$B134/100)*100-100 -> 51.438728 | AU134: =+(1+AC134/100)/(1+$B134/100)*100-100 -> 22.816226 | ... BC134: =+(1+AK134/100)/(1+$B134/100)*100-100 -> -21.864198 | BF134: =+(E134/D134)*100 -> 1.9461817 | BG134: =+(G134/F134)*100 -> 4.608226 | BH134: =+(I134/H134)*100 -> 8.1189778 | BI134: =+(K134/J134)*100 -> 4.7742924 | BJ134: =+(M134/L134)*100 -> 13.185898 | BK134: =+(O134/N134)*100 -> 3.207668 | BL134: =+(Q134/P134)*100 -> 4.0854326 | BM134: =+(S134/R134)*100 -> 4.0742945 | BN134: =+(D134/$N134)*100 -> 65.4975 | BO134: =+(E134/$O134)*100 -> 39.739162 | BP134: =+(F134/$N134)*100 -> 23.151805 | BQ134: =+(G134/$O134)*100 -> 33.260534 | BR134: =+(H134/$N134)*100 -> 9.6919357 | BS134: =+(I134/$O134)*100 -> 24.531407 | BT134: =+(J134/$N134)*100 -> 1.6587589 | BU134: =+(K134/$O134)*100 -> 2.4688964 | BV134: ND | BW134: ND | BX134: =+(N134/$N134)*100 -> 100 | BY134: =+(O134/$O134)*100 -> 100 | BZ134: ND | CA134: ND
A135: 38657 | B135: =+'[1]Senda Inflación Total'!F619 -> 5.1 | C135: =+'[1]Senda Inflación Total'!D619 -> 58.66 | D135: ='[2]Nov-05'!$D$836/1000 -> 46764.942 | E135: ='[2]Nov-05'!$D$837/1000 -> 881.77797 | F135: ='[2]Nov-05'!$D$848/1000 -> 16912.904 | G135: ='[2]Nov-05'!$D$849/1000 -> 751.44731 | H135: ='[2]Nov-05'!$D$862/1000 -> 6863.7523 | I135: ='[2]Nov-05'!$D$863/1000 -> 530.04692 | J135: ='[2]Nov-05'!$D$874/1000 -> 1235.1325 | K135: ='[2]Nov-05'!$D$875/1000 -> 57.7417 | L135: =+H135+(Titularizaciones!C47/1000) -> 9794.9451 | M135: =+I135+((Titularizaciones!C47/1000)*Titularizaciones!M47) -> 1255.4055 | N135: =+D135+F135+H135+J135 -> 71776.731 | O135: =+E135+G135+I135+K135 -> 2221.0139 | P135: =+L135+J135+F135+D135 -> 74707.923 | Q135: =+M135+K135+G135+E135 -> 2946.3725 | R135: =+D135+F135+L135 -> 73472.791 | S135: =+E135+G135+M135 -> 2888.6308 | V135: =+D135/D123*100-100 -> 12.906016 | W135: =+E135/E123*100-100 -> -0.507628 | X135: =+F135/F123*100-100 -> 37.526705 | Y135: =+G135/G123*100-100 -> 22.125111 | Z135: =+H135/H123*100-100 -> -14.000153 | AA135: =+I135/I123*100-100 -> -44.625121 | AB135: =+J135/J123*100-100 -> 51.431825 | AC135: =+K135/K123*100-100 -> 19.646054 | ... AK135: =+S135/S123*100-100 -> -15.218651 | AN135: =+(1+V135/100)/(1+$B135/100)*100-100 -> 7.4272276 | AO135: =+(1+W135/100)/(1+$B135/100)*100-100 -> -5.3355167 | AP135: =+(1+X135/100)/(1+$B135/100)*100-100 -> 30.853193 | AQ135: =+(1+Y135/100)/(1+$B135/100)*100-100 -> 16.198964 | AR135: =+(1+Z135/100)/(1+$B135/100)*100-100 -> -18.173314 | AS135: =+(1+AA135/100)/(1+$B135/100)*100-100 -> -47.312199 | AT135: =+(1+AB135/100)/(1+$B135/100)*100-100 -> 44.083563 | AU135: =+(1+AC135/100)/(1+$B135/100)*100-100 -> 13.840203 | ... BC135: =+(1+AK135/100)/(1+$B135/100)*100-100 -> -19.332684 | BF135: =+(E135/D135)*100 -> 1.8855534 | BG135: =+(G135/F135)*100 -> 4.4430413 | BH135: =+(I135/H135)*100 -> 7.7224074 | BI135: =+(K135/J135)*100 -> 4.6749399 | BJ135: =+(M135/L135)*100 -> 12.816871 | BK135: =+(O135/N135)*100 -> 3.094337 | BL135: =+(Q135/P135)*100 -> 3.9438554 | BM135: =+(S135/R135)*100 -> 3.9315653 | BN135: =+(D135/$N135)*100 -> 65.153346 | BO135: =+(E135/$O135)*100 -> 39.701596 | BP135: =+(F135/$N135)*100 -> 23.563213 | BQ135: =+(G135/$O135)*100 -> 33.833526 | BR135: =+(H135/$N135)*100 -> 9.5626427 | BS135: =+(I135/$O135)*100 -> 23.865088 | BT135: =+(J135/$N135)*100 -> 1.7207979 | BU135: =+(K135/$O135)*100 -> 2.5997901 | BV135: ND | BW135: ND | BX135: =+(N135/$N135)*100 -> 100 | BY135: =+(O135/$O135)*100 -> 100 | BZ135: ND | CA135: ND
